Workbook

Sheet Dataset
A1: Question ID | D1: ID | E1: 1.Delay in delivering material to construction site | F1: 2.Monopoly of material by some suppliers | G1: 3.Prices fluctuation | H1: 4.Types of material availability at local market | I1: 5.Lack of consultant’s knowledge of available materials | J1: 6.Low productivity | K1: 7.Poor work execution | L1: 8.Shortage of laborers | M1: 9.Mistakes happens during construction phase | N1: 10.Unavailability of equipment | O1: 11.Lack of engineering experience | P1: 12.Construction cost underestimation | Q1: 13.Poor site management | R1: 14.Delayed payment for completed work | S1: 15.Cash flow problem during construction | T1: 16.High rate of interest | U1: 17.Contractor’s financial difficulties | V1: 18.Increase in salaries of skilled laborers | W1: 19.Change design | X1: 20.Errors and omission in design | Y1: 21.Incomplete design drawings and specifications at tendering stage | Z1: 22.Delay in preparation and approval of drawing | AA1: 23.Inaccurate quantity take-off | AB1: 24.Long period from planning of project to construction | AC1: 25.Delays in issuing information to the contractor during construction stage | AD1: 26.No practical use of earned value management system | AE1: 27.Lack of cost planning/monitoring during pre and post contract stage | AF1: 28.Poor communication between client, consultant and contractor | AG1: 29.Insufficient coordination between local authority who is responsible about road projects and service authorities | AH1: 30.Delays in decisions making by the approval authorities | AI1: 31.Change schedule | AJ1: 32.Stoppages because of work being rejected by consultant | AK1: 33.Lowest bid price | AL1: 34.Insufficient time for preparation of contract documents | AM1: 35.Discrepancies in contract documents | AN1: 36.Underestimation of time for completion of project | AO1: 37.Extension of time with cost claims | AP1: 38.Scope and specification changes | AQ1: 39.Changes in client requirements | AR1: 40.Frequency of variation orders and additional works | AS1: 41.Rework due to error in execution | AT1: 42.Weather conditions | AU1: 43.Accidents during construction | AV1: 44.Delay in getting NOCs from different government authorities | AW1: Type of Organization | AX1: Respondents designation | AY1: Indicate the highest formal qualification | AZ1: How often do you experience cost overrun | BA1: Location of organization | BB1: Relevant working experience
A2: 1.Delay in delivering material to construction site | D2: ID001 | E2: 1 | F2: 1 | G2: 1 | H2: 1 | I2: 1 | J2: 1 | K2: 1 | L2: 1 | M2: 1 | N2: 1 | O2: 1 | P2: 1 | Q2: 1 | R2: 1 | S2: 1 | T2: 1 | U2: 1 | V2: 1 | W2: 3 | X2: 3 | Y2: 3 | Z2: 4 | AA2: 4 | AB2: 3 | AC2: 3 | AD2: 2 | AE2: 1 | AF2: 2 | AG2: 4 | AH2: 4 | AI2: 1 | AJ2: 1 | AK2: 2 | AL2: 2 | AM2: 2 | AN2: 2 | AO2: 2 | AP2: 3 | AQ2: 3 | AR2: 3 | AS2: 1 | AT2: 2 | AU2: 2 | AV2: 3 | AW2: 1 | AX2: 2 | AY2: 2 | AZ2: 2 | BA2: 3 | BB2: 5
A3: 2.Monopoly of material by some suppliers | D3: ID002 | E3: 2 | F3: 5 | G3: 3 | H3: 2 | I3: 3 | J3: 2 | K3: 2 | L3: 2 | M3: 3 | N3: 2 | O3: 2 | P3: 2 | Q3: 2 | R3: 2 | S3: 2 | T3: 1 | U3: 4 | V3: 1 | W3: 5 | X3: 5 | Y3: 4 | Z3: 4 | AA3: 4 | AB3: 5 | AC3: 3 | AD3: 3 | AE3: 3 | AF3: 4 | AG3: 4 | AH3: 3 | AI3: 4 | AJ3: 4 | AK3: 5 | AL3: 3 | AM3: 4 | AN3: 4 | AO3: 4 | AP3: 3 | AQ3: 3 | AR3: 4 | AS3: 3 | AT3: 1 | AU3: 1 | AV3: 4 | AW3: 1 | AX3: 3 | AY3: 2 | AZ3: 3 | BA3: 3 | BB3: 3
A4: 3.Prices fluctuation | D4: ID003 | E4: 1 | F4: 2 | G4: 1 | H4: 1 | I4: 2 | J4: 2 | K4: 1 | L4: 2 | M4: 1 | N4: 1 | O4: 2 | P4: 1 | Q4: 3 | R4: 3 | S4: 3 | T4: 2 | U4: 2 | V4: 1 | W4: 2 | X4: 2 | Y4: 2 | Z4: 2 | AA4: 3 | AB4: 2 | AC4: 3 | AD4: 1 | AE4: 2 | AF4: 1 | AG4: 3 | AH4: 4 | AI4: 3 | AJ4: 1 | AK4: 2 | AL4: 2 | AM4: 2 | AN4: 2 | AO4: 4 | AP4: 2 | AQ4: 2 | AR4: 2 | AS4: 2 | AT4: 1 | AU4: 1 | AV4: 4 | AW4: 1 | AX4: 2 | AY4: 2 | AZ4: 1 | BA4: 2 | BB4: 4
A5: 4.Types of material availability at local market | D5: ID004 | E5: 2 | F5: 2 | G5: 3 | H5: 3 | I5: 2 | J5: 2 | K5: 3 | L5: 4 | M5: 4 | N5: 4 | O5: 2 | P5: 5 | Q5: 2 | R5: 2 | S5: 1 | T5: 1 | U5: 1 | V5: 1 | W5: 4 | X5: 4 | Y5: 4 | Z5: 4 | AA5: 4 | AB5: 3 | AC5: 2 | AD5: 2 | AE5: 2 | AF5: 2 | AG5: 3 | AH5: 3 | AI5: 2 | AJ5: 2 | AK5: 2 | AL5: 3 | AM5: 2 | AN5: 4 | AO5: 4 | AP5: 4 | AQ5: 4 | AR5: 4 | AS5: 3 | AT5: 4 | AU5: 3 | AV5: 3 | AW5: 1 | AX5: 3 | AY5: 1 | AZ5: 1 | BA5: 3 | BB5: 4
A6: 5.Lack of consultant’s knowledge of available materials | D6: ID005 | E6: 1 | F6: 2 | G6: 1 | H6: 1 | I6: 2 | J6: 2 | K6: 1 | L6: 2 | M6: 1 | N6: 1 | O6: 2 | P6: 1 | Q6: 2 | R6: 4 | S6: 4 | T6: 2 | U6: 2 | V6: 1 | W6: 2 | X6: 2 | Y6: 2 | Z6: 2 | AA6: 3 | AB6: 2 | AC6: 4 | AD6: 3 | AE6: 2 | AF6: 1 | AG6: 3 | AH6: 4 | AI6: 3 | AJ6: 1 | AK6: 2 | AL6: 2 | AM6: 2 | AN6: 2 | AO6: 4 | AP6: 2 | AQ6: 2 | AR6: 2 | AS6: 2 | AT6: 1 | AU6: 1 | AV6: 4 | AW6: 1 | AX6: 2 | AY6: 3 | AZ6: 1 | BA6: 2 | BB6: 4
A7: 6.Low productivity | D7: ID006 | E7: 1 | F7: 1 | G7: 1 | H7: 1 | I7: 1 | J7: 2 | K7: 2 | L7: 2 | M7: 1 | N7: 1 | O7: 1 | P7: 2 | Q7: 1 | R7: 4 | S7: 4 | T7: 4 | U7: 4 | V7: 1 | W7: 4 | X7: 4 | Y7: 4 | Z7: 4 | AA7: 4 | AB7: 4 | AC7: 2 | AD7: 2 | AE7: 2 | AF7: 1 | AG7: 1 | AH7: 3 | AI7: 3 | AJ7: 4 | AK7: 2 | AL7: 2 | AM7: 2 | AN7: 2 | AO7: 2 | AP7: 3 | AQ7: 2 | AR7: 3 | AS7: 3 | AT7: 2 | AU7: 2 | AV7: 2 | AW7: 1 | AX7: 4 | AY7: 2 | AZ7: 1 | BA7: 3 | BB7: 5
A8: 7.Poor work execution | D8: ID007 | E8: 1 | F8: 1 | G8: 1 | H8: 1 | I8: 1 | J8: 1 | K8: 1 | L8: 1 | M8: 1 | N8: 1 | O8: 1 | P8: 1 | Q8: 1 | R8: 4 | S8: 4 | T8: 4 | U8: 4 | V8: 1 | W8: 4 | X8: 4 | Y8: 4 | Z8: 4 | AA8: 4 | AB8: 4 | AC8: 2 | AD8: 2 | AE8: 2 | AF8: 1 | AG8: 2 | AH8: 4 | AI8: 3 | AJ8: 4 | AK8: 2 | AL8: 2 | AM8: 2 | AN8: 2 | AO8: 4 | AP8: 4 | AQ8: 3 | AR8: 4 | AS8: 4 | AT8: 2 | AU8: 2 | AV8: 2 | AW8: 1 | AX8: 5 | AY8: 2 | AZ8: 1 | BA8: 3 | BB8: 5
A9: 8.Shortage of laborers | D9: ID008 | E9: 1 | F9: 1 | G9: 1 | H9: 1 | I9: 1 | J9: 1 | K9: 1 | L9: 1 | M9: 1 | N9: 1 | O9: 1 | P9: 1 | Q9: 1 | R9: 3 | S9: 3 | T9: 3 | U9: 4 | V9: 4 | W9: 4 | X9: 4 | Y9: 4 | Z9: 4 | AA9: 4 | AB9: 4 | AC9: 2 | AD9: 2 | AE9: 2 | AF9: 1 | AG9: 1 | AH9: 3 | AI9: 3 | AJ9: 4 | AK9: 2 | AL9: 2 | AM9: 2 | AN9: 2 | AO9: 2 | AP9: 3 | AQ9: 2 | AR9: 3 | AS9: 3 | AT9: 2 | AU9: 2 | AV9: 2 | AW9: 1 | AX9: 4 | AY9: 2 | AZ9: 1 | BA9: 3 | BB9: 5
A10: 9.Mistakes happens during construction phase | D10: ID009 | E10: 1 | F10: 1 | G10: 1 | H10: 1 | I10: 1 | J10: 1 | K10: 1 | L10: 1 | M10: 1 | N10: 1 | O10: 1 | P10: 1 | Q10: 1 | R10: 4 | S10: 4 | T10: 4 | U10: 4 | V10: 3 | W10: 4 | X10: 4 | Y10: 4 | Z10: 4 | AA10: 4 | AB10: 4 | AC10: 2 | AD10: 2 | AE10: 2 | AF10: 1 | AG10: 2 | AH10: 4 | AI10: 3 | AJ10: 4 | AK10: 2 | AL10: 2 | AM10: 2 | AN10: 2 | AO10: 2 | AP10: 4 | AQ10: 3 | AR10: 4 | AS10: 4 | AT10: 2 | AU10: 2 | AV10: 2 | AW10: 1 | AX10: 4 | AY10: 2 | AZ10: 1 | BA10: 3 | BB10: 5
A11: 10.Unavailability of equipment | D11: ID010 | E11: 1 | F11: 1 | G11: 1 | H11: 1 | I11: 1 | J11: 1 | K11: 1 | L11: 1 | M11: 1 | N11: 1 | O11: 1 | P11: 1 | Q11: 1 | R11: 4 | S11: 4 | T11: 4 | U11: 4 | V11: 2 | W11: 4 | X11: 4 | Y11: 4 | Z11: 4 | AA11: 4 | AB11: 4 | AC11: 2 | AD11: 2 | AE11: 2 | AF11: 1 | AG11: 1 | AH11: 3 | AI11: 3 | AJ11: 4 | AK11: 2 | AL11: 2 | AM11: 2 | AN11: 2 | AO11: 2 | AP11: 3 | AQ11: 2 | AR11: 3 | AS11: 3 | AT11: 2 | AU11: 2 | AV11: 2 | AW11: 1 | AX11: 4 | AY11: 2 | AZ11: 1 | BA11: 3 | BB11: 5
A12: 11.Lack of engineering experience | D12: ID011 | E12: 2 | F12: 4 | G12: 4 | H12: 1 | I12: 1 | J12: 5 | K12: 1 | L12: 4 | M12: 5 | N12: 3 | O12: 2 | P12: 5 | Q12: 2 | R12: 1 | S12: 1 | T12: 1 | U12: 1 | V12: 3 | W12: 5 | X12: 2 | Y12: 3 | Z12: 4 | AA12: 3 | AB12: 2 | AC12: 2 | AD12: 1 | AE12: 2 | AF12: 1 | AG12: 5 | AH12: 1 | AI12: 1 | AJ12: 1 | AK12: 1 | AL12: 1 | AM12: 1 | AN12: 3 | AO12: 3 | AP12: 4 | AQ12: 4 | AR12: 4 | AS12: 1 | AT12: 1 | AU12: 1 | AV12: 1 | AW12: 1 | AX12: 5 | AY12: 3 | AZ12: 2 | BA12: 3 | BB12: 4
A13: 12.Construction cost underestimation | D13: ID012 | E13: 2 | F13: 1 | G13: 3 | H13: 4 | I13: 4 | J13: 3 | K13: 3 | L13: 4 | M13: 3 | N13: 4 | O13: 5 | P13: 4 | Q13: 3 | R13: 3 | S13: 4 | T13: 2 | U13: 4 | V13: 2 | W13: 4 | X13: 4 | Y13: 5 | Z13: 3 | AA13: 4 | AB13: 3 | AC13: 3 | AD13: 3 | AE13: 3 | AF13: 4 | AG13: 4 | AH13: 4 | AI13: 3 | AJ13: 4 | AK13: 4 | AL13: 3 | AM13: 3 | AN13: 4 | AO13: 4 | AP13: 4 | AQ13: 4 | AR13: 4 | AS13: 4 | AT13: 2 | AU13: 2 | AV13: 3 | AW13: 1 | AX13: 2 | AY13: 2 | AZ13: 1 | BA13: 3 | BB13: 5
... A44: 43.Accidents during construction | D44: ID043 | E44: 4 | F44: 5 | G44: 3 | H44: 4 | I44: 4 | J44: 4 | K44: 5 | L44: 4 | M44: 4 | N44: 4 | O44: 4 | P44: 4 | Q44: 4 | R44: 5 | S44: 5 | T44: 5 | U44: 4 | V44: 3 | W44: 5 | X44: 4 | Y44: 4 | Z44: 4 | AA44: 4 | AB44: 3 | AC44: 4 | AD44: 3 | AE44: 4 | AF44: 4 | AG44: 4 | AH44: 4 | AI44: 4 | AJ44: 4 | AK44: 1 | AL44: 2 | AM44: 3 | AN44: 4 | AO44: 5 | AP44: 4 | AQ44: 5 | AR44: 4 | AS44: 4 | AT44: 3 | AU44: 3 | AV44: 5 | AW44: 1 | AX44: 3 | AY44: 3 | AZ44: 1 | BA44: 2 | BB44: 4
A45: 44.Delay in getting NOCs from different government authorities | D45: ID044 | E45: 4 | F45: 5 | G45: 3 | H45: 4 | I45: 4 | J45: 4 | K45: 5 | L45: 4 | M45: 4 | N45: 5 | O45: 4 | P45: 4 | Q45: 4 | R45: 5 | S45: 5 | T45: 5 | U45: 4 | V45: 3 | W45: 5 | X45: 4 | Y45: 4 | Z45: 4 | AA45: 4 | AB45: 3 | AC45: 4 | AD45: 3 | AE45: 4 | AF45: 3 | AG45: 3 | AH45: 4 | AI45: 4 | AJ45: 4 | AL45: 5 | AM45: 4 | AN45: 3 | AO45: 4 | AP45: 5 | AQ45: 4 | AR45: 5 | AS45: 3 | AT45: 2 | AU45: 2 | AV45: 5 | AW45: 1 | AX45: 3 | AY45: 2 | AZ45: 1 | BA45: 1 | BB45: 4
A46: Type of Organization | D46: ID045 | E46: 4 | F46: 5 | G46: 3 | H46: 4 | I46: 4 | J46: 4 | K46: 5 | L46: 4 | M46: 4 | N46: 5 | O46: 4 | P46: 4 | Q46: 4 | R46: 5 | S46: 5 | T46: 5 | U46: 4 | V46: 3 | W46: 5 | X46: 4 | Y46: 4 | Z46: 4 | AA46: 4 | AB46: 3 | AC46: 4 | AD46: 3 | AE46: 4 | AF46: 3 | AG46: 3 | AH46: 4 | AI46: 4 | AJ46: 4 | AK46: 5 | AL46: 4 | AM46: 3 | AN46: 4 | AO46: 5 | AP46: 4 | AQ46: 5 | AR46: 4 | AS46: 4 | AT46: 3 | AU46: 3 | AV46: 5 | AW46: 2 | AX46: 3 | AY46: 3 | AZ46: 1 | BA46: 1 | BB46: 4
A47: Respondents designation | D47: ID046 | E47: 4 | F47: 5 | G47: 3 | H47: 4 | I47: 4 | J47: 4 | K47: 5 | L47: 4 | M47: 4 | N47: 5 | O47: 4 | P47: 4 | Q47: 4 | R47: 5 | S47: 5 | T47: 5 | U47: 4 | V47: 3 | W47: 5 | X47: 4 | Y47: 4 | Z47: 4 | AA47: 4 | AB47: 3 | AC47: 4 | AD47: 3 | AE47: 4 | AF47: 4 | AG47: 4 | AH47: 5 | AI47: 4 | AJ47: 4 | AK47: 5 | AL47: 4 | AM47: 3 | AN47: 4 | AO47: 5 | AP47: 4 | AQ47: 5 | AR47: 4 | AS47: 4 | AT47: 3 | AU47: 3 | AV47: 5 | AW47: 2 | AX47: 2 | AY47: 3 | AZ47: 1 | BA47: 3 | BB47: 4
A48: Indicate the highest formal qualification | D48: ID047 | E48: 4 | F48: 3 | G48: 3 | H48: 3 | I48: 3 | J48: 5 | K48: 5 | L48: 5 | M48: 5 | N48: 5 | O48: 4 | P48: 4 | Q48: 4 | R48: 4 | S48: 4 | T48: 3 | U48: 3 | V48: 3 | W48: 3 | X48: 2 | Y48: 2 | Z48: 4 | AA48: 3 | AB48: 2 | AC48: 3 | AD48: 4 | AE48: 4 | AF48: 5 | AG48: 5 | AH48: 5 | AI48: 4 | AJ48: 4 | AK48: 3 | AL48: 4 | AM48: 4 | AN48: 5 | AO48: 4 | AP48: 5 | AQ48: 3 | AR48: 3 | AS48: 4 | AT48: 3 | AU48: 2 | AV48: 4 | AW48: 2 | AX48: 2 | AY48: 2 | AZ48: 2 | BA48: 3 | BB48: 4
A49: How often do you experience cost overrun | D49: ID048 | E49: 1 | F49: 1 | G49: 2 | H49: 2 | I49: 2 | J49: 4 | K49: 4 | L49: 3 | M49: 4 | N49: 4 | O49: 5 | P49: 5 | Q49: 5 | R49: 5 | S49: 5 | T49: 5 | U49: 4 | V49: 3 | W49: 3 | X49: 4 | Y49: 3 | Z49: 4 | AA49: 4 | AB49: 4 | AC49: 3 | AD49: 2 | AE49: 4 | AF49: 5 | AG49: 5 | AH49: 5 | AI49: 3 | AJ49: 2 | AK49: 4 | AL49: 5 | AM49: 5 | AN49: 4 | AO49: 5 | AP49: 5 | AQ49: 5 | AR49: 4 | AS49: 5 | AT49: 3 | AU49: 5 | AV49: 4 | AW49: 2 | AX49: 5 | AY49: 2 | AZ49: 1 | BA49: 1 | BB49: 5
A50: Location of organization | D50: ID049 | E50: 4 | F50: 2 | G50: 4 | H50: 4 | I50: 3 | J50: 4 | K50: 5 | L50: 3 | M50: 5 | N50: 3 | O50: 5 | P50: 5 | Q50: 5 | R50: 4 | S50: 4 | T50: 3 | U50: 2 | V50: 2 | W50: 4 | X50: 5 | Y50: 4 | Z50: 4 | AA50: 4 | AB50: 4 | AC50: 3 | AD50: 3 | AE50: 4 | AF50: 4 | AG50: 5 | AH50: 5 | AI50: 3 | AJ50: 3 | AK50: 4 | AL50: 3 | AM50: 4 | AN50: 4 | AO50: 3 | AP50: 4 | AQ50: 4 | AR50: 4 | AS50: 4 | AT50: 3 | AU50: 3 | AV50: 3 | AW50: 2 | AX50: 5 | AY50: 3 | AZ50: 2 | BA50: 3 | BB50: 3
A51: Relevant working experience | D51: ID050 | E51: 5 | F51: 4 | G51: 4 | H51: 5 | I51: 2 | J51: 5 | K51: 5 | L51: 5 | M51: 4 | N51: 4 | O51: 4 | P51: 4 | Q51: 5 | R51: 3 | S51: 5 | T51: 4 | U51: 5 | V51: 3 | W51: 4 | X51: 4 | Y51: 4 | Z51: 4 | AA51: 4 | AB51: 4 | AC51: 5 | AD51: 4 | AE51: 5 | AF51: 5 | AG51: 4 | AH51: 5 | AI51: 5 | AJ51: 4 | AK51: 4 | AL51: 5 | AM51: 4 | AN51: 4 | AO51: 4 | AP51: 5 | AQ51: 4 | AR51: 5 | AS51: 4 | AT51: 4 | AU51: 4 | AV51: 4 | AW51: 2 | AX51: 5 | AY51: 3 | AZ51: 1 | BA51: 1 | BB51: 4
D52: ID051 | E52: 4 | F52: 2 | G52: 4 | H52: 3 | I52: 3 | J52: 4 | K52: 4 | L52: 3 | M52: 4 | N52: 3 | O52: 3 | P52: 5 | Q52: 4 | R52: 2 | S52: 2 | T52: 3 | U52: 3 | V52: 3 | W52: 4 | X52: 3 | Y52: 2 | Z52: 3 | AA52: 4 | AB52: 4 | AC52: 3 | AD52: 3 | AE52: 3 | AF52: 2 | AG52: 2 | AH52: 3 | AI52: 4 | AJ52: 4 | AK52: 4 | AL52: 3 | AM52: 3 | AN52: 4 | AO52: 3 | AP52: 4 | AQ52: 4 | AR52: 3 | AS52: 4 | AT52: 3 | AU52: 3 | AV52: 2 | AW52: 2 | AX52: 5 | AY52: 2 | AZ52: 1 | BA52: 3 | BB52: 4
D53: ID052 | E53: 5 | F53: 4 | G53: 4 | H53: 5 | I53: 2 | J53: 5 | K53: 5 | L53: 5 | M53: 4 | N53: 4 | O53: 4 | P53: 4 | Q53: 5 | R53: 4 | S53: 5 | T53: 4 | U53: 5 | V53: 3 | W53: 4 | X53: 4 | Y53: 4 | Z53: 4 | AA53: 4 | AB53: 4 | AC53: 5 | AD53: 4 | AE53: 5 | AF53: 5 | AG53: 4 | AH53: 5 | AI53: 5 | AJ53: 4 | AK53: 4 | AL53: 5 | AM53: 4 | AN53: 4 | AO53: 4 | AP53: 4 | AQ53: 5 | AR53: 4 | AS53: 5 | AT53: 4 | AU53: 4 | AV53: 4 | AW53: 2 | AX53: 4 | AY53: 2 | AZ53: 1 | BA53: 3 | BB53: 3
D54: ID053 | E54: 5 | F54: 4 | G54: 1 | H54: 3 | I54: 1 | J54: 4 | K54: 4 | L54: 4 | M54: 4 | N54: 4 | O54: 4 | P54: 3 | Q54: 3 | R54: 3 | S54: 3 | T54: 2 | U54: 4 | V54: 2 | W54: 3 | X54: 3 | Y54: 1 | Z54: 2 | AA54: 3 | AB54: 4 | AC54: 3 | AD54: 2 | AE54: 3 | AF54: 3 | AG54: 4 | AH54: 5 | AI54: 1 | AJ54: 2 | AK54: 3 | AL54: 2 | AM54: 3 | AN54: 5 | AO54: 4 | AP54: 2 | AQ54: 3 | AR54: 3 | AS54: 3 | AT54: 2 | AU54: 2 | AV54: 4 | AW54: 2 | AX54: 3 | AY54: 2 | AZ54: 2 | BA54: 3 | BB54: 5
D55: ID054 | E55: 4 | F55: 5 | G55: 3 | H55: 4 | I55: 4 | J55: 4 | K55: 5 | L55: 4 | M55: 4 | N55: 5 | O55: 4 | P55: 4 | Q55: 4 | R55: 5 | S55: 5 | T55: 5 | U55: 4 | V55: 3 | W55: 5 | X55: 4 | Y55: 4 | Z55: 4 | AA55: 4 | AB55: 3 | AC55: 4 | AD55: 3 | AE55: 4 | AF55: 4 | AG55: 4 | AH55: 5 | AI55: 4 | AJ55: 4 | AK55: 5 | AL55: 4 | AM55: 3 | AN55: 4 | AO55: 5 | AP55: 4 | AQ55: 5 | AR55: 4 | AS55: 4 | AT55: 3 | AU55: 3 | AV55: 5 | AW55: 2 | AX55: 2 | AY55: 3 | AZ55: 1 | BA55: 3 | BB55: 4
D56: ID055 | E56: 2 | F56: 3 | G56: 4 | H56: 2 | I56: 4 | J56: 3 | K56: 2 | L56: 3 | M56: 4 | N56: 3 | O56: 4 | P56: 5 | Q56: 5 | R56: 3 | S56: 5 | T56: 4 | U56: 5 | V56: 4 | W56: 5 | X56: 4 | Y56: 5 | Z56: 3 | AA56: 5 | AB56: 5 | AC56: 3 | AD56: 4 | AE56: 4 | AF56: 3 | AG56: 3 | AH56: 4 | AI56: 3 | AJ56: 3 | AK56: 3 | AL56: 4 | AM56: 3 | AN56: 4 | AO56: 4 | AP56: 4 | AQ56: 5 | AR56: 4 | AS56: 4 | AT56: 3 | AU56: 3 | AV56: 3 | AW56: 2 | AX56: 3 | AY56: 2 | AZ56: 1 | BA56: 3 | BB56: 5
D57: ID056 | E57: 1 | F57: 1 | G57: 1 | H57: 1 | I57: 1 | J57: 5 | K57: 5 | L57: 3 | M57: 2 | N57: 5 | O57: 5 | P57: 5 | Q57: 4 | R57: 5 | S57: 5 | T57: 5 | U57: 5 | V57: 3 | W57: 5 | X57: 4 | Y57: 4 | Z57: 3 | AA57: 1 | AB57: 1 | AC57: 2 | AD57: 2 | AE57: 5 | AF57: 5 | AG57: 5 | AH57: 5 | AI57: 2 | AJ57: 2 | AK57: 3 | AL57: 5 | AM57: 4 | AN57: 5 | AO57: 3 | AP57: 4 | AQ57: 5 | AR57: 4 | AS57: 5 | AT57: 2 | AU57: 1 | AV57: 5 | AW57: 2 | AX57: 3 | AY57: 2 | AZ57: 1 | BA57: 1 | BB57: 5
D58: ID057 | E58: 1 | F58: 1 | G58: 4 | H58: 3 | I58: 4 | J58: 4 | K58: 4 | L58: 4 | M58: 5 | N58: 3 | O58: 3 | P58: 5 | Q58: 5 | R58: 4 | S58: 2 | T58: 3 | U58: 2 | V58: 5 | W58: 5 | X58: 4 | Y58: 3 | Z58: 5 | AA58: 5 | AB58: 4 | AC58: 4 | AD58: 3 | AE58: 4 | AF58: 4 | AG58: 3 | AH58: 5 | AI58: 5 | AJ58: 3 | AK58: 3 | AL58: 2 | AM58: 2 | AN58: 5 | AO58: 3 | AP58: 4 | AQ58: 5 | AR58: 4 | AS58: 3 | AT58: 2 | AU58: 2 | AV58: 4 | AW58: 2 | AX58: 5 | AY58: 2 | AZ58: 1 | BA58: 3 | BB58: 4
D59: ID058 | E59: 1 | F59: 1 | G59: 4 | H59: 3 | I59: 4 | J59: 4 | K59: 4 | L59: 4 | M59: 5 | N59: 3 | O59: 3 | P59: 5 | Q59: 5 | R59: 3 | S59: 2 | T59: 4 | U59: 2 | V59: 5 | W59: 5 | X59: 4 | Y59: 3 | Z59: 5 | AA59: 5 | AB59: 3 | AC59: 3 | AD59: 5 | AE59: 3 | AF59: 4 | AG59: 4 | AH59: 5 | AI59: 5 | AJ59: 3 | AK59: 3 | AL59: 4 | AM59: 4 | AN59: 3 | AO59: 1 | AP59: 4 | AQ59: 5 | AR59: 4 | AS59: 3 | AT59: 2 | AU59: 2 | AV59: 4 | AW59: 2 | AX59: 5 | AY59: 2 | AZ59: 1 | BA59: 3 | BB59: 4
D60: ID059 | E60: 1 | F60: 1 | G60: 4 | H60: 3 | I60: 4 | J60: 4 | K60: 4 | L60: 4 | M60: 5 | N60: 3 | O60: 3 | P60: 5 | Q60: 5 | R60: 3 | S60: 2 | T60: 4 | U60: 2 | V60: 5 | W60: 5 | X60: 4 | Y60: 3 | Z60: 5 | AA60: 5 | AB60: 3 | AC60: 3 | AD60: 5 | AE60: 3 | AF60: 4 | AG60: 4 | AH60: 5 | AI60: 5 | AJ60: 3 | AK60: 3 | AL60: 4 | AM60: 4 | AN60: 5 | AO60: 3 | AP60: 4 | AQ60: 5 | AR60: 4 | AS60: 3 | AT60: 2 | AU60: 2 | AV60: 4 | AW60: 2 | AX60: 5 | AY60: 2 | AZ60: 1 | BA60: 1 | BB60: 4
D61: ID060 | E61: 4 | F61: 5 | G61: 3 | H61: 4 | I61: 4 | J61: 4 | K61: 5 | L61: 4 | M61: 4 | N61: 5 | O61: 4 | P61: 4 | Q61: 4 | R61: 5 | S61: 5 | T61: 5 | U61: 4 | V61: 3 | W61: 5 | X61: 4 | Y61: 4 | Z61: 4 | AA61: 4 | AB61: 3 | AC61: 4 | AD61: 3 | AE61: 4 | AF61: 3 | AG61: 3 | AH61: 4 | AI61: 4 | AJ61: 4 | AK61: 5 | AL61: 4 | AM61: 3 | AN61: 4 | AO61: 5 | AP61: 4 | AQ61: 5 | AR61: 4 | AS61: 4 | AT61: 3 | AU61: 3 | AV61: 5 | AW61: 2 | AX61: 3 | AY61: 3 | AZ61: 1 | BA61: 1 | BB61: 4
D62: ID061 | E62: 4 | F62: 5 | G62: 3 | H62: 4 | I62: 4 | J62: 4 | K62: 5 | L62: 4 | M62: 4 | N62: 5 | O62: 4 | P62: 4 | Q62: 4 | R62: 5 | S62: 5 | T62: 5 | U62: 4 | V62: 3 | W62: 5 | X62: 4 | Y62: 4 | Z62: 4 | AA62: 4 | AB62: 3 | AC62: 4 | AD62: 3 | AE62: 4 | AF62: 3 | AG62: 3 | AH62: 4 | AI62: 4 | AJ62: 4 | AK62: 5 | AL62: 4 | AM62: 3 | AN62: 4 | AO62: 5 | AP62: 4 | AQ62: 5 | AR62: 4 | AS62: 4 | AT62: 3 | AU62: 3 | AV62: 5 | AW62: 2 | AX62: 3 | AY62: 2 | AZ62: 1 | BA62: 2 | BB62: 4
D63: ID062 | E63: 5 | F63: 4 | G63: 1 | H63: 3 | I63: 1 | J63: 4 | K63: 4 | L63: 4 | M63: 4 | N63: 4 | O63: 4 | P63: 3 | Q63: 3 | R63: 3 | S63: 3 | T63: 2 | U63: 4 | V63: 2 | W63: 3 | X63: 3 | Y63: 1 | Z63: 2 | AA63: 3 | AB63: 4 | AC63: 3 | AD63: 2 | AE63: 3 | AF63: 3 | AG63: 4 | AH63: 5 | AI63: 1 | AJ63: 2 | AK63: 3 | AL63: 2 | AM63: 3 | AN63: 5 | AO63: 4 | AP63: 2 | AQ63: 3 | AR63: 3 | AS63: 3 | AT63: 2 | AU63: 2 | AV63: 4 | AW63: 2 | AX63: 5 | AY63: 2 | AZ63: 2 | BA63: 1 | BB63: 5
... D72: ID071 | E72: 4 | F72: 4 | G72: 3 | H72: 4 | I72: 4 | J72: 4 | K72: 4 | L72: 4 | M72: 4 | N72: 4 | O72: 4 | P72: 4 | Q72: 4 | R72: 4 | S72: 4 | T72: 4 | U72: 4 | V72: 4 | W72: 4 | X72: 4 | Y72: 4 | Z72: 4 | AA72: 4 | AB72: 3 | AC72: 3 | AD72: 3 | AE72: 4 | AF72: 5 | AG72: 4 | AH72: 5 | AI72: 3 | AJ72: 4 | AK72: 4 | AL72: 5 | AM72: 4 | AN72: 4 | AO72: 4 | AP72: 4 | AQ72: 4 | AR72: 5 | AS72: 5 | AT72: 4 | AU72: 4 | AV72: 5 | AW72: 2 | AX72: 2 | AY72: 3 | AZ72: 2 | BA72: 1 | BB72: 5
D73: ID072 | E73: 3 | F73: 3 | G73: 3 | H73: 3 | I73: 3 | J73: 3 | K73: 2 | L73: 3 | M73: 2 | N73: 3 | O73: 3 | P73: 3 | Q73: 4 | R73: 4 | S73: 4 | T73: 4 | U73: 5 | V73: 4 | X73: 2 | Y73: 2 | Z73: 3 | AA73: 3 | AB73: 2 | AC73: 3 | AD73: 3 | AE73: 4 | AF73: 3 | AG73: 3 | AH73: 4 | AI73: 3 | AJ73: 3 | AK73: 3 | AL73: 2 | AM73: 2 | AN73: 4 | AO73: 5 | AP73: 4 | AQ73: 5 | AR73: 5 | AS73: 2 | AT73: 2 | AU73: 2 | AV73: 4 | AW73: 2 | AX73: 2 | AY73: 3 | AZ73: 2 | BA73: 3 | BB73: 5
D74: ID073 | E74: 1 | F74: 1 | G74: 5 | H74: 1 | I74: 1 | J74: 5 | K74: 5 | L74: 5 | M74: 5 | N74: 5 | O74: 5 | P74: 5 | Q74: 5 | R74: 4 | S74: 4 | T74: 4 | U74: 4 | V74: 4 | W74: 5 | X74: 5 | Y74: 5 | Z74: 5 | AA74: 5 | AB74: 5 | AC74: 5 | AD74: 3 | AE74: 3 | AF74: 3 | AG74: 5 | AH74: 5 | AI74: 3 | AJ74: 3 | AK74: 1 | AL74: 1 | AM74: 1 | AN74: 1 | AO74: 1 | AP74: 5 | AQ74: 5 | AR74: 5 | AS74: 5 | AT74: 1 | AU74: 1 | AV74: 1 | AW74: 2 | AX74: 4 | AY74: 3 | AZ74: 2 | BA74: 3 | BB74: 4
D75: ID074 | E75: 4 | F75: 4 | G75: 1 | H75: 3 | I75: 3 | J75: 4 | K75: 4 | L75: 5 | M75: 4 | N75: 5 | O75: 3 | P75: 5 | Q75: 5 | R75: 3 | S75: 5 | T75: 3 | U75: 4 | V75: 2 | W75: 5 | X75: 5 | Y75: 4 | Z75: 5 | AA75: 4 | AB75: 3 | AC75: 5 | AD75: 3 | AE75: 5 | AF75: 3 | AG75: 4 | AH75: 4 | AI75: 3 | AJ75: 4 | AK75: 5 | AL75: 5 | AM75: 5 | AN75: 3 | AO75: 2 | AP75: 5 | AQ75: 5 | AR75: 5 | AS75: 4 | AT75: 3 | AU75: 3 | AV75: 4 | AW75: 2 | AX75: 4 | AY75: 3 | AZ75: 2 | BA75: 1 | BB75: 4
D76: ID075 | E76: 4 | F76: 4 | G76: 1 | H76: 3 | I76: 3 | J76: 4 | K76: 4 | L76: 3 | M76: 4 | N76: 5 | O76: 3 | P76: 5 | Q76: 5 | R76: 3 | S76: 4 | T76: 2 | U76: 4 | V76: 2 | W76: 3 | X76: 3 | Y76: 4 | Z76: 5 | AA76: 4 | AB76: 3 | AC76: 5 | AD76: 3 | AE76: 5 | AF76: 4 | AG76: 4 | AH76: 4 | AI76: 4 | AJ76: 5 | AK76: 2 | AL76: 2 | AM76: 2 | AN76: 5 | AO76: 3 | AP76: 4 | AQ76: 4 | AR76: 4 | AS76: 4 | AT76: 3 | AU76: 3 | AV76: 4 | AW76: 2 | AX76: 5 | AY76: 2 | AZ76: 2 | BA76: 3 | BB76: 4
D77: ID076 | E77: 3 | F77: 1 | G77: 1 | H77: 2 | I77: 1 | J77: 1 | K77: 1 | L77: 3 | M77: 1 | N77: 5 | O77: 1 | P77: 3 | Q77: 1 | R77: 5 | S77: 4 | T77: 2 | U77: 5 | V77: 5 | W77: 1 | X77: 1 | Y77: 3 | Z77: 5 | AA77: 3 | AB77: 3 | AC77: 2 | AD77: 3 | AE77: 3 | AF77: 5 | AG77: 5 | AH77: 5 | AI77: 5 | AJ77: 2 | AK77: 5 | AL77: 2 | AM77: 2 | AN77: 1 | AO77: 4 | AP77: 5 | AQ77: 5 | AR77: 5 | AS77: 1 | AT77: 2 | AU77: 2 | AV77: 5 | AW77: 2 | AX77: 2 | AY77: 3 | AZ77: 2 | BA77: 1 | BB77: 3
D78: ID077 | E78: 5 | F78: 3 | G78: 3 | H78: 3 | I78: 2 | J78: 5 | K78: 4 | L78: 4 | M78: 4 | N78: 4 | O78: 4 | P78: 5 | Q78: 4 | R78: 3 | S78: 3 | T78: 2 | U78: 3 | V78: 1 | W78: 5 | X78: 5 | Y78: 5 | Z78: 5 | AA78: 5 | AB78: 5 | AC78: 5 | AD78: 4 | AE78: 5 | AF78: 4 | AG78: 4 | AH78: 5 | AI78: 5 | AJ78: 4 | AK78: 5 | AL78: 5 | AM78: 5 | AN78: 5 | AO78: 4 | AP78: 5 | AQ78: 5 | AR78: 5 | AS78: 5 | AT78: 3 | AU78: 3 | AV78: 4 | AW78: 2 | AX78: 4 | AY78: 2 | AZ78: 2 | BA78: 2 | BB78: 3
D79: ID078 | E79: 5 | F79: 3 | G79: 2 | H79: 3 | I79: 5 | J79: 3 | K79: 3 | L79: 3 | M79: 4 | N79: 4 | O79: 5 | P79: 4 | Q79: 5 | R79: 4 | S79: 3 | T79: 3 | U79: 3 | V79: 4 | W79: 5 | X79: 5 | Y79: 5 | Z79: 4 | AA79: 5 | AB79: 5 | AC79: 4 | AD79: 4 | AE79: 4 | AF79: 4 | AG79: 4 | AH79: 5 | AI79: 4 | AJ79: 3 | AK79: 3 | AL79: 3 | AM79: 5 | AN79: 5 | AO79: 5 | AP79: 4 | AQ79: 4 | AR79: 4 | AS79: 5 | AT79: 3 | AU79: 3 | AV79: 5 | AW79: 2 | AX79: 5 | AY79: 3 | AZ79: 2 | BA79: 2 | BB79: 5
D80: ID079 | E80: 2 | F80: 2 | G80: 2 | H80: 2 | I80: 1 | J80: 3 | K80: 3 | L80: 1 | M80: 1 | N80: 1 | O80: 1 | P80: 2 | Q80: 3 | R80: 3 | S80: 3 | T80: 1 | U80: 3 | V80: 1 | W80: 2 | X80: 1 | Y80: 2 | Z80: 3 | AA80: 3 | AB80: 4 | AC80: 2 | AD80: 1 | AE80: 2 | AF80: 1 | AG80: 3 | AH80: 4 | AI80: 2 | AJ80: 1 | AK80: 2 | AL80: 1 | AM80: 2 | AN80: 3 | AO80: 3 | AP80: 5 | AQ80: 5 | AR80: 4 | AS80: 4 | AT80: 1 | AU80: 2 | AV80: 3 | AW80: 2 | AX80: 4 | AY80: 2 | AZ80: 2 | BA80: 1 | BB80: 5
D81: ID080 | E81: 3 | F81: 4 | G81: 2 | H81: 2 | I81: 3 | J81: 4 | K81: 4 | L81: 4 | M81: 5 | N81: 3 | O81: 5 | P81: 4 | Q81: 5 | R81: 5 | S81: 5 | T81: 3 | U81: 2 | V81: 2 | W81: 4 | X81: 4 | Y81: 4 | Z81: 4 | AA81: 4 | AB81: 3 | AC81: 4 | AD81: 3 | AE81: 4 | AF81: 5 | AG81: 5 | AH81: 5 | AI81: 4 | AJ81: 3 | AK81: 3 | AL81: 3 | AM81: 3 | AN81: 3 | AO81: 3 | AP81: 3 | AQ81: 4 | AR81: 5 | AS81: 3 | AT81: 2 | AU81: 3 | AV81: 4 | AW81: 2 | AX81: 2 | AY81: 2 | AZ81: 1 | BA81: 1 | BB81: 5
D82: ID081 | E82: 2 | F82: 2 | G82: 3 | H82: 4 | I82: 5 | J82: 5 | K82: 5 | L82: 4 | M82: 5 | N82: 5 | O82: 4 | P82: 4 | Q82: 5 | R82: 4 | S82: 4 | T82: 4 | U82: 4 | V82: 3 | W82: 3 | X82: 4 | Y82: 4 | Z82: 2 | AA82: 4 | AB82: 4 | AC82: 4 | AD82: 4 | AE82: 5 | AF82: 5 | AG82: 5 | AH82: 4 | AI82: 5 | AJ82: 5 | AK82: 5 | AL82: 4 | AM82: 4 | AN82: 4 | AO82: 4 | AP82: 5 | AQ82: 5 | AR82: 4 | AS82: 4 | AT82: 2 | AU82: 2 | AV82: 3 | AW82: 2 | AX82: 1 | AY82: 3 | AZ82: 2 | BA82: 1 | BB82: 5
D83: ID082 | E83: 4 | F83: 1 | G83: 2 | H83: 3 | I83: 4 | J83: 5 | K83: 5 | L83: 5 | M83: 3 | N83: 3 | O83: 4 | P83: 5 | Q83: 5 | R83: 4 | S83: 1 | T83: 1 | U83: 1 | V83: 3 | W83: 5 | X83: 4 | Y83: 5 | Z83: 3 | AA83: 1 | AB83: 1 | AC83: 3 | AD83: 2 | AE83: 3 | AF83: 4 | AG83: 4 | AH83: 4 | AI83: 4 | AJ83: 4 | AK83: 4 | AL83: 3 | AM83: 2 | AN83: 1 | AO83: 1 | AP83: 5 | AQ83: 5 | AR83: 5 | AS83: 2 | AT83: 1 | AU83: 1 | AV83: 3 | AW83: 2 | AX83: 4 | AY83: 2 | AZ83: 2 | BA83: 1 | BB83: 5
D84: ID083 | E84: 4 | F84: 5 | G84: 3 | H84: 4 | I84: 4 | J84: 4 | K84: 4 | L84: 4 | M84: 4 | N84: 4 | O84: 4 | P84: 4 | Q84: 4 | R84: 5 | S84: 5 | T84: 5 | U84: 5 | V84: 3 | W84: 5 | X84: 5 | Y84: 4 | Z84: 4 | AA84: 5 | AB84: 4 | AC84: 5 | AD84: 3 | AE84: 4 | AF84: 4 | AG84: 4 | AH84: 4 | AI84: 5 | AJ84: 5 | AK84: 4 | AL84: 4 | AM84: 3 | AN84: 4 | AO84: 5 | AP84: 4 | AQ84: 4 | AR84: 4 | AS84: 2 | AT84: 4 | AU84: 3 | AV84: 3 | AW84: 2 | AX84: 2 | AY84: 2 | AZ84: 1 | BA84: 3 | BB84: 5
D85: ID084 | E85: 3 | F85: 4 | G85: 4 | H85: 3 | I85: 2 | J85: 4 | K85: 4 | L85: 4 | M85: 4 | N85: 4 | O85: 3 | P85: 3 | Q85: 3 | R85: 3 | S85: 2 | T85: 1 | U85: 4 | V85: 1 | W85: 4 | X85: 2 | Y85: 3 | Z85: 3 | AA85: 1 | AB85: 4 | AC85: 1 | AD85: 2 | AE85: 4 | AF85: 3 | AG85: 3 | AH85: 4 | AI85: 3 | AJ85: 1 | AK85: 3 | AL85: 3 | AM85: 4 | AN85: 4 | AO85: 4 | AP85: 4 | AQ85: 5 | AR85: 4 | AS85: 3 | AT85: 2 | AU85: 2 | AV85: 4 | AW85: 2 | AX85: 2 | AY85: 3 | AZ85: 1 | BA85: 3 | BB85: 4
... D115: ID114 | E115: 4 | F115: 5 | G115: 3 | H115: 3 | I115: 3 | J115: 4 | K115: 4 | L115: 5 | M115: 3 | N115: 2 | O115: 4 | P115: 5 | Q115: 5 | R115: 4 | S115: 1 | T115: 2 | U115: 1 | V115: 3 | W115: 4 | X115: 2 | Y115: 2 | Z115: 2 | AA115: 1 | AB115: 3 | AC115: 2 | AD115: 1 | AE115: 1 | AF115: 1 | AG115: 2 | AH115: 4 | AI115: 2 | AJ115: 3 | AK115: 5 | AL115: 2 | AM115: 2 | AN115: 4 | AO115: 4 | AP115: 4 | AQ115: 4 | AR115: 4 | AS115: 3 | AT115: 2 | AU115: 5 | AV115: 5 | AW115: 3 | AX115: 2 | AY115: 2 | AZ115: 1 | BA115: 2 | BB115: 2
D116: ID115 | E116: 3 | F116: 3 | G116: 3 | H116: 3 | I116: 3 | J116: 3 | K116: 2 | L116: 3 | M116: 2 | N116: 3 | O116: 3 | P116: 3 | Q116: 4 | R116: 4 | S116: 4 | T116: 4 | U116: 5 | V116: 4 | X116: 2 | Y116: 2 | Z116: 3 | AA116: 3 | AB116: 2 | AC116: 3 | AD116: 3 | AE116: 4 | AF116: 3 | AG116: 3 | AH116: 4 | AI116: 3 | AJ116: 3 | AK116: 3 | AL116: 2 | AM116: 2 | AN116: 4 | AO116: 5 | AP116: 4 | AQ116: 5 | AR116: 5 | AS116: 2 | AT116: 2 | AU116: 2 | AV116: 4 | AW116: 3 | AX116: 2 | AY116: 3 | AZ116: 2 | BA116: 3 | BB116: 5
D117: ID116 | E117: 4 | F117: 4 | G117: 4 | H117: 4 | I117: 3 | J117: 4 | K117: 4 | L117: 4 | M117: 3 | N117: 4 | O117: 4 | P117: 4 | Q117: 4 | R117: 4 | S117: 4 | T117: 3 | U117: 3 | V117: 3 | W117: 5 | X117: 5 | Y117: 5 | Z117: 3 | AA117: 3 | AB117: 3 | AC117: 4 | AD117: 3 | AE117: 4 | AF117: 4 | AG117: 4 | AH117: 4 | AI117: 4 | AJ117: 4 | AK117: 3 | AL117: 3 | AM117: 3 | AN117: 3 | AO117: 3 | AP117: 4 | AQ117: 3 | AR117: 3 | AS117: 3 | AT117: 4 | AU117: 4 | AV117: 5 | AW117: 3 | AX117: 5 | AY117: 2 | AZ117: 1 | BA117: 3 | BB117: 4
D118: ID117 | E118: 2 | F118: 4 | G118: 4 | H118: 3 | I118: 2 | J118: 4 | K118: 4 | L118: 3 | M118: 4 | N118: 4 | O118: 5 | P118: 5 | Q118: 4 | R118: 2 | S118: 2 | T118: 2 | U118: 4 | V118: 3 | W118: 2 | X118: 2 | Y118: 2 | Z118: 2 | AA118: 5 | AB118: 3 | AC118: 2 | AD118: 3 | AE118: 4 | AF118: 4 | AG118: 4 | AH118: 2 | AI118: 2 | AJ118: 3 | AK118: 2 | AL118: 2 | AM118: 3 | AN118: 5 | AO118: 2 | AP118: 2 | AQ118: 2 | AR118: 2 | AS118: 5 | AT118: 3 | AU118: 4 | AV118: 3 | AW118: 3 | AX118: 5 | AY118: 2 | AZ118: 3 | BA118: 2 | BB118: 5
D119: ID118 | E119: 1 | F119: 1 | G119: 1 | H119: 1 | I119: 2 | J119: 3 | K119: 3 | L119: 3 | M119: 3 | N119: 3 | O119: 4 | P119: 5 | Q119: 5 | R119: 4 | S119: 4 | T119: 5 | U119: 5 | V119: 2 | W119: 4 | X119: 4 | Y119: 5 | Z119: 4 | AA119: 5 | AB119: 5 | AC119: 4 | AD119: 4 | AE119: 4 | AF119: 4 | AG119: 4 | AH119: 5 | AI119: 4 | AJ119: 2 | AK119: 1 | AL119: 4 | AM119: 4 | AN119: 4 | AO119: 4 | AP119: 4 | AQ119: 4 | AR119: 4 | AS119: 4 | AT119: 3 | AU119: 3 | AV119: 4 | AW119: 3 | AX119: 2 | AY119: 2 | AZ119: 2 | BA119: 1 | BB119: 5
D120: ID119 | E120: 4 | F120: 5 | G120: 3 | H120: 5 | I120: 5 | J120: 4 | K120: 4 | L120: 4 | M120: 3 | N120: 4 | O120: 4 | P120: 4 | Q120: 5 | R120: 5 | S120: 5 | T120: 4 | U120: 5 | V120: 2 | W120: 4 | X120: 4 | Y120: 5 | Z120: 5 | AA120: 5 | AB120: 2 | AC120: 4 | AD120: 3 | AE120: 4 | AF120: 5 | AG120: 3 | AH120: 4 | AI120: 4 | AJ120: 5 | AK120: 2 | AL120: 4 | AM120: 4 | AN120: 4 | AO120: 5 | AP120: 4 | AQ120: 4 | AR120: 4 | AS120: 5 | AT120: 4 | AU120: 4 | AV120: 4 | AW120: 3 | AX120: 5 | AY120: 3 | AZ120: 1 | BA120: 3 | BB120: 5
D121: ID120 | E121: 1 | F121: 1 | G121: 1 | H121: 1 | I121: 2 | J121: 3 | K121: 3 | L121: 3 | M121: 3 | N121: 3 | O121: 4 | P121: 5 | Q121: 5 | R121: 4 | S121: 4 | T121: 5 | U121: 5 | V121: 2 | W121: 4 | X121: 4 | Y121: 5 | Z121: 4 | AA121: 5 | AB121: 5 | AC121: 4 | AD121: 4 | AE121: 4 | AF121: 4 | AG121: 4 | AH121: 5 | AI121: 4 | AJ121: 2 | AK121: 1 | AL121: 4 | AM121: 4 | AN121: 4 | AO121: 4 | AP121: 4 | AQ121: 4 | AR121: 4 | AS121: 4 | AT121: 3 | AU121: 3 | AV121: 4 | AW121: 3 | AX121: 2 | AY121: 2 | AZ121: 2 | BA121: 1 | BB121: 3
D122: ID121 | E122: 2 | F122: 2 | G122: 3 | H122: 3 | I122: 4 | J122: 4 | K122: 4 | L122: 3 | M122: 3 | N122: 3 | O122: 4 | P122: 4 | Q122: 4 | R122: 3 | S122: 3 | T122: 3 | U122: 4 | V122: 4 | W122: 4 | X122: 3 | Y122: 4 | Z122: 5 | AA122: 4 | AB122: 3 | AC122: 3 | AD122: 5 | AE122: 4 | AF122: 2 | AG122: 3 | AH122: 3 | AI122: 3 | AJ122: 3 | AK122: 4 | AL122: 5 | AM122: 5 | AN122: 4 | AO122: 4 | AP122: 5 | AQ122: 5 | AR122: 5 | AS122: 4 | AT122: 2 | AU122: 2 | AV122: 3 | AW122: 3 | AX122: 2 | AY122: 2 | AZ122: 2 | BA122: 2 | BB122: 4
D123: ID122 | E123: 4 | F123: 3 | G123: 3 | H123: 3 | I123: 3 | J123: 4 | K123: 4 | L123: 5 | M123: 4 | N123: 5 | O123: 4 | P123: 5 | Q123: 4 | R123: 4 | S123: 4 | T123: 3 | U123: 4 | V123: 3 | W123: 4 | X123: 3 | Y123: 4 | Z123: 4 | AA123: 3 | AB123: 2 | AC123: 1 | AD123: 5 | AE123: 3 | AF123: 4 | AG123: 2 | AH123: 3 | AI123: 4 | AJ123: 3 | AK123: 4 | AL123: 3 | AM123: 3 | AN123: 3 | AO123: 4 | AP123: 5 | AQ123: 5 | AR123: 5 | AS123: 5 | AT123: 1 | AU123: 2 | AV123: 3 | AW123: 3 | AX123: 2 | AY123: 2 | AZ123: 1 | BA123: 1 | BB123: 5
D124: ID123 | E124: 4 | F124: 5 | G124: 3 | H124: 3 | I124: 3 | J124: 4 | K124: 4 | L124: 5 | M124: 3 | N124: 2 | O124: 4 | P124: 5 | Q124: 5 | R124: 4 | S124: 1 | T124: 2 | U124: 1 | V124: 3 | W124: 4 | X124: 2 | Y124: 2 | Z124: 2 | AA124: 1 | AB124: 3 | AC124: 2 | AD124: 1 | AE124: 1 | AF124: 1 | AG124: 2 | AH124: 4 | AI124: 2 | AJ124: 3 | AK124: 5 | AL124: 2 | AM124: 2 | AN124: 4 | AO124: 4 | AP124: 4 | AQ124: 4 | AR124: 4 | AS124: 3 | AT124: 2 | AU124: 5 | AV124: 5 | AW124: 3 | AX124: 2 | AY124: 2 | AZ124: 1 | BA124: 2 | BB124: 5
D125: ID124 | E125: 4 | F125: 5 | G125: 3 | H125: 5 | I125: 4 | J125: 4 | K125: 4 | L125: 4 | M125: 3 | N125: 3 | O125: 5 | P125: 5 | Q125: 4 | R125: 2 | S125: 3 | T125: 4 | U125: 4 | V125: 3 | W125: 4 | X125: 5 | Y125: 4 | Z125: 4 | AA125: 5 | AB125: 5 | AC125: 4 | AD125: 3 | AE125: 4 | AF125: 3 | AG125: 4 | AH125: 5 | AI125: 4 | AJ125: 5 | AK125: 5 | AL125: 4 | AM125: 4 | AN125: 5 | AO125: 4 | AP125: 4 | AQ125: 4 | AR125: 2 | AS125: 4 | AT125: 5 | AU125: 5 | AV125: 4 | AW125: 3 | AX125: 2 | AY125: 3 | AZ125: 2 | BA125: 2 | BB125: 3
D126: ID125 | E126: 1 | F126: 1 | G126: 1 | H126: 1 | I126: 2 | J126: 3 | K126: 3 | L126: 3 | M126: 3 | N126: 3 | O126: 4 | P126: 5 | Q126: 5 | R126: 4 | S126: 4 | T126: 5 | U126: 5 | V126: 2 | W126: 4 | X126: 4 | Y126: 5 | Z126: 4 | AA126: 5 | AB126: 5 | AC126: 4 | AD126: 4 | AE126: 4 | AF126: 4 | AG126: 4 | AH126: 5 | AI126: 4 | AJ126: 2 | AK126: 1 | AL126: 4 | AM126: 4 | AN126: 4 | AO126: 4 | AP126: 4 | AQ126: 4 | AR126: 4 | AS126: 4 | AT126: 3 | AU126: 3 | AV126: 4 | AW126: 3 | AX126: 2 | AY126: 2 | AZ126: 2 | BA126: 1 | BB126: 5
D127: ID126 | E127: 4 | F127: 5 | G127: 3 | H127: 3 | I127: 3 | J127: 4 | K127: 4 | L127: 5 | M127: 3 | N127: 2 | O127: 4 | P127: 5 | Q127: 5 | R127: 4 | S127: 1 | T127: 2 | U127: 1 | V127: 3 | W127: 4 | X127: 2 | Y127: 2 | Z127: 2 | AA127: 1 | AB127: 3 | AC127: 2 | AD127: 1 | AE127: 1 | AF127: 1 | AG127: 2 | AH127: 4 | AI127: 2 | AJ127: 3 | AK127: 5 | AL127: 2 | AM127: 2 | AN127: 4 | AO127: 4 | AP127: 4 | AQ127: 4 | AR127: 4 | AS127: 3 | AT127: 2 | AU127: 5 | AV127: 5 | AW127: 3 | AX127: 2 | AY127: 2 | AZ127: 1 | BA127: 2 | BB127: 5
D128: ID127 | E128: 4 | F128: 3 | G128: 3 | H128: 3 | I128: 3 | J128: 4 | K128: 4 | L128: 5 | M128: 4 | N128: 5 | O128: 4 | P128: 5 | Q128: 4 | R128: 4 | S128: 4 | T128: 3 | U128: 4 | V128: 3 | W128: 4 | X128: 3 | Y128: 4 | Z128: 4 | AA128: 3 | AB128: 2 | AC128: 1 | AD128: 5 | AE128: 3 | AF128: 4 | AG128: 2 | AH128: 3 | AI128: 4 | AJ128: 3 | AK128: 4 | AL128: 3 | AM128: 3 | AN128: 3 | AO128: 4 | AP128: 5 | AQ128: 5 | AR128: 5 | AS128: 5 | AT128: 1 | AU128: 2 | AV128: 3 | AW128: 3 | AX128: 2 | AY128: 2 | AZ128: 1 | BA128: 1 | BB128: 4
D129: ID128 | E129: 3 | F129: 3 | G129: 3 | H129: 3 | I129: 3 | J129: 3 | K129: 2 | L129: 3 | M129: 2 | N129: 3 | O129: 3 | P129: 3 | Q129: 4 | R129: 4 | S129: 4 | T129: 4 | U129: 5 | V129: 4 | X129: 2 | Y129: 2 | Z129: 3 | AA129: 3 | AB129: 2 | AC129: 3 | AD129: 3 | AE129: 4 | AF129: 3 | AG129: 3 | AH129: 4 | AI129: 3 | AJ129: 3 | AK129: 3 | AL129: 2 | AM129: 2 | AN129: 4 | AO129: 5 | AP129: 4 | AQ129: 5 | AR129: 5 | AS129: 2 | AT129: 2 | AU129: 2 | AV129: 4 | AW129: 3 | AX129: 2 | AY129: 3 | AZ129: 2 | BA129: 3 | BB129: 4
D130: ID129 | E130: 4 | F130: 4 | G130: 3 | H130: 4 | I130: 4 | J130: 4 | K130: 4 | L130: 4 | M130: 4 | N130: 4 | O130: 4 | P130: 4 | Q130: 4 | R130: 4 | S130: 4 | T130: 4 | U130: 4 | V130: 4 | W130: 4 | X130: 4 | Y130: 4 | Z130: 4 | AA130: 4 | AB130: 3 | AC130: 3 | AD130: 3 | AE130: 4 | AF130: 5 | AG130: 4 | AH130: 5 | AI130: 3 | AJ130: 4 | AK130: 4 | AL130: 5 | AM130: 4 | AN130: 4 | AO130: 4 | AP130: 4 | AQ130: 4 | AR130: 5 | AS130: 5 | AT130: 4 | AU130: 4 | AV130: 5 | AW130: 3 | AX130: 2 | AY130: 3 | AZ130: 2 | BA130: 3 | BB130: 5
D131: ID130 | E131: 2 | F131: 2 | G131: 3 | H131: 3 | I131: 1 | J131: 2 | K131: 3 | L131: 3 | M131: 2 | N131: 2 | O131: 3 | P131: 2 | Q131: 3 | R131: 4 | S131: 4 | T131: 1 | U131: 4 | V131: 2 | W131: 3 | X131: 3 | Y131: 3 | Z131: 3 | AA131: 3 | AB131: 4 | AC131: 3 | AD131: 3 | AE131: 3 | AF131: 2 | AG131: 2 | AH131: 5 | AI131: 4 | AJ131: 1 | AK131: 4 | AL131: 3 | AM131: 3 | AN131: 3 | AO131: 4 | AP131: 4 | AQ131: 4 | AR131: 3 | AS131: 3 | AT131: 1 | AU131: 1 | AV131: 2 | AW131: 3 | AX131: 2 | AY131: 4 | AZ131: 2 | BA131: 2 | BB131: 3
D132: ID131 | E132: 3 | F132: 4 | G132: 2 | H132: 2 | I132: 3 | J132: 4 | K132: 4 | L132: 4 | M132: 5 | N132: 3 | O132: 5 | P132: 4 | Q132: 5 | R132: 5 | S132: 5 | T132: 3 | U132: 2 | V132: 2 | W132: 4 | X132: 4 | Y132: 4 | Z132: 4 | AA132: 4 | AB132: 3 | AC132: 4 | AD132: 3 | AE132: 4 | AF132: 5 | AG132: 5 | AH132: 5 | AI132: 4 | AJ132: 3 | AK132: 3 | AL132: 3 | AM132: 3 | AN132: 3 | AO132: 3 | AP132: 3 | AQ132: 4 | AR132: 5 | AS132: 3 | AT132: 2 | AU132: 3 | AV132: 4 | AW132: 3 | AX132: 2 | AY132: 2 | AZ132: 2 | BA132: 1 | BB132: 5
D133: ID132 | E133: 2 | F133: 2 | G133: 2 | H133: 2 | I133: 1 | J133: 3 | K133: 3 | L133: 1 | M133: 1 | N133: 1 | O133: 1 | P133: 2 | Q133: 3 | R133: 3 | S133: 3 | T133: 1 | U133: 3 | V133: 1 | W133: 2 | X133: 1 | Y133: 2 | Z133: 3 | AA133: 3 | AB133: 4 | AC133: 2 | AD133: 1 | AE133: 2 | AF133: 1 | AG133: 3 | AH133: 4 | AI133: 2 | AJ133: 1 | AK133: 2 | AL133: 1 | AM133: 2 | AN133: 3 | AO133: 3 | AP133: 5 | AQ133: 5 | AR133: 4 | AS133: 4 | AT133: 1 | AU133: 2 | AV133: 3 | AW133: 3 | AX133: 4 | AY133: 2 | AZ133: 2 | BA133: 1 | BB133: 2
D134: ID133 | E134: 3 | F134: 1 | G134: 1 | H134: 2 | I134: 1 | J134: 1 | K134: 1 | L134: 3 | M134: 1 | N134: 5 | O134: 1 | P134: 3 | Q134: 1 | R134: 5 | S134: 4 | T134: 2 | U134: 5 | V134: 5 | W134: 1 | X134: 1 | Y134: 3 | Z134: 5 | AA134: 3 | AB134: 3 | AC134: 2 | AD134: 3 | AE134: 3 | AF134: 5 | AG134: 5 | AH134: 5 | AI134: 5 | AJ134: 2 | AK134: 5 | AL134: 2 | AM134: 2 | AN134: 1 | AO134: 4 | AP134: 5 | AQ134: 5 | AR134: 5 | AS134: 1 | AT134: 2 | AU134: 2 | AV134: 5 | AW134: 3 | AX134: 2 | AY134: 3 | AZ134: 2 | BA134: 1 | BB134: 3
D135: ID134 | E135: 4 | F135: 4 | G135: 1 | H135: 3 | I135: 3 | J135: 4 | K135: 4 | L135: 5 | M135: 4 | N135: 5 | O135: 3 | P135: 5 | Q135: 5 | R135: 3 | S135: 5 | T135: 3 | U135: 4 | V135: 2 | W135: 5 | X135: 5 | Y135: 4 | Z135: 5 | AA135: 4 | AB135: 3 | AC135: 5 | AD135: 3 | AE135: 5 | AF135: 3 | AG135: 4 | AH135: 4 | AI135: 3 | AJ135: 4 | AK135: 5 | AL135: 5 | AM135: 5 | AN135: 3 | AO135: 2 | AP135: 5 | AQ135: 5 | AR135: 5 | AS135: 4 | AT135: 3 | AU135: 3 | AV135: 4 | AW135: 2 | AX135: 5 | AY135: 3 | AZ135: 2 | BA135: 3 | BB135: 4
D136: ID135 | E136: 3 | F136: 3 | G136: 3 | H136: 3 | I136: 3 | J136: 3 | K136: 2 | L136: 3 | M136: 2 | N136: 3 | O136: 3 | P136: 3 | Q136: 4 | R136: 4 | S136: 4 | T136: 4 | U136: 5 | V136: 4 | X136: 2 | Y136: 2 | Z136: 3 | AA136: 3 | AB136: 2 | AC136: 3 | AD136: 3 | AE136: 4 | AF136: 3 | AG136: 3 | AH136: 4 | AI136: 3 | AJ136: 3 | AK136: 3 | AL136: 2 | AM136: 2 | AN136: 4 | AO136: 5 | AP136: 4 | AQ136: 5 | AR136: 5 | AS136: 2 | AT136: 2 | AU136: 2 | AV136: 4 | AW136: 2 | AX136: 2 | AY136: 3 | AZ136: 2 | BA136: 3 | BB136: 5
D137: ID136 | E137: 4 | F137: 4 | G137: 3 | H137: 4 | I137: 4 | J137: 4 | K137: 4 | L137: 4 | M137: 4 | N137: 4 | O137: 4 | P137: 4 | Q137: 4 | R137: 4 | S137: 4 | T137: 4 | U137: 4 | V137: 4 | W137: 4 | X137: 4 | Y137: 4 | Z137: 4 | AA137: 4 | AB137: 3 | AC137: 3 | AD137: 3 | AE137: 4 | AF137: 5 | AG137: 4 | AH137: 5 | AI137: 3 | AJ137: 4 | AK137: 4 | AL137: 5 | AM137: 4 | AN137: 4 | AO137: 4 | AP137: 4 | AQ137: 4 | AR137: 5 | AS137: 5 | AT137: 4 | AU137: 4 | AV137: 5 | AW137: 2 | AX137: 2 | AY137: 3 | AZ137: 3 | BA137: 2 | BB137: 1
D138: ID137 | E138: 4 | F138: 5 | G138: 4 | H138: 3 | I138: 4 | J138: 4 | K138: 4 | L138: 4 | M138: 4 | N138: 4 | O138: 5 | P138: 5 | Q138: 5 | R138: 3 | S138: 4 | T138: 4 | U138: 5 | V138: 4 | W138: 4 | X138: 4 | Y138: 4 | Z138: 4 | AA138: 4 | AB138: 5 | AC138: 4 | AD138: 4 | AE138: 4 | AF138: 5 | AG138: 5 | AH138: 4 | AI138: 4 | AJ138: 4 | AK138: 3 | AL138: 4 | AM138: 4 | AN138: 5 | AO138: 4 | AP138: 4 | AQ138: 5 | AR138: 5 | AS138: 4 | AT138: 4 | AU138: 3 | AV138: 4 | AW138: 2 | AX138: 5 | AY138: 2 | AZ138: 2 | BA138: 2 | BB138: 3
D139: ID138 | E139: 2 | F139: 2 | G139: 3 | H139: 3 | I139: 1 | J139: 2 | K139: 3 | L139: 3 | M139: 2 | N139: 2 | O139: 3 | P139: 2 | Q139: 3 | R139: 4 | S139: 4 | T139: 1 | U139: 4 | V139: 2 | W139: 3 | X139: 3 | Y139: 3 | Z139: 3 | AA139: 3 | AB139: 4 | AC139: 3 | AD139: 3 | AE139: 3 | AF139: 2 | AG139: 2 | AH139: 5 | AI139: 4 | AJ139: 1 | AK139: 4 | AL139: 3 | AM139: 3 | AN139: 3 | AO139: 4 | AP139: 4 | AQ139: 4 | AR139: 3 | AS139: 3 | AT139: 1 | AU139: 1 | AV139: 2 | AW139: 2 | AX139: 2 | AY139: 4 | AZ139: 2 | BA139: 2 | BB139: 3
D140: ID139 | E140: 5 | F140: 3 | G140: 2 | H140: 3 | I140: 5 | J140: 5 | K140: 5 | L140: 5 | M140: 5 | N140: 4 | O140: 5 | P140: 5 | Q140: 5 | R140: 5 | S140: 5 | T140: 4 | U140: 4 | V140: 4 | W140: 5 | X140: 5 | Y140: 5 | Z140: 5 | AA140: 4 | AB140: 5 | AC140: 5 | AD140: 4 | AE140: 4 | AF140: 4 | AG140: 5 | AH140: 5 | AI140: 4 | AJ140: 4 | AK140: 4 | AL140: 5 | AM140: 5 | AN140: 4 | AO140: 5 | AP140: 5 | AQ140: 5 | AR140: 5 | AS140: 4 | AT140: 4 | AU140: 4 | AV140: 5 | AW140: 2 | AX140: 2 | AY140: 3 | AZ140: 1 | BA140: 1 | BB140: 5
D141: ID140 | E141: 3 | F141: 3 | G141: 3 | H141: 3 | I141: 3 | J141: 4 | K141: 4 | L141: 4 | M141: 4 | N141: 4 | O141: 4 | P141: 4 | Q141: 4 | R141: 3 | S141: 2 | T141: 4 | U141: 2 | V141: 2 | W141: 4 | X141: 4 | Y141: 4 | Z141: 4 | AA141: 4 | AB141: 4 | AC141: 5 | AD141: 4 | AE141: 4 | AF141: 3 | AG141: 3 | AH141: 3 | AI141: 4 | AJ141: 4 | AK141: 4 | AL141: 4 | AM141: 4 | AN141: 4 | AO141: 4 | AP141: 3 | AQ141: 3 | AR141: 3 | AS141: 3 | AT141: 3 | AU141: 3 | AV141: 3 | AW141: 2 | AX141: 5 | AY141: 3 | AZ141: 1 | BA141: 2 | BB141: 5
D142: ID141 | E142: 3 | F142: 2 | G142: 3 | H142: 3 | I142: 3 | J142: 4 | K142: 4 | L142: 3 | M142: 4 | N142: 3 | O142: 3 | P142: 5 | Q142: 4 | R142: 2 | S142: 2 | T142: 3 | U142: 2 | V142: 3 | W142: 4 | X142: 3 | Y142: 2 | Z142: 3 | AA142: 4 | AB142: 4 | AC142: 3 | AD142: 3 | AE142: 3 | AF142: 2 | AG142: 2 | AH142: 3 | AI142: 4 | AJ142: 4 | AK142: 4 | AL142: 3 | AM142: 3 | AN142: 4 | AO142: 3 | AP142: 4 | AQ142: 4 | AR142: 3 | AS142: 4 | AT142: 3 | AU142: 3 | AV142: 2 | AW142: 2 | AX142: 2 | AY142: 2 | AZ142: 2 | BA142: 2 | BB142: 4
D143: ID142 | E143: 3 | F143: 2 | G143: 3 | H143: 3 | I143: 3 | J143: 4 | K143: 4 | L143: 3 | M143: 4 | N143: 3 | O143: 3 | P143: 5 | Q143: 4 | R143: 2 | S143: 2 | T143: 3 | U143: 2 | V143: 3 | W143: 4 | X143: 3 | Y143: 2 | Z143: 3 | AA143: 4 | AB143: 4 | AC143: 3 | AD143: 3 | AE143: 3 | AF143: 2 | AG143: 2 | AH143: 3 | AI143: 4 | AJ143: 4 | AK143: 4 | AL143: 3 | AM143: 3 | AN143: 4 | AO143: 3 | AP143: 4 | AQ143: 4 | AR143: 3 | AS143: 4 | AT143: 3 | AU143: 3 | AV143: 2 | AW143: 2 | AX143: 5 | AY143: 2 | AZ143: 1 | BA143: 2 | BB143: 4
D144: ID143 | E144: 2 | F144: 2 | G144: 3 | H144: 2 | I144: 1 | J144: 2 | K144: 2 | L144: 3 | M144: 2 | N144: 3 | O144: 2 | P144: 3 | Q144: 2 | R144: 4 | S144: 4 | T144: 2 | U144: 3 | V144: 2 | W144: 2 | X144: 2 | Y144: 2 | Z144: 2 | AA144: 2 | AB144: 4 | AC144: 2 | AD144: 2 | AE144: 2 | AF144: 2 | AG144: 3 | AH144: 3 | AI144: 3 | AJ144: 2 | AK144: 3 | AL144: 4 | AM144: 2 | AN144: 4 | AO144: 3 | AP144: 4 | AQ144: 4 | AR144: 3 | AS144: 2 | AT144: 2 | AU144: 2 | AV144: 4 | AW144: 1 | AX144: 2 | AY144: 3 | AZ144: 2 | BA144: 3 | BB144: 5

Sheet 3rd Iteration Dataset
A1: ID | B1: 1.Delay in delivering material to construction site | C1: 2.Monopoly of material by some suppliers | D1: 3.Prices fluctuation | E1: 4.Types of material availability at local market | F1: 5.Lack of consultant’s knowledge of available materials | G1: 6.Low productivity | H1: 7.Poor work execution | I1: 8.Shortage of laborers | J1: 9.Mistakes happens during construction phase | K1: 10.Unavailability of equipment | L1: 11.Lack of engineering experience | M1: 12.Construction cost underestimation | N1: 13.Poor site management | O1: 14.Delayed payment for completed work | P1: 15.Cash flow problem during construction | Q1: 16.High rate of interest | R1: 17.Contractor’s financial difficulties | S1: 19.Change design | T1: 20.Errors and omission in design | U1: 21.Incomplete design drawings and specifications at tendering stage | V1: 22.Delay in preparation and approval of drawing | W1: 23.Inaccurate quantity take-off | X1: 24.Long period from planning of project to construction | Y1: 25.Delays in issuing information to the contractor during construction stage | Z1: 26.No practical use of earned value management system | AA1: 27.Lack of cost planning/monitoring during pre and post contract stage | AB1: 28.Poor communication between client, consultant and contractor | AC1: 29.Insufficient coordination between local authority who is responsible about road projects and service authorities | AD1: 30.Delays in decisions making by the approval authorities | AE1: 31.Change schedule | AF1: 32.Stoppages because of work being rejected by consultant | AG1: 33.Lowest bid price | AH1: 34.Insufficient time for preparation of contract documents | AI1: 35.Discrepancies in contract documents | AJ1: 36.Underestimation of time for completion of project | AK1: 37.Extension of time with cost claims | AL1: 38.Scope and specification changes | AM1: 39.Changes in client requirements | AN1: 40.Frequency of variation orders and additional works | AO1: 41.Rework due to error in execution | AP1: 42.Weather conditions | AQ1: 43.Accidents during construction | AR1: 44.Delay in getting NOCs from different government authorities | AS1: Location of organization | AT1: Relevant working experience
A2: ID001 | B2: 1 | C2: 1 | D2: 1 | E2: 1 | F2: 1 | G2: 1 | H2: 1 | I2: 1 | J2: 1 | K2: 1 | L2: 1 | M2: 1 | N2: 1 | O2: 1 | P2: 1 | Q2: 1 | R2: 1 | S2: 3 | T2: 3 | U2: 3 | V2: 4 | W2: 4 | X2: 3 | Y2: 3 | Z2: 2 | AA2: 1 | AB2: 2 | AC2: 4 | AD2: 4 | AE2: 1 | AF2: 1 | AG2: 2 | AH2: 2 | AI2: 2 | AJ2: 2 | AK2: 2 | AL2: 3 | AM2: 3 | AN2: 3 | AO2: 1 | AP2: 2 | AQ2: 2 | AR2: 3 | AS2: 3 | AT2: 5
A3: ID002 | B3: 2 | C3: 5 | D3: 3 | E3: 2 | F3: 3 | G3: 2 | H3: 2 | I3: 2 | J3: 3 | K3: 2 | L3: 2 | M3: 2 | N3: 2 | O3: 2 | P3: 2 | Q3: 1 | R3: 4 | S3: 5 | T3: 5 | U3: 4 | V3: 4 | W3: 4 | X3: 5 | Y3: 3 | Z3: 3 | AA3: 3 | AB3: 4 | AC3: 4 | AD3: 3 | AE3: 4 | AF3: 4 | AG3: 5 | AH3: 3 | AI3: 4 | AJ3: 4 | AK3: 4 | AL3: 3 | AM3: 3 | AN3: 4 | AO3: 3 | AP3: 1 | AQ3: 1 | AR3: 4 | AS3: 3 | AT3: 3
A4: ID003 | B4: 1 | C4: 2 | D4: 1 | E4: 1 | F4: 2 | G4: 2 | H4: 1 | I4: 2 | J4: 1 | K4: 1 | L4: 2 | M4: 1 | N4: 3 | O4: 3 | P4: 3 | Q4: 2 | R4: 2 | S4: 2 | T4: 2 | U4: 2 | V4: 2 | W4: 3 | X4: 2 | Y4: 3 | Z4: 1 | AA4: 2 | AB4: 1 | AC4: 3 | AD4: 4 | AE4: 3 | AF4: 1 | AG4: 2 | AH4: 2 | AI4: 2 | AJ4: 2 | AK4: 4 | AL4: 2 | AM4: 2 | AN4: 2 | AO4: 2 | AP4: 1 | AQ4: 1 | AR4: 4 | AS4: 2 | AT4: 4
A5: ID004 | B5: 2 | C5: 2 | D5: 3 | E5: 3 | F5: 2 | G5: 2 | H5: 3 | I5: 4 | J5: 4 | K5: 4 | L5: 2 | M5: 5 | N5: 2 | O5: 2 | P5: 1 | Q5: 1 | R5: 1 | S5: 4 | T5: 4 | U5: 4 | V5: 4 | W5: 4 | X5: 3 | Y5: 2 | Z5: 2 | AA5: 2 | AB5: 2 | AC5: 3 | AD5: 3 | AE5: 2 | AF5: 2 | AG5: 2 | AH5: 3 | AI5: 2 | AJ5: 4 | AK5: 4 | AL5: 4 | AM5: 4 | AN5: 4 | AO5: 3 | AP5: 4 | AQ5: 3 | AR5: 3 | AS5: 3 | AT5: 4
A6: ID005 | B6: 1 | C6: 2 | D6: 1 | E6: 1 | F6: 2 | G6: 2 | H6: 1 | I6: 2 | J6: 1 | K6: 1 | L6: 2 | M6: 1 | N6: 2 | O6: 4 | P6: 4 | Q6: 2 | R6: 2 | S6: 2 | T6: 2 | U6: 2 | V6: 2 | W6: 3 | X6: 2 | Y6: 4 | Z6: 3 | AA6: 2 | AB6: 1 | AC6: 3 | AD6: 4 | AE6: 3 | AF6: 1 | AG6: 2 | AH6: 2 | AI6: 2 | AJ6: 2 | AK6: 4 | AL6: 2 | AM6: 2 | AN6: 2 | AO6: 2 | AP6: 1 | AQ6: 1 | AR6: 4 | AS6: 2 | AT6: 4
A7: ID006 | B7: 1 | C7: 1 | D7: 1 | E7: 1 | F7: 1 | G7: 2 | H7: 2 | I7: 2 | J7: 1 | K7: 1 | L7: 1 | M7: 2 | N7: 1 | O7: 4 | P7: 4 | Q7: 4 | R7: 4 | S7: 4 | T7: 4 | U7: 4 | V7: 4 | W7: 4 | X7: 4 | Y7: 2 | Z7: 2 | AA7: 2 | AB7: 1 | AC7: 1 | AD7: 3 | AE7: 3 | AF7: 4 | AG7: 2 | AH7: 2 | AI7: 2 | AJ7: 2 | AK7: 2 | AL7: 3 | AM7: 2 | AN7: 3 | AO7: 3 | AP7: 2 | AQ7: 2 | AR7: 2 | AS7: 3 | AT7: 5
A8: ID007 | B8: 1 | C8: 1 | D8: 1 | E8: 1 | F8: 1 | G8: 1 | H8: 1 | I8: 1 | J8: 1 | K8: 1 | L8: 1 | M8: 1 | N8: 1 | O8: 4 | P8: 4 | Q8: 4 | R8: 4 | S8: 4 | T8: 4 | U8: 4 | V8: 4 | W8: 4 | X8: 4 | Y8: 2 | Z8: 2 | AA8: 2 | AB8: 1 | AC8: 2 | AD8: 4 | AE8: 3 | AF8: 4 | AG8: 2 | AH8: 2 | AI8: 2 | AJ8: 2 | AK8: 4 | AL8: 4 | AM8: 3 | AN8: 4 | AO8: 4 | AP8: 2 | AQ8: 2 | AR8: 2 | AS8: 3 | AT8: 5
A9: ID008 | B9: 1 | C9: 1 | D9: 1 | E9: 1 | F9: 1 | G9: 1 | H9: 1 | I9: 1 | J9: 1 | K9: 1 | L9: 1 | M9: 1 | N9: 1 | O9: 3 | P9: 3 | Q9: 3 | R9: 4 | S9: 4 | T9: 4 | U9: 4 | V9: 4 | W9: 4 | X9: 4 | Y9: 2 | Z9: 2 | AA9: 2 | AB9: 1 | AC9: 1 | AD9: 3 | AE9: 3 | AF9: 4 | AG9: 2 | AH9: 2 | AI9: 2 | AJ9: 2 | AK9: 2 | AL9: 3 | AM9: 2 | AN9: 3 | AO9: 3 | AP9: 2 | AQ9: 2 | AR9: 2 | AS9: 3 | AT9: 5
A10: ID009 | B10: 1 | C10: 1 | D10: 1 | E10: 1 | F10: 1 | G10: 1 | H10: 1 | I10: 1 | J10: 1 | K10: 1 | L10: 1 | M10: 1 | N10: 1 | O10: 4 | P10: 4 | Q10: 4 | R10: 4 | S10: 4 | T10: 4 | U10: 4 | V10: 4 | W10: 4 | X10: 4 | Y10: 2 | Z10: 2 | AA10: 2 | AB10: 1 | AC10: 2 | AD10: 4 | AE10: 3 | AF10: 4 | AG10: 2 | AH10: 2 | AI10: 2 | AJ10: 2 | AK10: 2 | AL10: 4 | AM10: 3 | AN10: 4 | AO10: 4 | AP10: 2 | AQ10: 2 | AR10: 2 | AS10: 3 | AT10: 5
A11: ID010 | B11: 1 | C11: 1 | D11: 1 | E11: 1 | F11: 1 | G11: 1 | H11: 1 | I11: 1 | J11: 1 | K11: 1 | L11: 1 | M11: 1 | N11: 1 | O11: 4 | P11: 4 | Q11: 4 | R11: 4 | S11: 4 | T11: 4 | U11: 4 | V11: 4 | W11: 4 | X11: 4 | Y11: 2 | Z11: 2 | AA11: 2 | AB11: 1 | AC11: 1 | AD11: 3 | AE11: 3 | AF11: 4 | AG11: 2 | AH11: 2 | AI11: 2 | AJ11: 2 | AK11: 2 | AL11: 3 | AM11: 2 | AN11: 3 | AO11: 3 | AP11: 2 | AQ11: 2 | AR11: 2 | AS11: 3 | AT11: 5
A12: ID011 | B12: 2 | C12: 4 | D12: 4 | E12: 1 | F12: 1 | G12: 5 | H12: 1 | I12: 4 | J12: 5 | K12: 3 | L12: 2 | M12: 5 | N12: 2 | O12: 1 | P12: 1 | Q12: 1 | R12: 1 | S12: 5 | T12: 2 | U12: 3 | V12: 4 | W12: 3 | X12: 2 | Y12: 2 | Z12: 1 | AA12: 2 | AB12: 1 | AC12: 5 | AD12: 1 | AE12: 1 | AF12: 1 | AG12: 1 | AH12: 1 | AI12: 1 | AJ12: 3 | AK12: 3 | AL12: 4 | AM12: 4 | AN12: 4 | AO12: 1 | AP12: 1 | AQ12: 1 | AR12: 1 | AS12: 3 | AT12: 4
A13: ID012 | B13: 2 | C13: 1 | D13: 3 | E13: 4 | F13: 4 | G13: 3 | H13: 3 | I13: 4 | J13: 3 | K13: 4 | L13: 5 | M13: 4 | N13: 3 | O13: 3 | P13: 4 | Q13: 2 | R13: 4 | S13: 4 | T13: 4 | U13: 5 | V13: 3 | W13: 4 | X13: 3 | Y13: 3 | Z13: 3 | AA13: 3 | AB13: 4 | AC13: 4 | AD13: 4 | AE13: 3 | AF13: 4 | AG13: 4 | AH13: 3 | AI13: 3 | AJ13: 4 | AK13: 4 | AL13: 4 | AM13: 4 | AN13: 4 | AO13: 4 | AP13: 2 | AQ13: 2 | AR13: 3 | AS13: 3 | AT13: 5
... A44: ID043 | B44: 4 | C44: 5 | D44: 3 | E44: 4 | F44: 4 | G44: 4 | H44: 5 | I44: 4 | J44: 4 | K44: 4 | L44: 4 | M44: 4 | N44: 4 | O44: 5 | P44: 5 | Q44: 5 | R44: 4 | S44: 5 | T44: 4 | U44: 4 | V44: 4 | W44: 4 | X44: 3 | Y44: 4 | Z44: 3 | AA44: 4 | AB44: 4 | AC44: 4 | AD44: 4 | AE44: 4 | AF44: 4 | AG44: 1 | AH44: 2 | AI44: 3 | AJ44: 4 | AK44: 5 | AL44: 4 | AM44: 5 | AN44: 4 | AO44: 4 | AP44: 3 | AQ44: 3 | AR44: 5 | AS44: 2 | AT44: 4
A45: ID044 | B45: 4 | C45: 5 | D45: 3 | E45: 4 | F45: 4 | G45: 4 | H45: 5 | I45: 4 | J45: 4 | K45: 5 | L45: 4 | M45: 4 | N45: 4 | O45: 5 | P45: 5 | Q45: 5 | R45: 4 | S45: 5 | T45: 4 | U45: 4 | V45: 4 | W45: 4 | X45: 3 | Y45: 4 | Z45: 3 | AA45: 4 | AB45: 3 | AC45: 3 | AD45: 4 | AE45: 4 | AF45: 4 | AH45: 5 | AI45: 4 | AJ45: 3 | AK45: 4 | AL45: 5 | AM45: 4 | AN45: 5 | AO45: 3 | AP45: 2 | AQ45: 2 | AR45: 5 | AS45: 1 | AT45: 4
A46: ID045 | B46: 4 | C46: 5 | D46: 3 | E46: 4 | F46: 4 | G46: 4 | H46: 5 | I46: 4 | J46: 4 | K46: 5 | L46: 4 | M46: 4 | N46: 4 | O46: 5 | P46: 5 | Q46: 5 | R46: 4 | S46: 5 | T46: 4 | U46: 4 | V46: 4 | W46: 4 | X46: 3 | Y46: 4 | Z46: 3 | AA46: 4 | AB46: 3 | AC46: 3 | AD46: 4 | AE46: 4 | AF46: 4 | AG46: 5 | AH46: 4 | AI46: 3 | AJ46: 4 | AK46: 5 | AL46: 4 | AM46: 5 | AN46: 4 | AO46: 4 | AP46: 3 | AQ46: 3 | AR46: 5 | AS46: 1 | AT46: 4
A47: ID046 | B47: 4 | C47: 5 | D47: 3 | E47: 4 | F47: 4 | G47: 4 | H47: 5 | I47: 4 | J47: 4 | K47: 5 | L47: 4 | M47: 4 | N47: 4 | O47: 5 | P47: 5 | Q47: 5 | R47: 4 | S47: 5 | T47: 4 | U47: 4 | V47: 4 | W47: 4 | X47: 3 | Y47: 4 | Z47: 3 | AA47: 4 | AB47: 4 | AC47: 4 | AD47: 5 | AE47: 4 | AF47: 4 | AG47: 5 | AH47: 4 | AI47: 3 | AJ47: 4 | AK47: 5 | AL47: 4 | AM47: 5 | AN47: 4 | AO47: 4 | AP47: 3 | AQ47: 3 | AR47: 5 | AS47: 3 | AT47: 4
A48: ID047 | B48: 4 | C48: 3 | D48: 3 | E48: 3 | F48: 3 | G48: 5 | H48: 5 | I48: 5 | J48: 5 | K48: 5 | L48: 4 | M48: 4 | N48: 4 | O48: 4 | P48: 4 | Q48: 3 | R48: 3 | S48: 3 | T48: 2 | U48: 2 | V48: 4 | W48: 3 | X48: 2 | Y48: 3 | Z48: 4 | AA48: 4 | AB48: 5 | AC48: 5 | AD48: 5 | AE48: 4 | AF48: 4 | AG48: 3 | AH48: 4 | AI48: 4 | AJ48: 5 | AK48: 4 | AL48: 5 | AM48: 3 | AN48: 3 | AO48: 4 | AP48: 3 | AQ48: 2 | AR48: 4 | AS48: 3 | AT48: 4
A49: ID048 | B49: 1 | C49: 1 | D49: 2 | E49: 2 | F49: 2 | G49: 4 | H49: 4 | I49: 3 | J49: 4 | K49: 4 | L49: 5 | M49: 5 | N49: 5 | O49: 5 | P49: 5 | Q49: 5 | R49: 4 | S49: 3 | T49: 4 | U49: 3 | V49: 4 | W49: 4 | X49: 4 | Y49: 3 | Z49: 2 | AA49: 4 | AB49: 5 | AC49: 5 | AD49: 5 | AE49: 3 | AF49: 2 | AG49: 4 | AH49: 5 | AI49: 5 | AJ49: 4 | AK49: 5 | AL49: 5 | AM49: 5 | AN49: 4 | AO49: 5 | AP49: 3 | AQ49: 5 | AR49: 4 | AS49: 1 | AT49: 5
A50: ID049 | B50: 4 | C50: 2 | D50: 4 | E50: 4 | F50: 3 | G50: 4 | H50: 5 | I50: 3 | J50: 5 | K50: 3 | L50: 5 | M50: 5 | N50: 5 | O50: 4 | P50: 4 | Q50: 3 | R50: 2 | S50: 4 | T50: 5 | U50: 4 | V50: 4 | W50: 4 | X50: 4 | Y50: 3 | Z50: 3 | AA50: 4 | AB50: 4 | AC50: 5 | AD50: 5 | AE50: 3 | AF50: 3 | AG50: 4 | AH50: 3 | AI50: 4 | AJ50: 4 | AK50: 3 | AL50: 4 | AM50: 4 | AN50: 4 | AO50: 4 | AP50: 3 | AQ50: 3 | AR50: 3 | AS50: 3 | AT50: 3
A51: ID050 | B51: 5 | C51: 4 | D51: 4 | E51: 5 | F51: 2 | G51: 5 | H51: 5 | I51: 5 | J51: 4 | K51: 4 | L51: 4 | M51: 4 | N51: 5 | O51: 3 | P51: 5 | Q51: 4 | R51: 5 | S51: 4 | T51: 4 | U51: 4 | V51: 4 | W51: 4 | X51: 4 | Y51: 5 | Z51: 4 | AA51: 5 | AB51: 5 | AC51: 4 | AD51: 5 | AE51: 5 | AF51: 4 | AG51: 4 | AH51: 5 | AI51: 4 | AJ51: 4 | AK51: 4 | AL51: 5 | AM51: 4 | AN51: 5 | AO51: 4 | AP51: 4 | AQ51: 4 | AR51: 4 | AS51: 1 | AT51: 4
A52: ID051 | B52: 4 | C52: 2 | D52: 4 | E52: 3 | F52: 3 | G52: 4 | H52: 4 | I52: 3 | J52: 4 | K52: 3 | L52: 3 | M52: 5 | N52: 4 | O52: 2 | P52: 2 | Q52: 3 | R52: 3 | S52: 4 | T52: 3 | U52: 2 | V52: 3 | W52: 4 | X52: 4 | Y52: 3 | Z52: 3 | AA52: 3 | AB52: 2 | AC52: 2 | AD52: 3 | AE52: 4 | AF52: 4 | AG52: 4 | AH52: 3 | AI52: 3 | AJ52: 4 | AK52: 3 | AL52: 4 | AM52: 4 | AN52: 3 | AO52: 4 | AP52: 3 | AQ52: 3 | AR52: 2 | AS52: 3 | AT52: 4
A53: ID052 | B53: 5 | C53: 4 | D53: 4 | E53: 5 | F53: 2 | G53: 5 | H53: 5 | I53: 5 | J53: 4 | K53: 4 | L53: 4 | M53: 4 | N53: 5 | O53: 4 | P53: 5 | Q53: 4 | R53: 5 | S53: 4 | T53: 4 | U53: 4 | V53: 4 | W53: 4 | X53: 4 | Y53: 5 | Z53: 4 | AA53: 5 | AB53: 5 | AC53: 4 | AD53: 5 | AE53: 5 | AF53: 4 | AG53: 4 | AH53: 5 | AI53: 4 | AJ53: 4 | AK53: 4 | AL53: 4 | AM53: 5 | AN53: 4 | AO53: 5 | AP53: 4 | AQ53: 4 | AR53: 4 | AS53: 3 | AT53: 3
A54: ID053 | B54: 5 | C54: 4 | D54: 1 | E54: 3 | F54: 1 | G54: 4 | H54: 4 | I54: 4 | J54: 4 | K54: 4 | L54: 4 | M54: 3 | N54: 3 | O54: 3 | P54: 3 | Q54: 2 | R54: 4 | S54: 3 | T54: 3 | U54: 1 | V54: 2 | W54: 3 | X54: 4 | Y54: 3 | Z54: 2 | AA54: 3 | AB54: 3 | AC54: 4 | AD54: 5 | AE54: 1 | AF54: 2 | AG54: 3 | AH54: 2 | AI54: 3 | AJ54: 5 | AK54: 4 | AL54: 2 | AM54: 3 | AN54: 3 | AO54: 3 | AP54: 2 | AQ54: 2 | AR54: 4 | AS54: 3 | AT54: 5
A55: ID054 | B55: 4 | C55: 5 | D55: 3 | E55: 4 | F55: 4 | G55: 4 | H55: 5 | I55: 4 | J55: 4 | K55: 5 | L55: 4 | M55: 4 | N55: 4 | O55: 5 | P55: 5 | Q55: 5 | R55: 4 | S55: 5 | T55: 4 | U55: 4 | V55: 4 | W55: 4 | X55: 3 | Y55: 4 | Z55: 3 | AA55: 4 | AB55: 4 | AC55: 4 | AD55: 5 | AE55: 4 | AF55: 4 | AG55: 5 | AH55: 4 | AI55: 3 | AJ55: 4 | AK55: 5 | AL55: 4 | AM55: 5 | AN55: 4 | AO55: 4 | AP55: 3 | AQ55: 3 | AR55: 5 | AS55: 3 | AT55: 4
A56: ID055 | B56: 2 | C56: 3 | D56: 4 | E56: 2 | F56: 4 | G56: 3 | H56: 2 | I56: 3 | J56: 4 | K56: 3 | L56: 4 | M56: 5 | N56: 5 | O56: 3 | P56: 5 | Q56: 4 | R56: 5 | S56: 5 | T56: 4 | U56: 5 | V56: 3 | W56: 5 | X56: 5 | Y56: 3 | Z56: 4 | AA56: 4 | AB56: 3 | AC56: 3 | AD56: 4 | AE56: 3 | AF56: 3 | AG56: 3 | AH56: 4 | AI56: 3 | AJ56: 4 | AK56: 4 | AL56: 4 | AM56: 5 | AN56: 4 | AO56: 4 | AP56: 3 | AQ56: 3 | AR56: 3 | AS56: 3 | AT56: 5
A57: ID056 | B57: 1 | C57: 1 | D57: 1 | E57: 1 | F57: 1 | G57: 5 | H57: 5 | I57: 3 | J57: 2 | K57: 5 | L57: 5 | M57: 5 | N57: 4 | O57: 5 | P57: 5 | Q57: 5 | R57: 5 | S57: 5 | T57: 4 | U57: 4 | V57: 3 | W57: 1 | X57: 1 | Y57: 2 | Z57: 2 | AA57: 5 | AB57: 5 | AC57: 5 | AD57: 5 | AE57: 2 | AF57: 2 | AG57: 3 | AH57: 5 | AI57: 4 | AJ57: 5 | AK57: 3 | AL57: 4 | AM57: 5 | AN57: 4 | AO57: 5 | AP57: 2 | AQ57: 1 | AR57: 5 | AS57: 1 | AT57: 5
... A72: ID071 | B72: 4 | C72: 4 | D72: 3 | E72: 4 | F72: 4 | G72: 4 | H72: 4 | I72: 4 | J72: 4 | K72: 4 | L72: 4 | M72: 4 | N72: 4 | O72: 4 | P72: 4 | Q72: 4 | R72: 4 | S72: 4 | T72: 4 | U72: 4 | V72: 4 | W72: 4 | X72: 3 | Y72: 3 | Z72: 3 | AA72: 4 | AB72: 5 | AC72: 4 | AD72: 5 | AE72: 3 | AF72: 4 | AG72: 4 | AH72: 5 | AI72: 4 | AJ72: 4 | AK72: 4 | AL72: 4 | AM72: 4 | AN72: 5 | AO72: 5 | AP72: 4 | AQ72: 4 | AR72: 5 | AS72: 1 | AT72: 5
A73: ID072 | B73: 3 | C73: 3 | D73: 3 | E73: 3 | F73: 3 | G73: 3 | H73: 2 | I73: 3 | J73: 2 | K73: 3 | L73: 3 | M73: 3 | N73: 4 | O73: 4 | P73: 4 | Q73: 4 | R73: 5 | T73: 2 | U73: 2 | V73: 3 | W73: 3 | X73: 2 | Y73: 3 | Z73: 3 | AA73: 4 | AB73: 3 | AC73: 3 | AD73: 4 | AE73: 3 | AF73: 3 | AG73: 3 | AH73: 2 | AI73: 2 | AJ73: 4 | AK73: 5 | AL73: 4 | AM73: 5 | AN73: 5 | AO73: 2 | AP73: 2 | AQ73: 2 | AR73: 4 | AS73: 3 | AT73: 5
A74: ID073 | B74: 1 | C74: 1 | D74: 5 | E74: 1 | F74: 1 | G74: 5 | H74: 5 | I74: 5 | J74: 5 | K74: 5 | L74: 5 | M74: 5 | N74: 5 | O74: 4 | P74: 4 | Q74: 4 | R74: 4 | S74: 5 | T74: 5 | U74: 5 | V74: 5 | W74: 5 | X74: 5 | Y74: 5 | Z74: 3 | AA74: 3 | AB74: 3 | AC74: 5 | AD74: 5 | AE74: 3 | AF74: 3 | AG74: 1 | AH74: 1 | AI74: 1 | AJ74: 1 | AK74: 1 | AL74: 5 | AM74: 5 | AN74: 5 | AO74: 5 | AP74: 1 | AQ74: 1 | AR74: 1 | AS74: 3 | AT74: 4
A75: ID074 | B75: 4 | C75: 4 | D75: 1 | E75: 3 | F75: 3 | G75: 4 | H75: 4 | I75: 5 | J75: 4 | K75: 5 | L75: 3 | M75: 5 | N75: 5 | O75: 3 | P75: 5 | Q75: 3 | R75: 4 | S75: 5 | T75: 5 | U75: 4 | V75: 5 | W75: 4 | X75: 3 | Y75: 5 | Z75: 3 | AA75: 5 | AB75: 3 | AC75: 4 | AD75: 4 | AE75: 3 | AF75: 4 | AG75: 5 | AH75: 5 | AI75: 5 | AJ75: 3 | AK75: 2 | AL75: 5 | AM75: 5 | AN75: 5 | AO75: 4 | AP75: 3 | AQ75: 3 | AR75: 4 | AS75: 1 | AT75: 4
A76: ID075 | B76: 4 | C76: 4 | D76: 1 | E76: 3 | F76: 3 | G76: 4 | H76: 4 | I76: 3 | J76: 4 | K76: 5 | L76: 3 | M76: 5 | N76: 5 | O76: 3 | P76: 4 | Q76: 2 | R76: 4 | S76: 3 | T76: 3 | U76: 4 | V76: 5 | W76: 4 | X76: 3 | Y76: 5 | Z76: 3 | AA76: 5 | AB76: 4 | AC76: 4 | AD76: 4 | AE76: 4 | AF76: 5 | AG76: 2 | AH76: 2 | AI76: 2 | AJ76: 5 | AK76: 3 | AL76: 4 | AM76: 4 | AN76: 4 | AO76: 4 | AP76: 3 | AQ76: 3 | AR76: 4 | AS76: 3 | AT76: 4
A77: ID076 | B77: 3 | C77: 1 | D77: 1 | E77: 2 | F77: 1 | G77: 1 | H77: 1 | I77: 3 | J77: 1 | K77: 5 | L77: 1 | M77: 3 | N77: 1 | O77: 5 | P77: 4 | Q77: 2 | R77: 5 | S77: 1 | T77: 1 | U77: 3 | V77: 5 | W77: 3 | X77: 3 | Y77: 2 | Z77: 3 | AA77: 3 | AB77: 5 | AC77: 5 | AD77: 5 | AE77: 5 | AF77: 2 | AG77: 5 | AH77: 2 | AI77: 2 | AJ77: 1 | AK77: 4 | AL77: 5 | AM77: 5 | AN77: 5 | AO77: 1 | AP77: 2 | AQ77: 2 | AR77: 5 | AS77: 1 | AT77: 3
A78: ID077 | B78: 5 | C78: 3 | D78: 3 | E78: 3 | F78: 2 | G78: 5 | H78: 4 | I78: 4 | J78: 4 | K78: 4 | L78: 4 | M78: 5 | N78: 4 | O78: 3 | P78: 3 | Q78: 2 | R78: 3 | S78: 5 | T78: 5 | U78: 5 | V78: 5 | W78: 5 | X78: 5 | Y78: 5 | Z78: 4 | AA78: 5 | AB78: 4 | AC78: 4 | AD78: 5 | AE78: 5 | AF78: 4 | AG78: 5 | AH78: 5 | AI78: 5 | AJ78: 5 | AK78: 4 | AL78: 5 | AM78: 5 | AN78: 5 | AO78: 5 | AP78: 3 | AQ78: 3 | AR78: 4 | AS78: 2 | AT78: 3
A79: ID078 | B79: 5 | C79: 3 | D79: 2 | E79: 3 | F79: 5 | G79: 3 | H79: 3 | I79: 3 | J79: 4 | K79: 4 | L79: 5 | M79: 4 | N79: 5 | O79: 4 | P79: 3 | Q79: 3 | R79: 3 | S79: 5 | T79: 5 | U79: 5 | V79: 4 | W79: 5 | X79: 5 | Y79: 4 | Z79: 4 | AA79: 4 | AB79: 4 | AC79: 4 | AD79: 5 | AE79: 4 | AF79: 3 | AG79: 3 | AH79: 3 | AI79: 5 | AJ79: 5 | AK79: 5 | AL79: 4 | AM79: 4 | AN79: 4 | AO79: 5 | AP79: 3 | AQ79: 3 | AR79: 5 | AS79: 2 | AT79: 5
A80: ID079 | B80: 2 | C80: 2 | D80: 2 | E80: 2 | F80: 1 | G80: 3 | H80: 3 | I80: 1 | J80: 1 | K80: 1 | L80: 1 | M80: 2 | N80: 3 | O80: 3 | P80: 3 | Q80: 1 | R80: 3 | S80: 2 | T80: 1 | U80: 2 | V80: 3 | W80: 3 | X80: 4 | Y80: 2 | Z80: 1 | AA80: 2 | AB80: 1 | AC80: 3 | AD80: 4 | AE80: 2 | AF80: 1 | AG80: 2 | AH80: 1 | AI80: 2 | AJ80: 3 | AK80: 3 | AL80: 5 | AM80: 5 | AN80: 4 | AO80: 4 | AP80: 1 | AQ80: 2 | AR80: 3 | AS80: 1 | AT80: 5
A81: ID080 | B81: 3 | C81: 4 | D81: 2 | E81: 2 | F81: 3 | G81: 4 | H81: 4 | I81: 4 | J81: 5 | K81: 3 | L81: 5 | M81: 4 | N81: 5 | O81: 5 | P81: 5 | Q81: 3 | R81: 2 | S81: 4 | T81: 4 | U81: 4 | V81: 4 | W81: 4 | X81: 3 | Y81: 4 | Z81: 3 | AA81: 4 | AB81: 5 | AC81: 5 | AD81: 5 | AE81: 4 | AF81: 3 | AG81: 3 | AH81: 3 | AI81: 3 | AJ81: 3 | AK81: 3 | AL81: 3 | AM81: 4 | AN81: 5 | AO81: 3 | AP81: 2 | AQ81: 3 | AR81: 4 | AS81: 1 | AT81: 5
A82: ID081 | B82: 2 | C82: 2 | D82: 3 | E82: 4 | F82: 5 | G82: 5 | H82: 5 | I82: 4 | J82: 5 | K82: 5 | L82: 4 | M82: 4 | N82: 5 | O82: 4 | P82: 4 | Q82: 4 | R82: 4 | S82: 3 | T82: 4 | U82: 4 | V82: 2 | W82: 4 | X82: 4 | Y82: 4 | Z82: 4 | AA82: 5 | AB82: 5 | AC82: 5 | AD82: 4 | AE82: 5 | AF82: 5 | AG82: 5 | AH82: 4 | AI82: 4 | AJ82: 4 | AK82: 4 | AL82: 5 | AM82: 5 | AN82: 4 | AO82: 4 | AP82: 2 | AQ82: 2 | AR82: 3 | AS82: 1 | AT82: 5
A83: ID082 | B83: 4 | C83: 1 | D83: 2 | E83: 3 | F83: 4 | G83: 5 | H83: 5 | I83: 5 | J83: 3 | K83: 3 | L83: 4 | M83: 5 | N83: 5 | O83: 4 | P83: 1 | Q83: 1 | R83: 1 | S83: 5 | T83: 4 | U83: 5 | V83: 3 | W83: 1 | X83: 1 | Y83: 3 | Z83: 2 | AA83: 3 | AB83: 4 | AC83: 4 | AD83: 4 | AE83: 4 | AF83: 4 | AG83: 4 | AH83: 3 | AI83: 2 | AJ83: 1 | AK83: 1 | AL83: 5 | AM83: 5 | AN83: 5 | AO83: 2 | AP83: 1 | AQ83: 1 | AR83: 3 | AS83: 1 | AT83: 5
A84: ID083 | B84: 4 | C84: 5 | D84: 3 | E84: 4 | F84: 4 | G84: 4 | H84: 4 | I84: 4 | J84: 4 | K84: 4 | L84: 4 | M84: 4 | N84: 4 | O84: 5 | P84: 5 | Q84: 5 | R84: 5 | S84: 5 | T84: 5 | U84: 4 | V84: 4 | W84: 5 | X84: 4 | Y84: 5 | Z84: 3 | AA84: 4 | AB84: 4 | AC84: 4 | AD84: 4 | AE84: 5 | AF84: 5 | AG84: 4 | AH84: 4 | AI84: 3 | AJ84: 4 | AK84: 5 | AL84: 4 | AM84: 4 | AN84: 4 | AO84: 2 | AP84: 4 | AQ84: 3 | AR84: 3 | AS84: 3 | AT84: 5
A85: ID084 | B85: 3 | C85: 4 | D85: 4 | E85: 3 | F85: 2 | G85: 4 | H85: 4 | I85: 4 | J85: 4 | K85: 4 | L85: 3 | M85: 3 | N85: 3 | O85: 3 | P85: 2 | Q85: 1 | R85: 4 | S85: 4 | T85: 2 | U85: 3 | V85: 3 | W85: 1 | X85: 4 | Y85: 1 | Z85: 2 | AA85: 4 | AB85: 3 | AC85: 3 | AD85: 4 | AE85: 3 | AF85: 1 | AG85: 3 | AH85: 3 | AI85: 4 | AJ85: 4 | AK85: 4 | AL85: 4 | AM85: 5 | AN85: 4 | AO85: 3 | AP85: 2 | AQ85: 2 | AR85: 4 | AS85: 3 | AT85: 4
... A115: ID114 | B115: 4 | C115: 5 | D115: 3 | E115: 3 | F115: 3 | G115: 4 | H115: 4 | I115: 5 | J115: 3 | K115: 2 | L115: 4 | M115: 5 | N115: 5 | O115: 4 | P115: 1 | Q115: 2 | R115: 1 | S115: 4 | T115: 2 | U115: 2 | V115: 2 | W115: 1 | X115: 3 | Y115: 2 | Z115: 1 | AA115: 1 | AB115: 1 | AC115: 2 | AD115: 4 | AE115: 2 | AF115: 3 | AG115: 5 | AH115: 2 | AI115: 2 | AJ115: 4 | AK115: 4 | AL115: 4 | AM115: 4 | AN115: 4 | AO115: 3 | AP115: 2 | AQ115: 5 | AR115: 5 | AS115: 2 | AT115: 2
A116: ID115 | B116: 3 | C116: 3 | D116: 3 | E116: 3 | F116: 3 | G116: 3 | H116: 2 | I116: 3 | J116: 2 | K116: 3 | L116: 3 | M116: 3 | N116: 4 | O116: 4 | P116: 4 | Q116: 4 | R116: 5 | T116: 2 | U116: 2 | V116: 3 | W116: 3 | X116: 2 | Y116: 3 | Z116: 3 | AA116: 4 | AB116: 3 | AC116: 3 | AD116: 4 | AE116: 3 | AF116: 3 | AG116: 3 | AH116: 2 | AI116: 2 | AJ116: 4 | AK116: 5 | AL116: 4 | AM116: 5 | AN116: 5 | AO116: 2 | AP116: 2 | AQ116: 2 | AR116: 4 | AS116: 3 | AT116: 5
A117: ID116 | B117: 4 | C117: 4 | D117: 4 | E117: 4 | F117: 3 | G117: 4 | H117: 4 | I117: 4 | J117: 3 | K117: 4 | L117: 4 | M117: 4 | N117: 4 | O117: 4 | P117: 4 | Q117: 3 | R117: 3 | S117: 5 | T117: 5 | U117: 5 | V117: 3 | W117: 3 | X117: 3 | Y117: 4 | Z117: 3 | AA117: 4 | AB117: 4 | AC117: 4 | AD117: 4 | AE117: 4 | AF117: 4 | AG117: 3 | AH117: 3 | AI117: 3 | AJ117: 3 | AK117: 3 | AL117: 4 | AM117: 3 | AN117: 3 | AO117: 3 | AP117: 4 | AQ117: 4 | AR117: 5 | AS117: 3 | AT117: 4
A118: ID117 | B118: 2 | C118: 4 | D118: 4 | E118: 3 | F118: 2 | G118: 4 | H118: 4 | I118: 3 | J118: 4 | K118: 4 | L118: 5 | M118: 5 | N118: 4 | O118: 2 | P118: 2 | Q118: 2 | R118: 4 | S118: 2 | T118: 2 | U118: 2 | V118: 2 | W118: 5 | X118: 3 | Y118: 2 | Z118: 3 | AA118: 4 | AB118: 4 | AC118: 4 | AD118: 2 | AE118: 2 | AF118: 3 | AG118: 2 | AH118: 2 | AI118: 3 | AJ118: 5 | AK118: 2 | AL118: 2 | AM118: 2 | AN118: 2 | AO118: 5 | AP118: 3 | AQ118: 4 | AR118: 3 | AS118: 2 | AT118: 5
A119: ID118 | B119: 1 | C119: 1 | D119: 1 | E119: 1 | F119: 2 | G119: 3 | H119: 3 | I119: 3 | J119: 3 | K119: 3 | L119: 4 | M119: 5 | N119: 5 | O119: 4 | P119: 4 | Q119: 5 | R119: 5 | S119: 4 | T119: 4 | U119: 5 | V119: 4 | W119: 5 | X119: 5 | Y119: 4 | Z119: 4 | AA119: 4 | AB119: 4 | AC119: 4 | AD119: 5 | AE119: 4 | AF119: 2 | AG119: 1 | AH119: 4 | AI119: 4 | AJ119: 4 | AK119: 4 | AL119: 4 | AM119: 4 | AN119: 4 | AO119: 4 | AP119: 3 | AQ119: 3 | AR119: 4 | AS119: 1 | AT119: 5
A120: ID119 | B120: 4 | C120: 5 | D120: 3 | E120: 5 | F120: 5 | G120: 4 | H120: 4 | I120: 4 | J120: 3 | K120: 4 | L120: 4 | M120: 4 | N120: 5 | O120: 5 | P120: 5 | Q120: 4 | R120: 5 | S120: 4 | T120: 4 | U120: 5 | V120: 5 | W120: 5 | X120: 2 | Y120: 4 | Z120: 3 | AA120: 4 | AB120: 5 | AC120: 3 | AD120: 4 | AE120: 4 | AF120: 5 | AG120: 2 | AH120: 4 | AI120: 4 | AJ120: 4 | AK120: 5 | AL120: 4 | AM120: 4 | AN120: 4 | AO120: 5 | AP120: 4 | AQ120: 4 | AR120: 4 | AS120: 3 | AT120: 5
A121: ID120 | B121: 1 | C121: 1 | D121: 1 | E121: 1 | F121: 2 | G121: 3 | H121: 3 | I121: 3 | J121: 3 | K121: 3 | L121: 4 | M121: 5 | N121: 5 | O121: 4 | P121: 4 | Q121: 5 | R121: 5 | S121: 4 | T121: 4 | U121: 5 | V121: 4 | W121: 5 | X121: 5 | Y121: 4 | Z121: 4 | AA121: 4 | AB121: 4 | AC121: 4 | AD121: 5 | AE121: 4 | AF121: 2 | AG121: 1 | AH121: 4 | AI121: 4 | AJ121: 4 | AK121: 4 | AL121: 4 | AM121: 4 | AN121: 4 | AO121: 4 | AP121: 3 | AQ121: 3 | AR121: 4 | AS121: 1 | AT121: 3
A122: ID121 | B122: 2 | C122: 2 | D122: 3 | E122: 3 | F122: 4 | G122: 4 | H122: 4 | I122: 3 | J122: 3 | K122: 3 | L122: 4 | M122: 4 | N122: 4 | O122: 3 | P122: 3 | Q122: 3 | R122: 4 | S122: 4 | T122: 3 | U122: 4 | V122: 5 | W122: 4 | X122: 3 | Y122: 3 | Z122: 5 | AA122: 4 | AB122: 2 | AC122: 3 | AD122: 3 | AE122: 3 | AF122: 3 | AG122: 4 | AH122: 5 | AI122: 5 | AJ122: 4 | AK122: 4 | AL122: 5 | AM122: 5 | AN122: 5 | AO122: 4 | AP122: 2 | AQ122: 2 | AR122: 3 | AS122: 2 | AT122: 4
A123: ID122 | B123: 4 | C123: 3 | D123: 3 | E123: 3 | F123: 3 | G123: 4 | H123: 4 | I123: 5 | J123: 4 | K123: 5 | L123: 4 | M123: 5 | N123: 4 | O123: 4 | P123: 4 | Q123: 3 | R123: 4 | S123: 4 | T123: 3 | U123: 4 | V123: 4 | W123: 3 | X123: 2 | Y123: 1 | Z123: 5 | AA123: 3 | AB123: 4 | AC123: 2 | AD123: 3 | AE123: 4 | AF123: 3 | AG123: 4 | AH123: 3 | AI123: 3 | AJ123: 3 | AK123: 4 | AL123: 5 | AM123: 5 | AN123: 5 | AO123: 5 | AP123: 1 | AQ123: 2 | AR123: 3 | AS123: 1 | AT123: 5
A124: ID123 | B124: 4 | C124: 5 | D124: 3 | E124: 3 | F124: 3 | G124: 4 | H124: 4 | I124: 5 | J124: 3 | K124: 2 | L124: 4 | M124: 5 | N124: 5 | O124: 4 | P124: 1 | Q124: 2 | R124: 1 | S124: 4 | T124: 2 | U124: 2 | V124: 2 | W124: 1 | X124: 3 | Y124: 2 | Z124: 1 | AA124: 1 | AB124: 1 | AC124: 2 | AD124: 4 | AE124: 2 | AF124: 3 | AG124: 5 | AH124: 2 | AI124: 2 | AJ124: 4 | AK124: 4 | AL124: 4 | AM124: 4 | AN124: 4 | AO124: 3 | AP124: 2 | AQ124: 5 | AR124: 5 | AS124: 2 | AT124: 5
A125: ID124 | B125: 4 | C125: 5 | D125: 3 | E125: 5 | F125: 4 | G125: 4 | H125: 4 | I125: 4 | J125: 3 | K125: 3 | L125: 5 | M125: 5 | N125: 4 | O125: 2 | P125: 3 | Q125: 4 | R125: 4 | S125: 4 | T125: 5 | U125: 4 | V125: 4 | W125: 5 | X125: 5 | Y125: 4 | Z125: 3 | AA125: 4 | AB125: 3 | AC125: 4 | AD125: 5 | AE125: 4 | AF125: 5 | AG125: 5 | AH125: 4 | AI125: 4 | AJ125: 5 | AK125: 4 | AL125: 4 | AM125: 4 | AN125: 2 | AO125: 4 | AP125: 5 | AQ125: 5 | AR125: 4 | AS125: 2 | AT125: 3
A126: ID125 | B126: 1 | C126: 1 | D126: 1 | E126: 1 | F126: 2 | G126: 3 | H126: 3 | I126: 3 | J126: 3 | K126: 3 | L126: 4 | M126: 5 | N126: 5 | O126: 4 | P126: 4 | Q126: 5 | R126: 5 | S126: 4 | T126: 4 | U126: 5 | V126: 4 | W126: 5 | X126: 5 | Y126: 4 | Z126: 4 | AA126: 4 | AB126: 4 | AC126: 4 | AD126: 5 | AE126: 4 | AF126: 2 | AG126: 1 | AH126: 4 | AI126: 4 | AJ126: 4 | AK126: 4 | AL126: 4 | AM126: 4 | AN126: 4 | AO126: 4 | AP126: 3 | AQ126: 3 | AR126: 4 | AS126: 1 | AT126: 5
A127: ID126 | B127: 4 | C127: 5 | D127: 3 | E127: 3 | F127: 3 | G127: 4 | H127: 4 | I127: 5 | J127: 3 | K127: 2 | L127: 4 | M127: 5 | N127: 5 | O127: 4 | P127: 1 | Q127: 2 | R127: 1 | S127: 4 | T127: 2 | U127: 2 | V127: 2 | W127: 1 | X127: 3 | Y127: 2 | Z127: 1 | AA127: 1 | AB127: 1 | AC127: 2 | AD127: 4 | AE127: 2 | AF127: 3 | AG127: 5 | AH127: 2 | AI127: 2 | AJ127: 4 | AK127: 4 | AL127: 4 | AM127: 4 | AN127: 4 | AO127: 3 | AP127: 2 | AQ127: 5 | AR127: 5 | AS127: 2 | AT127: 5
A128: ID127 | B128: 4 | C128: 3 | D128: 3 | E128: 3 | F128: 3 | G128: 4 | H128: 4 | I128: 5 | J128: 4 | K128: 5 | L128: 4 | M128: 5 | N128: 4 | O128: 4 | P128: 4 | Q128: 3 | R128: 4 | S128: 4 | T128: 3 | U128: 4 | V128: 4 | W128: 3 | X128: 2 | Y128: 1 | Z128: 5 | AA128: 3 | AB128: 4 | AC128: 2 | AD128: 3 | AE128: 4 | AF128: 3 | AG128: 4 | AH128: 3 | AI128: 3 | AJ128: 3 | AK128: 4 | AL128: 5 | AM128: 5 | AN128: 5 | AO128: 5 | AP128: 1 | AQ128: 2 | AR128: 3 | AS128: 1 | AT128: 4
A129: ID128 | B129: 3 | C129: 3 | D129: 3 | E129: 3 | F129: 3 | G129: 3 | H129: 2 | I129: 3 | J129: 2 | K129: 3 | L129: 3 | M129: 3 | N129: 4 | O129: 4 | P129: 4 | Q129: 4 | R129: 5 | T129: 2 | U129: 2 | V129: 3 | W129: 3 | X129: 2 | Y129: 3 | Z129: 3 | AA129: 4 | AB129: 3 | AC129: 3 | AD129: 4 | AE129: 3 | AF129: 3 | AG129: 3 | AH129: 2 | AI129: 2 | AJ129: 4 | AK129: 5 | AL129: 4 | AM129: 5 | AN129: 5 | AO129: 2 | AP129: 2 | AQ129: 2 | AR129: 4 | AS129: 3 | AT129: 4
A130: ID129 | B130: 4 | C130: 4 | D130: 3 | E130: 4 | F130: 4 | G130: 4 | H130: 4 | I130: 4 | J130: 4 | K130: 4 | L130: 4 | M130: 4 | N130: 4 | O130: 4 | P130: 4 | Q130: 4 | R130: 4 | S130: 4 | T130: 4 | U130: 4 | V130: 4 | W130: 4 | X130: 3 | Y130: 3 | Z130: 3 | AA130: 4 | AB130: 5 | AC130: 4 | AD130: 5 | AE130: 3 | AF130: 4 | AG130: 4 | AH130: 5 | AI130: 4 | AJ130: 4 | AK130: 4 | AL130: 4 | AM130: 4 | AN130: 5 | AO130: 5 | AP130: 4 | AQ130: 4 | AR130: 5 | AS130: 3 | AT130: 5
A131: ID130 | B131: 2 | C131: 2 | D131: 3 | E131: 3 | F131: 1 | G131: 2 | H131: 3 | I131: 3 | J131: 2 | K131: 2 | L131: 3 | M131: 2 | N131: 3 | O131: 4 | P131: 4 | Q131: 1 | R131: 4 | S131: 3 | T131: 3 | U131: 3 | V131: 3 | W131: 3 | X131: 4 | Y131: 3 | Z131: 3 | AA131: 3 | AB131: 2 | AC131: 2 | AD131: 5 | AE131: 4 | AF131: 1 | AG131: 4 | AH131: 3 | AI131: 3 | AJ131: 3 | AK131: 4 | AL131: 4 | AM131: 4 | AN131: 3 | AO131: 3 | AP131: 1 | AQ131: 1 | AR131: 2 | AS131: 2 | AT131: 3
A132: ID131 | B132: 3 | C132: 4 | D132: 2 | E132: 2 | F132: 3 | G132: 4 | H132: 4 | I132: 4 | J132: 5 | K132: 3 | L132: 5 | M132: 4 | N132: 5 | O132: 5 | P132: 5 | Q132: 3 | R132: 2 | S132: 4 | T132: 4 | U132: 4 | V132: 4 | W132: 4 | X132: 3 | Y132: 4 | Z132: 3 | AA132: 4 | AB132: 5 | AC132: 5 | AD132: 5 | AE132: 4 | AF132: 3 | AG132: 3 | AH132: 3 | AI132: 3 | AJ132: 3 | AK132: 3 | AL132: 3 | AM132: 4 | AN132: 5 | AO132: 3 | AP132: 2 | AQ132: 3 | AR132: 4 | AS132: 1 | AT132: 5
A133: ID132 | B133: 2 | C133: 2 | D133: 2 | E133: 2 | F133: 1 | G133: 3 | H133: 3 | I133: 1 | J133: 1 | K133: 1 | L133: 1 | M133: 2 | N133: 3 | O133: 3 | P133: 3 | Q133: 1 | R133: 3 | S133: 2 | T133: 1 | U133: 2 | V133: 3 | W133: 3 | X133: 4 | Y133: 2 | Z133: 1 | AA133: 2 | AB133: 1 | AC133: 3 | AD133: 4 | AE133: 2 | AF133: 1 | AG133: 2 | AH133: 1 | AI133: 2 | AJ133: 3 | AK133: 3 | AL133: 5 | AM133: 5 | AN133: 4 | AO133: 4 | AP133: 1 | AQ133: 2 | AR133: 3 | AS133: 1 | AT133: 2
A134: ID133 | B134: 3 | C134: 1 | D134: 1 | E134: 2 | F134: 1 | G134: 1 | H134: 1 | I134: 3 | J134: 1 | K134: 5 | L134: 1 | M134: 3 | N134: 1 | O134: 5 | P134: 4 | Q134: 2 | R134: 5 | S134: 1 | T134: 1 | U134: 3 | V134: 5 | W134: 3 | X134: 3 | Y134: 2 | Z134: 3 | AA134: 3 | AB134: 5 | AC134: 5 | AD134: 5 | AE134: 5 | AF134: 2 | AG134: 5 | AH134: 2 | AI134: 2 | AJ134: 1 | AK134: 4 | AL134: 5 | AM134: 5 | AN134: 5 | AO134: 1 | AP134: 2 | AQ134: 2 | AR134: 5 | AS134: 1 | AT134: 3
A135: ID134 | B135: 4 | C135: 4 | D135: 1 | E135: 3 | F135: 3 | G135: 4 | H135: 4 | I135: 5 | J135: 4 | K135: 5 | L135: 3 | M135: 5 | N135: 5 | O135: 3 | P135: 5 | Q135: 3 | R135: 4 | S135: 5 | T135: 5 | U135: 4 | V135: 5 | W135: 4 | X135: 3 | Y135: 5 | Z135: 3 | AA135: 5 | AB135: 3 | AC135: 4 | AD135: 4 | AE135: 3 | AF135: 4 | AG135: 5 | AH135: 5 | AI135: 5 | AJ135: 3 | AK135: 2 | AL135: 5 | AM135: 5 | AN135: 5 | AO135: 4 | AP135: 3 | AQ135: 3 | AR135: 4 | AS135: 3 | AT135: 4
A136: ID135 | B136: 3 | C136: 3 | D136: 3 | E136: 3 | F136: 3 | G136: 3 | H136: 2 | I136: 3 | J136: 2 | K136: 3 | L136: 3 | M136: 3 | N136: 4 | O136: 4 | P136: 4 | Q136: 4 | R136: 5 | T136: 2 | U136: 2 | V136: 3 | W136: 3 | X136: 2 | Y136: 3 | Z136: 3 | AA136: 4 | AB136: 3 | AC136: 3 | AD136: 4 | AE136: 3 | AF136: 3 | AG136: 3 | AH136: 2 | AI136: 2 | AJ136: 4 | AK136: 5 | AL136: 4 | AM136: 5 | AN136: 5 | AO136: 2 | AP136: 2 | AQ136: 2 | AR136: 4 | AS136: 3 | AT136: 5
A137: ID136 | B137: 4 | C137: 4 | D137: 3 | E137: 4 | F137: 4 | G137: 4 | H137: 4 | I137: 4 | J137: 4 | K137: 4 | L137: 4 | M137: 4 | N137: 4 | O137: 4 | P137: 4 | Q137: 4 | R137: 4 | S137: 4 | T137: 4 | U137: 4 | V137: 4 | W137: 4 | X137: 3 | Y137: 3 | Z137: 3 | AA137: 4 | AB137: 5 | AC137: 4 | AD137: 5 | AE137: 3 | AF137: 4 | AG137: 4 | AH137: 5 | AI137: 4 | AJ137: 4 | AK137: 4 | AL137: 4 | AM137: 4 | AN137: 5 | AO137: 5 | AP137: 4 | AQ137: 4 | AR137: 5 | AS137: 2 | AT137: 1
A138: ID137 | B138: 4 | C138: 5 | D138: 4 | E138: 3 | F138: 4 | G138: 4 | H138: 4 | I138: 4 | J138: 4 | K138: 4 | L138: 5 | M138: 5 | N138: 5 | O138: 3 | P138: 4 | Q138: 4 | R138: 5 | S138: 4 | T138: 4 | U138: 4 | V138: 4 | W138: 4 | X138: 5 | Y138: 4 | Z138: 4 | AA138: 4 | AB138: 5 | AC138: 5 | AD138: 4 | AE138: 4 | AF138: 4 | AG138: 3 | AH138: 4 | AI138: 4 | AJ138: 5 | AK138: 4 | AL138: 4 | AM138: 5 | AN138: 5 | AO138: 4 | AP138: 4 | AQ138: 3 | AR138: 4 | AS138: 2 | AT138: 3
A139: ID138 | B139: 2 | C139: 2 | D139: 3 | E139: 3 | F139: 1 | G139: 2 | H139: 3 | I139: 3 | J139: 2 | K139: 2 | L139: 3 | M139: 2 | N139: 3 | O139: 4 | P139: 4 | Q139: 1 | R139: 4 | S139: 3 | T139: 3 | U139: 3 | V139: 3 | W139: 3 | X139: 4 | Y139: 3 | Z139: 3 | AA139: 3 | AB139: 2 | AC139: 2 | AD139: 5 | AE139: 4 | AF139: 1 | AG139: 4 | AH139: 3 | AI139: 3 | AJ139: 3 | AK139: 4 | AL139: 4 | AM139: 4 | AN139: 3 | AO139: 3 | AP139: 1 | AQ139: 1 | AR139: 2 | AS139: 2 | AT139: 3
A140: ID139 | B140: 5 | C140: 3 | D140: 2 | E140: 3 | F140: 5 | G140: 5 | H140: 5 | I140: 5 | J140: 5 | K140: 4 | L140: 5 | M140: 5 | N140: 5 | O140: 5 | P140: 5 | Q140: 4 | R140: 4 | S140: 5 | T140: 5 | U140: 5 | V140: 5 | W140: 4 | X140: 5 | Y140: 5 | Z140: 4 | AA140: 4 | AB140: 4 | AC140: 5 | AD140: 5 | AE140: 4 | AF140: 4 | AG140: 4 | AH140: 5 | AI140: 5 | AJ140: 4 | AK140: 5 | AL140: 5 | AM140: 5 | AN140: 5 | AO140: 4 | AP140: 4 | AQ140: 4 | AR140: 5 | AS140: 1 | AT140: 5
A141: ID140 | B141: 3 | C141: 3 | D141: 3 | E141: 3 | F141: 3 | G141: 4 | H141: 4 | I141: 4 | J141: 4 | K141: 4 | L141: 4 | M141: 4 | N141: 4 | O141: 3 | P141: 2 | Q141: 4 | R141: 2 | S141: 4 | T141: 4 | U141: 4 | V141: 4 | W141: 4 | X141: 4 | Y141: 5 | Z141: 4 | AA141: 4 | AB141: 3 | AC141: 3 | AD141: 3 | AE141: 4 | AF141: 4 | AG141: 4 | AH141: 4 | AI141: 4 | AJ141: 4 | AK141: 4 | AL141: 3 | AM141: 3 | AN141: 3 | AO141: 3 | AP141: 3 | AQ141: 3 | AR141: 3 | AS141: 2 | AT141: 5
A142: ID141 | B142: 3 | C142: 2 | D142: 3 | E142: 3 | F142: 3 | G142: 4 | H142: 4 | I142: 3 | J142: 4 | K142: 3 | L142: 3 | M142: 5 | N142: 4 | O142: 2 | P142: 2 | Q142: 3 | R142: 2 | S142: 4 | T142: 3 | U142: 2 | V142: 3 | W142: 4 | X142: 4 | Y142: 3 | Z142: 3 | AA142: 3 | AB142: 2 | AC142: 2 | AD142: 3 | AE142: 4 | AF142: 4 | AG142: 4 | AH142: 3 | AI142: 3 | AJ142: 4 | AK142: 3 | AL142: 4 | AM142: 4 | AN142: 3 | AO142: 4 | AP142: 3 | AQ142: 3 | AR142: 2 | AS142: 2 | AT142: 4
A143: ID142 | B143: 3 | C143: 2 | D143: 3 | E143: 3 | F143: 3 | G143: 4 | H143: 4 | I143: 3 | J143: 4 | K143: 3 | L143: 3 | M143: 5 | N143: 4 | O143: 2 | P143: 2 | Q143: 3 | R143: 2 | S143: 4 | T143: 3 | U143: 2 | V143: 3 | W143: 4 | X143: 4 | Y143: 3 | Z143: 3 | AA143: 3 | AB143: 2 | AC143: 2 | AD143: 3 | AE143: 4 | AF143: 4 | AG143: 4 | AH143: 3 | AI143: 3 | AJ143: 4 | AK143: 3 | AL143: 4 | AM143: 4 | AN143: 3 | AO143: 4 | AP143: 3 | AQ143: 3 | AR143: 2 | AS143: 2 | AT143: 4
A144: ID143 | B144: 2 | C144: 2 | D144: 3 | E144: 2 | F144: 1 | G144: 2 | H144: 2 | I144: 3 | J144: 2 | K144: 3 | L144: 2 | M144: 3 | N144: 2 | O144: 4 | P144: 4 | Q144: 2 | R144: 3 | S144: 2 | T144: 2 | U144: 2 | V144: 2 | W144: 2 | X144: 4 | Y144: 2 | Z144: 2 | AA144: 2 | AB144: 2 | AC144: 3 | AD144: 3 | AE144: 3 | AF144: 2 | AG144: 3 | AH144: 4 | AI144: 2 | AJ144: 4 | AK144: 3 | AL144: 4 | AM144: 4 | AN144: 3 | AO144: 2 | AP144: 2 | AQ144: 2 | AR144: 4 | AS144: 3 | AT144: 5

Sheet 3rd iteration
A1: Factor Analysis - Principal Component Extraction
B5: 1.Delay in delivering material to construction site | C5: 2.Monopoly of material by some suppliers | D5: 3.Prices fluctuation | E5: 4.Types of material availability at local market | F5: 5.Lack of consultant’s knowledge of available materials | G5: 6.Low productivity | H5: 7.Poor work execution | I5: 8.Shortage of laborers | J5: 9.Mistakes happens during construction phase | K5: 10.Unavailability of equipment | L5: 11.Lack of engineering experience | M5: 12.Construction cost underestimation | N5: 13.Poor site management | O5: 14.Delayed payment for completed work | P5: 15.Cash flow problem during construction | Q5: 16.High rate of interest | R5: 17.Contractor’s financial difficulties | S5: 19.Change design | T5: 20.Errors and omission in design | U5: 21.Incomplete design drawings and specifications at tendering stage | V5: 22.Delay in preparation and approval of drawing | W5: 23.Inaccurate quantity take-off | X5: 24.Long period from planning of project to construction | Y5: 25.Delays in issuing information to the contractor during construction stage | Z5: 26.No practical use of earned value management system | AA5: 27.Lack of cost planning/monitoring during pre and post contract stage | AB5: 28.Poor communication between client, consultant and contractor | AC5: 29.Insufficient coordination between local authority who is responsible about road projects and service authorities | AD5: 30.Delays in decisions making by the approval authorities | AE5: 31.Change schedule | AF5: 32.Stoppages because of work being rejected by consultant | AG5: 33.Lowest bid price | AH5: 34.Insufficient time for preparation of contract documents | AI5: 35.Discrepancies in contract documents | AJ5: 36.Underestimation of time for completion of project | AK5: 37.Extension of time with cost claims | AL5: 38.Scope and specification changes | AM5: 39.Changes in client requirements | AN5: 40.Frequency of variation orders and additional works | AO5: 41.Rework due to error in execution | AP5: 42.Weather conditions | AQ5: 43.Accidents during construction | AR5: 44.Delay in getting NOCs from different government authorities | AS5: Location of organization | AT5: Relevant working experience
A6: Mean | B6: 3.08 | C6: 2.99 | D6: 2.74 | E6: 2.92 | F6: 2.83 | G6: 3.45 | H6: 3.53 | I6: 3.41 | J6: 3.33 | K6: 3.42 | L6: 3.51 | M6: 3.79 | N6: 3.77 | O6: 3.61 | P6: 3.63 | Q6: 3.17 | R6: 3.58 | S6: 3.81 | T6: 3.47 | U6: 3.52 | V6: 3.62 | W6: 3.64 | X6: 3.48 | Y6: 3.25 | Z6: 3.06 | AA6: 3.46 | AB6: 3.32 | AC6: 3.55 | AD6: 4.03 | AE6: 3.28 | AF6: 3.1 | AG6: 3.28 | AH6: 3.18 | AI6: 3.19 | AJ6: 3.66 | AK6: 3.65 | AL6: 3.94 | AM6: 4.07 | AN6: 3.91 | AO6: 3.56 | AP6: 2.49 | AQ6: 2.7 | AR6: 3.66 | AS6: 2.15 | AT6: 4.05
A7: Std dev | B7: 1.261996 | C7: 1.334781 | D7: 1.117803 | E7: 1.058144 | F7: 1.255893 | G7: 1.092402 | H7: 1.191544 | I7: 1.114803 | J7: 1.208982 | K7: 1.171328 | L7: 1.18004 | M7: 1.203593 | N7: 1.220092 | O7: 0.993181 | P7: 1.123866 | Q7: 1.227536 | R7: 1.1653 | S7: 1.00634 | T7: 1.143285 | U7: 1.073714 | V7: 0.991543 | W7: 0.996794 | X7: 0.998965 | Y7: 1.010289 | Z7: 0.984215 | AA7: 0.976983 | AB7: 1.236769 | AC7: 1.066304 | AD7: 0.934051 | AE7: 1.030558 | AF7: 1.09874 | AG7: 1.22252 | AH7: 1.142251 | AI7: 1.047808 | AJ7: 0.992536 | AK7: 0.994766 | AL7: 0.902081 | AM7: 0.954237 | AN7: 0.910882 | AO7: 1.03884 | AP7: 1.026872 | AQ7: 1.132335 | AR7: 1.100218 | AS7: 0.824858 | AT7: 1.121673
A8: Skewness | B8: -0.35981 | C8: 0.012937 | D8: -0.17796 | E8: -0.19224 | F8: -0.08853 | G8: -0.72048 | H8: -0.77222 | I8: -0.60971 | J8: -0.5607 | K8: -0.55018 | L8: -0.76867 | M8: -0.84061 | N8: -0.96303 | O8: -0.41448 | P8: -0.70587 | Q8: -0.23326 | R8: -0.72541 | S8: -0.72531 | T8: -0.56682 | U8: -0.46137 | V8: -0.45528 | W8: -0.64329 | X8: -0.18765 | Y8: -0.15061 | Z8: -0.1132 | AA8: -0.44213 | AB8: -0.47709 | AC8: -0.45599 | AD8: -0.79229 | AE8: -0.35032 | AF8: -0.30751 | AG8: -0.2018 | AH8: -0.04753 | AI8: -0.0886 | AJ8: -0.72844 | AK8: -0.55498 | AL8: -0.82294 | AM8: -0.733 | AN8: -0.4986 | AO8: -0.52387 | AP8: 0.285851 | AQ8: 0.497504 | AR8: -0.68377 | AS8: -0.29413 | AT8: -1.25133
A9: Kurtosis | B9: -1.08886 | C9: -1.14576 | D9: -0.71607 | E9: -0.40074 | F9: -1.02825 | G9: -0.18631 | H9: -0.2154 | I9: -0.10683 | J9: -0.57079 | K9: -0.34221 | L9: -0.19563 | M9: -0.13374 | N9: 0.028493 | O9: -0.15998 | P9: -0.20726 | Q9: -0.86994 | R9: -0.3229 | S9: 0.025995 | T9: -0.55378 | U9: -0.5538 | V9: -0.48209 | W9: 0.327286 | X9: -0.52799 | Y9: -0.43982 | Z9: -0.09886 | AA9: -0.28377 | AB9: -0.70887 | AC9: -0.47317 | AD9: 0.308968 | AE9: -0.36556 | AF9: -0.73755 | AG9: -0.92286 | AH9: -0.87091 | AI9: -0.75921 | AJ9: 0.279245 | AK9: -0.05006 | AL9: 0.384649 | AM9: -0.44941 | AN9: -0.26897 | AO9: -0.13618 | AP9: -0.4768 | AQ9: -0.48746 | AR9: -0.14256 | AS9: -1.47084 | AT9: 0.986304
A11: Correlation Matrix
B13: 1.Delay in delivering material to construction site | C13: 2.Monopoly of material by some suppliers | D13: 3.Prices fluctuation | E13: 4.Types of material availability at local market | F13: 5.Lack of consultant’s knowledge of available materials | G13: 6.Low productivity | H13: 7.Poor work execution | I13: 8.Shortage of laborers | J13: 9.Mistakes happens during construction phase | K13: 10.Unavailability of equipment | L13: 11.Lack of engineering experience | M13: 12.Construction cost underestimation | N13: 13.Poor site management | O13: 14.Delayed payment for completed work | P13: 15.Cash flow problem during construction | Q13: 16.High rate of interest | R13: 17.Contractor’s financial difficulties | S13: 19.Change design | T13: 20.Errors and omission in design | U13: 21.Incomplete design drawings and specifications at tendering stage | V13: 22.Delay in preparation and approval of drawing | W13: 23.Inaccurate quantity take-off | X13: 24.Long period from planning of project to construction | Y13: 25.Delays in issuing information to the contractor during construction stage | Z13: 26.No practical use of earned value management system | AA13: 27.Lack of cost planning/monitoring during pre and post contract stage | AB13: 28.Poor communication between client, consultant and contractor | AC13: 29.Insufficient coordination between local authority who is responsible about road projects and service authorities | AD13: 30.Delays in decisions making by the approval authorities | AE13: 31.Change schedule | AF13: 32.Stoppages because of work being rejected by consultant | AG13: 33.Lowest bid price | AH13: 34.Insufficient time for preparation of contract documents | AI13: 35.Discrepancies in contract documents | AJ13: 36.Underestimation of time for completion of project | AK13: 37.Extension of time with cost claims | AL13: 38.Scope and specification changes | AM13: 39.Changes in client requirements | AN13: 40.Frequency of variation orders and additional works | AO13: 41.Rework due to error in execution | AP13: 42.Weather conditions | AQ13: 43.Accidents during construction | AR13: 44.Delay in getting NOCs from different government authorities | AS13: Location of organization | AT13: Relevant working experience
A14: 1.Delay in delivering material to construction site | B14: 1 | C14: 0.617447 | D14: 0.213695 | E14: 0.673332 | F14: 0.374378 | G14: 0.484591 | H14: 0.538329 | I14: 0.547602 | J14: 0.402341 | K14: 0.470701 | L14: 0.436309 | M14: 0.308012 | N14: 0.276926 | O14: 0.125762 | P14: 0.184925 | Q14: 0.058699 | R14: 0.086557 | S14: 0.15312 | T14: 0.074863 | U14: 0.029097 | V14: 0.088645 | W14: -0.13842 | X14: -0.07117 | Y14: 0.263414 | Z14: 0.150097 | AA14: 0.273813 | AB14: 0.324388 | AC14: 0.186236 | AD14: 0.106013 | AE14: 0.022708 | AF14: 0.367218 | AG14: 0.400073 | AH14: 0.240698 | AI14: 0.287874 | AJ14: 0.313114 | AK14: 0.323179 | AL14: 0.103723 | AM14: 0.181608 | AN14: 0.159553 | AO14: 0.261497 | AP14: 0.344058 | AQ14: 0.42143 | AR14: 0.340472 | AS14: -0.065 | AT14: -0.15217
A15: 2.Monopoly of material by some suppliers | B15: 0.617447 | C15: 1 | D15: 0.334336 | E15: 0.558668 | F15: 0.426873 | G15: 0.343882 | H15: 0.384931 | I15: 0.393506 | J15: 0.314199 | K15: 0.362904 | L15: 0.427641 | M15: 0.197617 | N15: 0.297861 | O15: 0.101421 | P15: 0.199332 | Q15: 0.146866 | R15: 0.147563 | S15: 0.303899 | T15: 0.221947 | U15: 0.044296 | V15: -0.04365 | W15: 0.015877 | X15: -0.05185 | Y15: 0.231034 | Z15: -0.0423 | AA15: 0.209817 | AB15: 0.180847 | AC15: 0.073655 | AD15: -0.1077 | AE15: -0.07324 | AF15: 0.307204 | AG15: 0.300923 | AH15: 0.17474 | AI15: 0.148534 | AJ15: 0.322445 | AK15: 0.317957 | AL15: -0.13152 | AM15: 0.10813 | AN15: 0.033642 | AO15: 0.179366 | AP15: 0.335591 | AQ15: 0.421812 | AR15: 0.350091 | AS15: 0.154389 | AT15: -0.18119
A16: 3.Prices fluctuation | B16: 0.213695 | C16: 0.334336 | D16: 1 | E16: 0.511606 | F16: 0.39448 | G16: 0.34846 | H16: 0.413956 | I16: 0.279592 | J16: 0.400803 | K16: 0.230993 | L16: 0.382316 | M16: 0.358718 | N16: 0.36283 | O16: -0.0595 | P16: 0.002948 | Q16: 0.061672 | R16: 0.004653 | S16: 0.265123 | T16: 0.089193 | U16: 0.131057 | V16: 0.023002 | W16: 0.045399 | X16: 0.108239 | Y16: 0.039962 | Z16: 0.25724 | AA16: 0.18405 | AB16: 0.180387 | AC16: 0.076737 | AD16: -0.11429 | AE16: 0.051891 | AF16: 0.14818 | AG16: 0.174717 | AH16: 0.110398 | AI16: 0.061732 | AJ16: 0.251131 | AK16: 0.088153 | AL16: 0.144634 | AM16: 0.205128 | AN16: -0.0201 | AO16: 0.223326 | AP16: 0.109573 | AQ16: 0.178412 | AR16: -0.00079 | AS16: 0.235288 | AT16: -0.25457
A17: 4.Types of material availability at local market | B17: 0.673332 | C17: 0.558668 | D17: 0.511606 | E17: 1 | F17: 0.55855 | G17: 0.527909 | H17: 0.625926 | I17: 0.531127 | J17: 0.392543 | K17: 0.462761 | L17: 0.515672 | M17: 0.360599 | N17: 0.448709 | O17: 0.099347 | P17: 0.17308 | Q17: 0.147487 | R17: 0.134703 | S17: 0.212299 | T17: 0.153376 | U17: 0.110675 | V17: 0.035865 | W17: 0.063933 | X17: -0.02161 | Y17: 0.30702 | Z17: 0.269866 | AA17: 0.390218 | AB17: 0.374996 | AC17: 0.146989 | AD17: 0.160056 | AE17: 0.153899 | AF17: 0.404253 | AG17: 0.415851 | AH17: 0.303602 | AI17: 0.278869 | AJ17: 0.341506 | AK17: 0.248039 | AL17: 0.120219 | AM17: 0.231206 | AN17: 0.024896 | AO17: 0.312467 | AP17: 0.389342 | AQ17: 0.430293 | AR17: 0.222421 | AS17: 0.05624 | AT17: -0.15982
A18: 5.Lack of consultant’s knowledge of available materials | B18: 0.374378 | C18: 0.426873 | D18: 0.39448 | E18: 0.55855 | F18: 1 | G18: 0.426822 | H18: 0.516328 | I18: 0.421754 | J18: 0.550363 | K18: 0.394762 | L18: 0.497702 | M18: 0.490624 | N18: 0.553822 | O18: 0.163971 | P18: 0.177539 | Q18: 0.433905 | R18: 0.051387 | S18: 0.467038 | T18: 0.437446 | U18: 0.410275 | V18: 0.285149 | W18: 0.348235 | X18: 0.042098 | Y18: 0.426336 | Z18: 0.454197 | AA18: 0.45199 | AB18: 0.434222 | AC18: 0.228668 | AD18: 0.088695 | AE18: 0.235763 | AF18: 0.500686 | AG18: 0.357036 | AH18: 0.414392 | AI18: 0.402695 | AJ18: 0.2871 | AK18: 0.274633 | AL18: 0.227963 | AM18: 0.335344 | AN18: 0.188694 | AO18: 0.315329 | AP18: 0.410886 | AQ18: 0.380858 | AR18: 0.2323 | AS18: 0.03796 | AT18: -0.18844
A19: 6.Low productivity | B19: 0.484591 | C19: 0.343882 | D19: 0.34846 | E19: 0.527909 | F19: 0.426822 | G19: 1 | H19: 0.82122 | I19: 0.724846 | J19: 0.702263 | K19: 0.546242 | L19: 0.65229 | M19: 0.660151 | N19: 0.675342 | O19: 0.08175 | P19: 0.098779 | Q19: 0.233492 | R19: 0.043609 | S19: 0.373471 | T19: 0.18297 | U19: 0.094957 | V19: 0.099699 | W19: 0.07354 | X19: -0.05932 | Y19: 0.403001 | Z19: 0.258229 | AA19: 0.444134 | AB19: 0.370043 | AC19: 0.382941 | AD19: 0.111805 | AE19: 0.093861 | AF19: 0.327582 | AG19: 0.161801 | AH19: 0.359979 | AI19: 0.366204 | AJ19: 0.456326 | AK19: 0.167462 | AL19: 0.203022 | AM19: 0.242078 | AN19: 0.170312 | AO19: 0.374298 | AP19: 0.281705 | AQ19: 0.233685 | AR19: 0.217358 | AS19: -0.1268 | AT19: 0.093833
A20: 7.Poor work execution | B20: 0.538329 | C20: 0.384931 | D20: 0.413956 | E20: 0.625926 | F20: 0.516328 | G20: 0.82122 | H20: 1 | I20: 0.606889 | J20: 0.681291 | K20: 0.54631 | L20: 0.67464 | M20: 0.594184 | N20: 0.692462 | O20: 0.199402 | P20: 0.18836 | Q20: 0.266013 | R20: 0.134551 | S20: 0.424654 | T20: 0.231783 | U20: 0.154811 | V20: 0.187002 | W20: 0.086875 | X20: 0.029888 | Y20: 0.424424 | Z20: 0.324708 | AA20: 0.536029 | AB20: 0.458468 | AC20: 0.36675 | AD20: 0.265599 | AE20: 0.112323 | AF20: 0.428292 | AG20: 0.327125 | AH20: 0.38895 | AI20: 0.463202 | AJ20: 0.483567 | AK20: 0.192141 | AL20: 0.231245 | AM20: 0.346915 | AN20: 0.166011 | AO20: 0.482768 | AP20: 0.306286 | AQ20: 0.300448 | AR20: 0.332622 | AS20: -0.08863 | AT20: -0.02331
A21: 8.Shortage of laborers | B21: 0.547602 | C21: 0.393506 | D21: 0.279592 | E21: 0.531127 | F21: 0.421754 | G21: 0.724846 | H21: 0.606889 | I21: 1 | J21: 0.637295 | K21: 0.692857 | L21: 0.610079 | M21: 0.660787 | N21: 0.543651 | O21: 0.24175 | P21: 0.160673 | Q21: 0.254432 | R21: 0.074707 | S21: 0.343841 | T21: 0.20507 | U21: 0.092432 | V21: 0.119919 | W21: -0.05228 | X21: -0.0863 | Y21: 0.355575 | Z21: 0.332783 | AA21: 0.318246 | AB21: 0.435951 | AC21: 0.309141 | AD21: 0.15158 | AE21: 0.264405 | AF21: 0.290272 | AG21: 0.314764 | AH21: 0.428882 | AI21: 0.331026 | AJ21: 0.245979 | AK21: 0.198476 | AL21: 0.259149 | AM21: 0.272815 | AN21: 0.196012 | AO21: 0.19772 | AP21: 0.359866 | AQ21: 0.31944 | AR21: 0.331813 | AS21: -0.12448 | AT21: 0.058905
A22: 9.Mistakes happens during construction phase | B22: 0.402341 | C22: 0.314199 | D22: 0.400803 | E22: 0.392543 | F22: 0.550363 | G22: 0.702263 | H22: 0.681291 | I22: 0.637295 | J22: 1 | K22: 0.602859 | L22: 0.640484 | M22: 0.716775 | N22: 0.57909 | O22: -0.06243 | P22: 0.05619 | Q22: 0.30667 | R22: -0.10843 | S22: 0.463957 | T22: 0.354787 | U22: 0.182947 | V22: 0.175382 | W22: 0.260035 | X22: 0.04027 | Y22: 0.337708 | Z22: 0.380576 | AA22: 0.475915 | AB22: 0.486931 | AC22: 0.362106 | AD22: 0.041629 | AE22: 0.166739 | AF22: 0.389531 | AG22: 0.217027 | AH22: 0.38808 | AI22: 0.440433 | AJ22: 0.510131 | AK22: 0.101647 | AL22: 0.173653 | AM22: 0.276445 | AN22: 0.244472 | AO22: 0.358397 | AP22: 0.346162 | AQ22: 0.320782 | AR22: 0.107286 | AS22: -0.03594 | AT22: -0.10373
A23: 10.Unavailability of equipment | B23: 0.470701 | C23: 0.362904 | D23: 0.230993 | E23: 0.462761 | F23: 0.394762 | G23: 0.546242 | H23: 0.54631 | I23: 0.692857 | J23: 0.602859 | K23: 1 | L23: 0.534699 | M23: 0.592702 | N23: 0.392132 | O23: 0.240034 | P23: 0.362282 | Q23: 0.338058 | R23: 0.334682 | S23: 0.201274 | T23: 0.231534 | U23: 0.19579 | V23: 0.196954 | W23: 0.135718 | X23: -0.09845 | Y23: 0.278545 | Z23: 0.355037 | AA23: 0.526397 | AB23: 0.641276 | AC23: 0.418262 | AD23: 0.066973 | AE23: 0.263137 | AF23: 0.326977 | AG23: 0.329632 | AH23: 0.398407 | AI23: 0.35683 | AJ23: 0.255843 | AK23: 0.242508 | AL23: 0.248417 | AM23: 0.36385 | AN23: 0.263656 | AO23: 0.258042 | AP23: 0.394698 | AQ23: 0.264021 | AR23: 0.369401 | AS23: -0.15021 | AT23: -0.07452
A24: 11.Lack of engineering experience | B24: 0.436309 | C24: 0.427641 | D24: 0.382316 | E24: 0.515672 | F24: 0.497702 | G24: 0.65229 | H24: 0.67464 | I24: 0.610079 | J24: 0.640484 | K24: 0.534699 | L24: 1 | M24: 0.673701 | N24: 0.742574 | O24: 0.15664 | P24: 0.231625 | Q24: 0.39417 | R24: 0.170229 | S24: 0.367693 | T24: 0.292584 | U24: 0.274944 | V24: -0.0177 | W24: 0.109076 | X24: 0.129685 | Y24: 0.366931 | Z24: 0.309221 | AA24: 0.457121 | AB24: 0.50896 | AC24: 0.334607 | AD24: 0.159702 | AE24: 0.073713 | AF24: 0.260559 | AG24: 0.187557 | AH24: 0.442714 | AI24: 0.486403 | AJ24: 0.426793 | AK24: 0.192961 | AL24: 0.017981 | AM24: 0.209146 | AN24: 0.124185 | AO24: 0.466641 | AP24: 0.383385 | AQ24: 0.435719 | AR24: 0.23868 | AS24: -0.10328 | AT24: 0.004912
A25: 12.Construction cost underestimation | B25: 0.308012 | C25: 0.197617 | D25: 0.358718 | E25: 0.360599 | F25: 0.490624 | G25: 0.660151 | H25: 0.594184 | I25: 0.660787 | J25: 0.716775 | K25: 0.592702 | L25: 0.673701 | M25: 1 | N25: 0.708867 | O25: 0.007546 | P25: 0.051844 | Q25: 0.37198 | R25: 0.010037 | S25: 0.439861 | T25: 0.249239 | U25: 0.302513 | V25: 0.224564 | W25: 0.195931 | X25: 0.089976 | Y25: 0.301563 | Z25: 0.385961 | AA25: 0.439367 | AB25: 0.446511 | AC25: 0.331241 | AD25: 0.086707 | AE25: 0.208261 | AF25: 0.304288 | AG25: 0.229953 | AH25: 0.461196 | AI25: 0.434186 | AJ25: 0.411536 | AK25: 0.065903 | AL25: 0.369358 | AM25: 0.420076 | AN25: 0.276308 | AO25: 0.392301 | AP25: 0.404163 | AQ25: 0.433821 | AR25: 0.187331 | AS25: -0.17828 | AT25: -0.03834
... A58: Relevant working experience | B58: -0.15217 | C58: -0.18119 | D58: -0.25457 | E58: -0.15982 | F58: -0.18844 | G58: 0.093833 | H58: -0.02331 | I58: 0.058905 | J58: -0.10373 | K58: -0.07452 | L58: 0.004912 | M58: -0.03834 | N58: 0.025722 | O58: 0.139253 | P58: -0.04215 | Q58: 0.075759 | R58: -0.0008 | S58: -0.02685 | T58: -0.10233 | U58: -0.10469 | V58: -0.10628 | W58: -0.12527 | X58: -0.0794 | Y58: 0.031313 | Z58: -0.05293 | AA58: -0.1027 | AB58: -0.09904 | AC58: -0.04329 | AD58: -0.00079 | AE58: -0.01927 | AF58: -0.03121 | AG58: -0.21396 | AH58: 0.018106 | AI58: 0.025474 | AJ58: -0.06804 | AK58: -0.0748 | AL58: -0.1039 | AM58: -0.12221 | AN58: -0.07477 | AO58: -0.04059 | AP58: -0.07443 | AQ58: -0.22453 | AR58: -0.02073 | AS58: -0.0357 | AT58: 1
B59: 4.246842 | C59: 3.320428 | D59: 2.255776 | E59: 5.220122 | F59: 6.172765 | G59: 6.357509 | H59: 7.491631 | I59: 6.09855 | J59: 6.69014 | K59: 6.1092 | L59: 6.853152 | M59: 6.741862 | N59: 6.359313 | O59: 2.56826 | P59: 3.511436 | Q59: 4.535595 | R59: 2.322142 | S59: 4.550833 | T59: 4.331501 | U59: 4.177802 | V59: 3.059908 | W59: 2.950592 | X59: 0.900143 | Y59: 5.193314 | Z59: 4.760238 | AA59: 6.929866 | AB59: 5.936491 | AC59: 3.2537 | AD59: 2.112584 | AE59: 2.955571 | AF59: 4.561587 | AG59: 2.182358 | AH59: 5.670787 | AI59: 5.345282 | AJ59: 3.381428 | AK59: 2.140692 | AL59: 2.573149 | AM59: 3.212254 | AN59: 2.3284 | AO59: 3.528989 | AP59: 5.028425 | AQ59: 3.41878 | AR59: 3.122772 | AS59: 0.699455 | AT59: 0.470446 | AU59: 185.6321
A61: Inverse of Correlation Matrix
B63: 1.Delay in delivering material to construction site | C63: 2.Monopoly of material by some suppliers | D63: 3.Prices fluctuation | E63: 4.Types of material availability at local market | F63: 5.Lack of consultant’s knowledge of available materials | G63: 6.Low productivity | H63: 7.Poor work execution | I63: 8.Shortage of laborers | J63: 9.Mistakes happens during construction phase | K63: 10.Unavailability of equipment | L63: 11.Lack of engineering experience | M63: 12.Construction cost underestimation | N63: 13.Poor site management | O63: 14.Delayed payment for completed work | P63: 15.Cash flow problem during construction | Q63: 16.High rate of interest | R63: 17.Contractor’s financial difficulties | S63: 19.Change design | T63: 20.Errors and omission in design | U63: 21.Incomplete design drawings and specifications at tendering stage | V63: 22.Delay in preparation and approval of drawing | W63: 23.Inaccurate quantity take-off | X63: 24.Long period from planning of project to construction | Y63: 25.Delays in issuing information to the contractor during construction stage | Z63: 26.No practical use of earned value management system | AA63: 27.Lack of cost planning/monitoring during pre and post contract stage | AB63: 28.Poor communication between client, consultant and contractor | AC63: 29.Insufficient coordination between local authority who is responsible about road projects and service authorities | AD63: 30.Delays in decisions making by the approval authorities | AE63: 31.Change schedule | AF63: 32.Stoppages because of work being rejected by consultant | AG63: 33.Lowest bid price | AH63: 34.Insufficient time for preparation of contract documents | AI63: 35.Discrepancies in contract documents | AJ63: 36.Underestimation of time for completion of project | AK63: 37.Extension of time with cost claims | AL63: 38.Scope and specification changes | AM63: 39.Changes in client requirements | AN63: 40.Frequency of variation orders and additional works | AO63: 41.Rework due to error in execution | AP63: 42.Weather conditions | AQ63: 43.Accidents during construction | AR63: 44.Delay in getting NOCs from different government authorities | AS63: Location of organization | AT63: Relevant working experience | AV63: sqrt(diag)
A64: 1.Delay in delivering material to construction site | B64: 4.625921 | C64: -1.60498 | D64: 0.907135 | E64: -1.57881 | F64: 0.323775 | G64: -0.91453 | H64: 0.069129 | I64: -0.37141 | J64: -0.94043 | K64: 0.013259 | L64: 0.138234 | M64: -0.27848 | N64: 1.159585 | O64: -0.13161 | P64: -0.56877 | Q64: 0.677967 | R64: 0.31961 | S64: 0.865304 | T64: 0.528233 | U64: -0.79227 | V64: -0.39179 | W64: 1.516412 | X64: -0.37385 | Y64: -0.76085 | Z64: -0.84446 | AA64: 0.912763 | AB64: 0.004959 | AC64: 0.217228 | AD64: -0.12589 | AE64: 0.505305 | AF64: -0.76892 | AG64: -0.38313 | AH64: 0.881286 | AI64: -0.75494 | AJ64: 0.022978 | AK64: -0.30264 | AL64: 0.43948 | AM64: -0.40812 | AN64: -0.17109 | AO64: -0.74407 | AP64: -0.59656 | AQ64: -0.08476 | AR64: 0.096106 | AS64: -0.01677 | AT64: 0.339915 | AV64: 2.150795
A65: 2.Monopoly of material by some suppliers | B65: -1.60498 | C65: 4.511733 | D65: -0.57771 | E65: -0.1915 | F65: -0.70926 | G65: 0.833987 | H65: -0.04411 | I65: -1.51711 | J65: 0.779811 | K65: 0.365234 | L65: -0.75284 | M65: 1.460216 | N65: -0.6556 | O65: 1.264017 | P65: -0.81139 | Q65: -0.48079 | R65: -0.6046 | S65: -1.32011 | T65: -0.09661 | U65: 0.711481 | V65: -0.35035 | W65: -0.35062 | X65: 0.43938 | Y65: 0.080503 | Z65: 1.182166 | AA65: -0.84953 | AB65: 0.305866 | AC65: -0.30408 | AD65: 1.459385 | AE65: -0.33022 | AF65: 0.391031 | AG65: -0.28063 | AH65: 0.600216 | AI65: 0.504272 | AJ65: -0.78341 | AK65: -0.24675 | AL65: 1.083862 | AM65: -0.62742 | AN65: -0.44779 | AO65: 0.424367 | AP65: 0.172614 | AQ65: -0.8386 | AR65: -0.79756 | AS65: -0.02881 | AT65: -0.06666 | AV65: 2.124084
A66: 3.Prices fluctuation | B66: 0.907135 | C66: -0.57771 | D66: 3.109929 | E66: -1.66103 | F66: 0.327171 | G66: -0.31571 | H66: -0.28972 | I66: 1.027586 | J66: -1.30162 | K66: 0.372767 | L66: -0.20362 | M66: -0.30366 | N66: -0.55848 | O66: 0.019217 | P66: -0.10953 | Q66: 0.194312 | R66: -0.09341 | S66: -0.06608 | T66: -0.03948 | U66: -0.25601 | V66: -0.36048 | W66: 0.823182 | X66: -0.48896 | Y66: 0.616299 | Z66: -1.14647 | AA66: 0.864546 | AB66: 0.038153 | AC66: -0.48252 | AD66: 0.830252 | AE66: -0.32029 | AF66: 0.469731 | AG66: -0.38584 | AH66: -0.18885 | AI66: 0.919197 | AJ66: 0.242458 | AK66: -0.2851 | AL66: -0.27993 | AM66: -0.02746 | AN66: 0.664487 | AO66: -0.36842 | AP66: -0.36634 | AQ66: 0.336384 | AR66: -0.21282 | AS66: -0.67946 | AT66: 0.366705 | AV66: 1.763499
A67: 4.Types of material availability at local market | B67: -1.57881 | C67: -0.1915 | D67: -1.66103 | E67: 5.617336 | F67: -1.69439 | G67: -0.57592 | H67: -1.71398 | I67: -1.64536 | J67: 3.386577 | K67: -0.84961 | L67: -0.30469 | M67: 1.068561 | N67: 0.220541 | O67: 0.986095 | P67: -1.28068 | Q67: 0.477747 | R67: 1.015232 | S67: -0.15402 | T67: 0.762063 | U67: -0.00939 | V67: 0.329767 | W67: -1.07748 | X67: 0.026848 | Y67: 0.272272 | Z67: 0.34532 | AA67: -0.5316 | AB67: -0.93533 | AC67: 0.909155 | AD67: -0.91411 | AE67: -0.43649 | AF67: 0.208718 | AG67: -0.56885 | AH67: 0.410843 | AI67: -0.16761 | AJ67: -0.97549 | AK67: 0.422785 | AL67: 0.20597 | AM67: 0.051635 | AN67: -0.23694 | AO67: 0.432188 | AP67: -0.48898 | AQ67: -0.61933 | AR67: 1.079331 | AS67: -0.18572 | AT67: -0.32771 | AV67: 2.370092
A68: 5.Lack of consultant’s knowledge of available materials | B68: 0.323775 | C68: -0.70926 | D68: 0.327171 | E68: -1.69439 | F68: 5.103568 | G68: -0.27625 | H68: 1.72632 | I68: 1.244343 | J68: -2.7026 | K68: 0.772456 | L68: 0.60618 | M68: -0.04691 | N68: -2.24351 | O68: -1.91369 | P68: 1.870248 | Q68: -0.47879 | R68: 0.009622 | S68: 0.561579 | T68: -0.37424 | U68: -0.5959 | V68: 0.355116 | W68: -0.37461 | X68: 0.539163 | Y68: -0.51849 | Z68: -1.53258 | AA68: 0.979668 | AB68: -0.60966 | AC68: 0.066727 | AD68: 0.581228 | AE68: 1.963879 | AF68: -1.56154 | AG68: -0.7147 | AH68: -0.40162 | AI68: -0.51819 | AJ68: 1.538942 | AK68: -1.01562 | AL68: -0.28128 | AM68: -1.33263 | AN68: 1.448314 | AO68: -0.12201 | AP68: -0.88989 | AQ68: 1.081937 | AR68: -0.31675 | AS68: -0.12666 | AT68: 0.788586 | AV68: 2.259108
A69: 6.Low productivity | B69: -0.91453 | C69: 0.833987 | D69: -0.31571 | E69: -0.57592 | F69: -0.27625 | G69: 8.320938 | H69: -4.41003 | I69: -2.98282 | J69: 0.166965 | K69: 0.512874 | L69: -0.02525 | M69: -0.52096 | N69: -0.81334 | O69: 1.045724 | P69: 0.323118 | Q69: -0.59721 | R69: -0.77647 | S69: -0.64543 | T69: -0.33213 | U69: 0.741114 | V69: -0.14175 | W69: -0.34826 | X69: 0.721003 | Y69: -0.03032 | Z69: 1.38112 | AA69: -1.62091 | AB69: 1.449 | AC69: -2.00337 | AD69: 0.894111 | AE69: -0.49227 | AF69: 0.253654 | AG69: 1.284022 | AH69: -0.88855 | AI69: 1.327661 | AJ69: -0.7039 | AK69: -0.58026 | AL69: -0.17904 | AM69: 1.329353 | AN69: -0.97622 | AO69: 0.46535 | AP69: 1.241074 | AQ69: -0.35684 | AR69: 0.687254 | AS69: 0.793827 | AT69: -0.65258 | AV69: 2.884604
A70: 7.Poor work execution | B70: 0.069129 | C70: -0.04411 | D70: -0.28972 | E70: -1.71398 | F70: 1.72632 | G70: -4.41003 | H70: 9.37512 | I70: 2.869223 | J70: -3.63457 | K70: -0.60926 | L70: -0.54696 | M70: 0.921514 | N70: -1.37712 | O70: -2.63529 | P70: 2.348471 | Q70: 0.45737 | R70: -0.80301 | S70: -0.49475 | T70: 0.2262 | U70: 0.421316 | V70: 0.032901 | W70: 0.804015 | X70: 0.384551 | Y70: -1.26632 | Z70: -0.98238 | AA70: 0.801344 | AB70: -0.46562 | AC70: 0.854821 | AD70: -0.87922 | AE70: 2.145484 | AF70: -2.17251 | AG70: -0.20272 | AH70: -0.30455 | AI70: -0.97464 | AJ70: 1.18967 | AK70: 0.052912 | AL70: -0.43057 | AM70: -2.09242 | AN70: 2.011137 | AO70: -1.17426 | AP70: -0.61573 | AQ70: 1.043487 | AR70: -0.80139 | AS70: 0.400349 | AT70: 0.807914 | AV70: 3.061882
A71: 8.Shortage of laborers | B71: -0.37141 | C71: -1.51711 | D71: 1.027586 | E71: -1.64536 | F71: 1.244343 | G71: -2.98282 | H71: 2.869223 | I71: 8.932024 | J71: -3.53198 | K71: -2.18747 | L71: -0.73443 | M71: -1.90137 | N71: -0.68466 | O71: -2.29013 | P71: 2.122472 | Q71: 1.394528 | R71: -0.90906 | S71: -0.5916 | T71: -1.20949 | U71: 1.611672 | V71: 0.470014 | W71: 1.190047 | X71: 0.240602 | Y71: -0.86784 | Z71: -2.11324 | AA71: 2.197905 | AB71: -0.08454 | AC71: 0.364439 | AD71: -0.9784 | AE71: 0.499655 | AF71: -0.44415 | AG71: 0.468763 | AH71: -2.45789 | AI71: 1.004388 | AJ71: 2.685573 | AK71: -0.57349 | AL71: -1.9134 | AM71: 0.373277 | AN71: 1.512512 | AO71: -0.20202 | AP71: -0.23627 | AQ71: 0.53156 | AR71: -0.34394 | AS71: -0.13538 | AT71: 0.134492 | AV71: 2.988649
A72: 9.Mistakes happens during construction phase | B72: -0.94043 | C72: 0.779811 | D72: -1.30162 | E72: 3.386577 | F72: -2.7026 | G72: 0.166965 | H72: -3.63457 | I72: -3.53198 | J72: 9.89475 | K72: -2.05245 | L72: -1.06777 | M72: 0.218041 | N72: 0.858558 | O72: 2.677148 | P72: -3.2272 | Q72: -0.37236 | R72: 3.146878 | S72: -1.27877 | T72: 0.58086 | U72: 1.169421 | V72: -0.71179 | W72: -1.61184 | X72: -0.67579 | Y72: 1.450412 | Z72: 1.276076 | AA72: -1.57138 | AB72: -0.86913 | AC72: -0.00249 | AD72: -0.24974 | AE72: -1.32495 | AF72: 0.661959 | AG72: 0.286454 | AH72: 1.00075 | AI72: -0.40981 | AJ72: -2.68499 | AK72: 0.528899 | AL72: 0.676764 | AM72: 1.206777 | AN72: -1.92266 | AO72: 1.247708 | AP72: 0.959486 | AQ72: -1.37896 | AR72: 1.692025 | AS72: -0.50908 | AT72: -0.40705 | AV72: 3.145592
A73: 10.Unavailability of equipment | B73: 0.013259 | C73: 0.365234 | D73: 0.372767 | E73: -0.84961 | F73: 0.772456 | G73: 0.512874 | H73: -0.60926 | I73: -2.18747 | J73: -2.05245 | K73: 6.510985 | L73: -0.12482 | M73: -1.94775 | N73: 1.18619 | O73: 0.1526 | P73: -0.48865 | Q73: -0.57989 | R73: -1.41156 | S73: 1.220977 | T73: -0.59132 | U73: 0.140252 | V73: 0.380882 | W73: -0.43114 | X73: 0.634601 | Y73: 0.347733 | Z73: 0.298584 | AA73: -1.31848 | AB73: -0.84144 | AC73: 0.106803 | AD73: 1.482717 | AE73: 0.045965 | AF73: 0.234553 | AG73: -1.03344 | AH73: 1.073027 | AI73: 0.201876 | AJ73: 0.932807 | AK73: -0.26438 | AL73: 0.628454 | AM73: -0.97987 | AN73: -0.28609 | AO73: -0.12624 | AP73: -1.10335 | AQ73: 1.206378 | AR73: -1.28902 | AS73: -0.04574 | AT73: 0.1095 | AV73: 2.551663
A74: 11.Lack of engineering experience | B74: 0.138234 | C74: -0.75284 | D74: -0.20362 | E74: -0.30469 | F74: 0.60618 | G74: -0.02525 | H74: -0.54696 | I74: -0.73443 | J74: -1.06777 | K74: -0.12482 | L74: 6.348883 | M74: -0.82619 | N74: -1.8727 | O74: -0.92839 | P74: 0.625139 | Q74: -0.58366 | R74: -0.23925 | S74: 0.788833 | T74: -0.01657 | U74: -2.16137 | V74: 1.317534 | W74: 0.698157 | X74: -0.33728 | Y74: -0.3045 | Z74: -0.54073 | AA74: 0.687666 | AB74: -0.47469 | AC74: -0.48777 | AD74: 0.114033 | AE74: 0.656458 | AF74: 0.716586 | AG74: -0.56097 | AH74: 0.547522 | AI74: -0.99143 | AJ74: -0.19263 | AK74: -0.04481 | AL74: 1.248267 | AM74: 0.303123 | AN74: 0.047467 | AO74: -0.95461 | AP74: -0.54103 | AQ74: -0.11491 | AR74: 0.532366 | AS74: 0.144421 | AT74: -0.03094 | AV74: 2.519699
A75: 12.Construction cost underestimation | B75: -0.27848 | C75: 1.460216 | D75: -0.30366 | E75: 1.068561 | F75: -0.04691 | G75: -0.52096 | H75: 0.921514 | I75: -1.90137 | J75: 0.218041 | K75: -1.94775 | L75: -0.82619 | M75: 7.75171 | N75: -2.74934 | O75: 1.130513 | P75: 0.063095 | Q75: -0.64317 | R75: 0.450312 | S75: -1.5041 | T75: 1.171993 | U75: -1.28303 | V75: -1.14731 | W75: 0.008014 | X75: -0.07209 | Y75: 0.455189 | Z75: 0.139246 | AA75: 0.51233 | AB75: -0.00993 | AC75: -0.69672 | AD75: 0.929092 | AE75: -0.16924 | AF75: 0.711181 | AG75: -0.85303 | AH75: 0.33745 | AI75: 0.301345 | AJ75: -2.07788 | AK75: 0.921813 | AL75: -0.39501 | AM75: -0.85011 | AN75: 0.923105 | AO75: -0.01803 | AP75: -0.60985 | AQ75: -1.37946 | AR75: 0.296105 | AS75: 0.614639 | AT75: -0.18663 | AV75: 2.784189
... A108: Relevant working experience | B108: 0.339915 | C108: -0.06666 | D108: 0.366705 | E108: -0.32771 | F108: 0.788586 | G108: -0.65258 | H108: 0.807914 | I108: 0.134492 | J108: -0.40705 | K108: 0.1095 | L108: -0.03094 | M108: -0.18663 | N108: -0.21703 | O108: -1.20118 | P108: 0.764596 | Q108: -0.04572 | R108: 0.019001 | S108: 0.0533 | T108: 0.406201 | U108: -0.09554 | V108: 0.404134 | W108: 0.059524 | X108: 0.026817 | Y108: -0.35075 | Z108: -0.43679 | AA108: 0.293306 | AB108: 0.008817 | AC108: 0.253307 | AD108: 0.003525 | AE108: 0.744755 | AF108: -0.95278 | AG108: 0.343385 | AH108: -0.15914 | AI108: -0.54648 | AJ108: 0.429139 | AK108: -0.08267 | AL108: 0.206751 | AM108: -0.62792 | AN108: 0.367123 | AO108: -0.0326 | AP108: -0.51416 | AQ108: 0.848795 | AR108: -0.0222 | AS108: -0.04615 | AT108: 1.803205 | AV108: 1.342835
A110: Partial Correlation Matrix
B112: 1.Delay in delivering material to construction site | C112: 2.Monopoly of material by some suppliers | D112: 3.Prices fluctuation | E112: 4.Types of material availability at local market | F112: 5.Lack of consultant’s knowledge of available materials | G112: 6.Low productivity | H112: 7.Poor work execution | I112: 8.Shortage of laborers | J112: 9.Mistakes happens during construction phase | K112: 10.Unavailability of equipment | L112: 11.Lack of engineering experience | M112: 12.Construction cost underestimation | N112: 13.Poor site management | O112: 14.Delayed payment for completed work | P112: 15.Cash flow problem during construction | Q112: 16.High rate of interest | R112: 17.Contractor’s financial difficulties | S112: 19.Change design | T112: 20.Errors and omission in design | U112: 21.Incomplete design drawings and specifications at tendering stage | V112: 22.Delay in preparation and approval of drawing | W112: 23.Inaccurate quantity take-off | X112: 24.Long period from planning of project to construction | Y112: 25.Delays in issuing information to the contractor during construction stage | Z112: 26.No practical use of earned value management system | AA112: 27.Lack of cost planning/monitoring during pre and post contract stage | AB112: 28.Poor communication between client, consultant and contractor | AC112: 29.Insufficient coordination between local authority who is responsible about road projects and service authorities | AD112: 30.Delays in decisions making by the approval authorities | AE112: 31.Change schedule | AF112: 32.Stoppages because of work being rejected by consultant | AG112: 33.Lowest bid price | AH112: 34.Insufficient time for preparation of contract documents | AI112: 35.Discrepancies in contract documents | AJ112: 36.Underestimation of time for completion of project | AK112: 37.Extension of time with cost claims | AL112: 38.Scope and specification changes | AM112: 39.Changes in client requirements | AN112: 40.Frequency of variation orders and additional works | AO112: 41.Rework due to error in execution | AP112: 42.Weather conditions | AQ112: 43.Accidents during construction | AR112: 44.Delay in getting NOCs from different government authorities | AS112: Location of organization | AT112: Relevant working experience
A113: 1.Delay in delivering material to construction site | B113: 1 | C113: 0.351317 | D113: -0.23916 | E113: 0.309717 | F113: -0.06664 | G113: 0.147406 | H113: -0.0105 | I113: 0.05778 | J113: 0.139003 | K113: -0.00242 | L113: -0.02551 | M113: 0.046505 | N113: -0.20881 | O113: 0.023703 | P113: 0.10184 | Q113: -0.16268 | R113: -0.07208 | S113: -0.17682 | T113: -0.11192 | U113: 0.145166 | V113: 0.099136 | W113: -0.34273 | X113: 0.117249 | Y113: 0.1758 | Z113: 0.187908 | AA113: -0.18395 | AB113: -0.00102 | AC113: -0.04817 | AD113: 0.031999 | AE113: -0.11573 | AF113: 0.151003 | AG113: 0.088106 | AH113: -0.15281 | AI113: 0.149694 | AJ113: -0.00465 | AK113: 0.078745 | AL113: -0.09851 | AM113: 0.084964 | AN113: 0.041774 | AO113: 0.193241 | AP113: 0.102608 | AQ113: 0.018384 | AR113: -0.02288 | AS113: 0.005476 | AT113: -0.11769
A114: 2.Monopoly of material by some suppliers | B114: 0.351317 | C114: 1 | D114: 0.154229 | E114: 0.038038 | F114: 0.147807 | G114: -0.13611 | H114: 0.006782 | I114: 0.238985 | J114: -0.11671 | K114: -0.06739 | L114: 0.140664 | M114: -0.24691 | N114: 0.119543 | O114: -0.23051 | P114: 0.147108 | Q114: 0.116816 | R114: 0.13806 | S114: 0.27315 | T114: 0.020728 | U114: -0.132 | V114: 0.089765 | W114: 0.080241 | X114: -0.13953 | Y114: -0.01883 | Z114: -0.26636 | AA114: 0.173364 | AB114: -0.06398 | AC114: 0.068271 | AD114: -0.37562 | AE114: 0.076578 | AF114: -0.07776 | AG114: 0.065346 | AH114: -0.10538 | AI114: -0.10125 | AJ114: 0.160522 | AK114: 0.065008 | AL114: -0.246 | AM114: 0.13226 | AN114: 0.110708 | AO114: -0.1116 | AP114: -0.03006 | AQ114: 0.184171 | AR114: 0.192271 | AS114: 0.009524 | AT114: 0.023369
A115: 3.Prices fluctuation | B115: -0.23916 | C115: 0.154229 | D115: 1 | E115: 0.397407 | F115: -0.08212 | G115: 0.062063 | H115: 0.053656 | I115: -0.19497 | J115: 0.234642 | K115: -0.08284 | L115: 0.045824 | M115: 0.061847 | N115: 0.122655 | O115: -0.00422 | P115: 0.023918 | Q115: -0.05686 | R115: 0.025692 | S115: 0.016468 | T115: 0.010201 | U115: 0.057209 | V115: 0.111246 | W115: -0.22691 | X115: 0.187032 | Y115: -0.17367 | Z115: 0.311139 | AA115: -0.2125 | AB115: -0.00961 | AC115: 0.130485 | AD115: -0.25739 | AE115: 0.089462 | AF115: -0.11251 | AG115: 0.108218 | AH115: 0.039938 | AI115: -0.22229 | AJ115: -0.05984 | AK115: 0.090471 | AL115: 0.076525 | AM115: 0.006972 | AN115: -0.19788 | AO115: 0.116694 | AP115: 0.076848 | AQ115: -0.08898 | AR115: 0.061797 | AS115: 0.270576 | AT115: -0.15485
A116: 4.Types of material availability at local market | B116: 0.309717 | C116: 0.038038 | D116: 0.397407 | E116: 1 | F116: 0.316454 | G116: 0.084239 | H116: 0.236185 | I116: 0.232285 | J116: -0.45425 | K116: 0.140485 | L116: 0.051021 | M116: -0.16193 | N116: -0.03604 | O116: -0.16116 | P116: 0.208092 | Q116: -0.10403 | R116: -0.20777 | S116: 0.028562 | T116: -0.14653 | U116: 0.001561 | V116: -0.07572 | W116: 0.220992 | X116: -0.00764 | Y116: -0.05709 | Z116: -0.06973 | AA116: 0.097224 | AB116: 0.175331 | AC116: -0.18293 | AD116: 0.210854 | AE116: 0.090716 | AF116: -0.0372 | AG116: 0.118714 | AH116: -0.06465 | AI116: 0.03016 | AJ116: 0.179133 | AK116: -0.09983 | AL116: -0.0419 | AM116: -0.00975 | AN116: 0.052499 | AO116: -0.10186 | AP116: 0.076321 | AQ116: 0.121897 | AR116: -0.23319 | AS116: 0.055028 | AT116: 0.102968
A117: 5.Lack of consultant’s knowledge of available materials | B117: -0.06664 | C117: 0.147807 | D117: -0.08212 | E117: 0.316454 | F117: 1 | G117: 0.042391 | H117: -0.24957 | I117: -0.1843 | J117: 0.380314 | K117: -0.134 | L117: -0.10649 | M117: 0.007459 | N117: 0.384633 | O117: 0.328134 | P117: -0.31882 | Q117: 0.109376 | R117: -0.00207 | S117: -0.10925 | T117: 0.075494 | U117: 0.103951 | V117: -0.08555 | W117: 0.080607 | X117: -0.16099 | Y117: 0.114055 | Z117: 0.324678 | AA117: -0.18797 | AB117: 0.119898 | AC117: -0.01409 | AD117: -0.14066 | AE117: -0.4282 | AF117: 0.291957 | AG117: 0.156477 | AH117: 0.066301 | AI117: 0.097822 | AJ117: -0.29649 | AK117: 0.251585 | AL117: 0.060024 | AM117: 0.264128 | AN117: -0.33667 | AO117: 0.030168 | AP117: 0.145721 | AQ117: -0.22341 | AR117: 0.071797 | AS117: 0.039373 | AT117: -0.25995
A118: 6.Low productivity | B118: 0.147406 | C118: -0.13611 | D118: 0.062063 | E118: 0.084239 | F118: 0.042391 | G118: 1 | H118: 0.499306 | I118: 0.345992 | J118: -0.0184 | K118: -0.06968 | L118: 0.003474 | M118: 0.064866 | N118: 0.109205 | O118: -0.14043 | P118: -0.04314 | Q118: 0.106845 | R118: 0.13056 | S118: 0.098339 | T118: 0.052471 | U118: -0.10125 | V118: 0.026743 | W118: 0.058688 | X118: -0.1686 | Y118: 0.005223 | Z118: -0.22915 | AA118: 0.24357 | AB118: -0.22317 | AC118: 0.331202 | AD118: -0.16946 | AE118: 0.08406 | AF118: -0.03714 | AG118: -0.22017 | AH118: 0.114877 | AI118: -0.19629 | AJ118: 0.106204 | AK118: 0.112572 | AL118: 0.029923 | AM118: -0.20635 | AN118: 0.177723 | AO118: -0.09011 | AP118: -0.15916 | AQ118: 0.057706 | AR118: -0.122 | AS118: -0.19326 | AT118: 0.168472
A119: 7.Poor work execution | B119: -0.0105 | C119: 0.006782 | D119: 0.053656 | E119: 0.236185 | F119: -0.24957 | G119: 0.499306 | H119: 1 | I119: -0.31355 | J119: 0.377366 | K119: 0.077982 | L119: 0.070896 | M119: -0.1081 | N119: 0.174197 | O119: 0.333394 | P119: -0.29538 | Q119: -0.07709 | R119: 0.127205 | S119: 0.071016 | T119: -0.03367 | U119: -0.05423 | V119: -0.00585 | W119: -0.12765 | X119: -0.08472 | Y119: 0.205528 | Z119: 0.153552 | AA119: -0.11344 | AB119: 0.067561 | AC119: -0.13314 | AD119: 0.156985 | AE119: -0.34515 | AF119: 0.299693 | AG119: 0.032748 | AH119: 0.037095 | AI119: 0.135751 | AJ119: -0.1691 | AK119: -0.00967 | AL119: 0.067793 | AM119: 0.305987 | AN119: -0.34493 | AO119: 0.21422 | AP119: 0.074392 | AQ119: -0.15898 | AR119: 0.134023 | AS119: -0.09182 | AT119: -0.1965
A120: 8.Shortage of laborers | B120: 0.05778 | C120: 0.238985 | D120: -0.19497 | E120: 0.232285 | F120: -0.1843 | G120: 0.345992 | H120: -0.31355 | I120: 1 | J120: 0.3757 | K120: 0.286843 | L120: 0.097527 | M120: 0.228503 | N120: 0.088726 | O120: 0.296826 | P120: -0.27349 | Q120: -0.24081 | R120: 0.147533 | S120: 0.086998 | T120: 0.184428 | U120: -0.21252 | V120: -0.08559 | W120: -0.19356 | X120: -0.0543 | Y120: 0.144305 | Z120: 0.338407 | AA120: -0.31878 | AB120: 0.012567 | AC120: -0.05815 | AD120: 0.178975 | AE120: -0.08235 | AF120: 0.062771 | AG120: -0.07758 | AH120: 0.306711 | AI120: -0.14332 | AJ120: -0.39109 | AK120: 0.107385 | AL120: 0.308644 | AM120: -0.05592 | AN120: -0.26577 | AO120: 0.037757 | AP120: 0.029245 | AQ120: -0.08297 | AR120: 0.058929 | AS120: 0.031812 | AT120: -0.03351
A121: 9.Mistakes happens during construction phase | B121: 0.139003 | C121: -0.11671 | D121: 0.234642 | E121: -0.45425 | F121: 0.380314 | G121: -0.0184 | H121: 0.377366 | I121: 0.3757 | J121: 1 | K121: 0.25571 | L121: 0.134718 | M121: -0.0249 | N121: -0.10571 | O121: -0.32968 | P121: 0.395095 | Q121: 0.061092 | R121: -0.48523 | S121: 0.17867 | T121: -0.08415 | U121: -0.14651 | V121: 0.123148 | W121: 0.249087 | X121: 0.144918 | Y121: -0.22914 | Z121: -0.19415 | AA121: 0.216536 | AB121: 0.122755 | AC121: 0.000378 | AD121: 0.043405 | AE121: 0.207478 | AF121: -0.08889 | AG121: -0.04504 | AH121: -0.11865 | AI121: 0.05556 | AJ121: 0.371499 | AK121: -0.09409 | AL121: -0.10372 | AM121: -0.17178 | AN121: 0.320982 | AO121: -0.22156 | AP121: -0.11284 | AQ121: 0.204498 | AR121: -0.27544 | AS121: 0.113655 | AT121: 0.096365
A122: 10.Unavailability of equipment | B122: -0.00242 | C122: -0.06739 | D122: -0.08284 | E122: 0.140485 | F122: -0.134 | G122: -0.06968 | H122: 0.077982 | I122: 0.286843 | J122: 0.25571 | K122: 1 | L122: 0.019415 | M122: 0.274165 | N122: -0.18005 | O122: -0.02317 | P122: 0.073748 | Q122: 0.117285 | R122: 0.268317 | S122: -0.2103 | T122: 0.105608 | U122: -0.02166 | V122: -0.08124 | W122: 0.082134 | X122: -0.16776 | Y122: -0.06772 | Z122: -0.056 | AA122: 0.223977 | AB122: 0.146506 | AC122: -0.01996 | AD122: -0.31768 | AE122: -0.00887 | AF122: -0.03883 | AG122: 0.200322 | AH122: -0.15683 | AI122: -0.03374 | AJ122: -0.15911 | AK122: 0.057983 | AL122: -0.11873 | AM122: 0.171944 | AN122: 0.058879 | AO122: 0.027634 | AP122: 0.15996 | AQ122: -0.22055 | AR122: 0.25868 | AS122: 0.012588 | AT122: -0.03196
A123: 11.Lack of engineering experience | B123: -0.02551 | C123: 0.140664 | D123: 0.045824 | E123: 0.051021 | F123: -0.10649 | G123: 0.003474 | H123: 0.070896 | I123: 0.097527 | J123: 0.134718 | K123: 0.019415 | L123: 1 | M123: 0.11777 | N123: 0.287855 | O123: 0.142725 | P123: -0.09554 | Q123: 0.119544 | R123: 0.046054 | S123: -0.13759 | T123: 0.002997 | U123: 0.33804 | V123: -0.28457 | W123: -0.13469 | X123: 0.090294 | Y123: 0.060056 | Z123: 0.102707 | AA123: -0.1183 | AB123: 0.0837 | AC123: 0.092318 | AD123: -0.02474 | AE123: -0.12833 | AF123: -0.12012 | AG123: 0.110117 | AH123: -0.08104 | AI123: 0.167803 | AJ123: 0.033273 | AK123: 0.009952 | AL123: -0.23883 | AM123: -0.05387 | AN123: -0.00989 | AO123: 0.211621 | AP123: 0.079432 | AQ123: 0.021274 | AR123: -0.10819 | AS123: -0.04025 | AT123: 0.009145
A124: 12.Construction cost underestimation | B124: 0.046505 | C124: -0.24691 | D124: 0.061847 | E124: -0.16193 | F124: 0.007459 | G124: 0.064866 | H124: -0.1081 | I124: 0.228503 | J124: -0.0249 | K124: 0.274165 | L124: 0.11777 | M124: 1 | N124: 0.382459 | O124: -0.15729 | P124: -0.00873 | Q124: 0.119218 | R124: -0.07845 | S124: 0.237432 | T124: -0.19183 | U124: 0.181604 | V124: 0.224266 | W124: -0.0014 | X124: 0.017465 | Y124: -0.08125 | Z124: -0.02394 | AA124: -0.07976 | AB124: 0.001584 | AC124: 0.119338 | AD124: -0.18244 | AE124: 0.029942 | AF124: -0.10789 | AG124: 0.151542 | AH124: -0.0452 | AI124: -0.04616 | AJ124: 0.324817 | AK124: -0.18528 | AL124: 0.068397 | AM124: 0.136715 | AN124: -0.17411 | AO124: 0.003618 | AP124: 0.08103 | AQ124: 0.231126 | AR124: -0.05446 | AS124: -0.15503 | AT124: 0.049918
... A157: Relevant working experience | B157: -0.11769 | C157: 0.023369 | D157: -0.15485 | E157: 0.102968 | F157: -0.25995 | G157: 0.168472 | H157: -0.1965 | I157: -0.03351 | J157: 0.096365 | K157: -0.03196 | L157: 0.009145 | M157: 0.049918 | N157: 0.062596 | O157: 0.346499 | P157: -0.21927 | Q157: 0.01757 | R157: -0.00686 | S157: -0.01744 | T157: -0.13785 | U157: 0.028038 | V157: -0.16379 | W157: -0.02155 | X157: -0.01347 | Y157: 0.129806 | Z157: 0.155674 | AA157: -0.09468 | AB157: -0.00292 | AC157: -0.08996 | AD157: -0.00144 | AE157: -0.27319 | AF157: 0.299689 | AG157: -0.12648 | AH157: 0.044197 | AI157: 0.173556 | AJ157: -0.13909 | AK157: 0.034451 | AL157: -0.07423 | AM157: 0.209376 | AN157: -0.14357 | AO157: 0.013563 | AP157: 0.141643 | AQ157: -0.29486 | AR157: 0.008465 | AS157: 0.024134 | AT157: 1
B158: 0.901023 | C158: 1.08719 | D158: 1.004421 | E158: 1.229429 | F158: 1.82203 | G158: 1.173791 | H158: 1.660451 | I158: 1.826746 | J158: 2.196911 | K158: 0.971739 | L158: 0.700925 | M158: 1.002959 | N158: 1.103414 | O158: 1.936138 | P158: 1.910428 | Q158: 0.72505 | R158: 1.180008 | S158: 0.886876 | T158: 1.000961 | U158: 1.579717 | V158: 0.998875 | W158: 1.001275 | X158: 0.681214 | Y158: 0.91576 | Z158: 1.395223 | AA158: 1.307835 | AB158: 0.867379 | AC158: 1.208314 | AD158: 1.107794 | AE158: 1.806218 | AF158: 1.735888 | AG158: 1.521076 | AH158: 1.885807 | AI158: 1.211524 | AJ158: 2.113708 | AK158: 1.241718 | AL158: 0.924878 | AM158: 1.245491 | AN158: 1.410425 | AO158: 0.848394 | AP158: 1.642164 | AQ158: 1.304326 | AR158: 0.726119 | AS158: 0.548806 | AT158: 0.886544 | AU158: 56.43696
A160: KMO
B162: 1.Delay in delivering material to construction site | C162: 2.Monopoly of material by some suppliers | D162: 3.Prices fluctuation | E162: 4.Types of material availability at local market | F162: 5.Lack of consultant’s knowledge of available materials | G162: 6.Low productivity | H162: 7.Poor work execution | I162: 8.Shortage of laborers | J162: 9.Mistakes happens during construction phase | K162: 10.Unavailability of equipment | L162: 11.Lack of engineering experience | M162: 12.Construction cost underestimation | N162: 13.Poor site management | O162: 14.Delayed payment for completed work | P162: 15.Cash flow problem during construction | Q162: 16.High rate of interest | R162: 17.Contractor’s financial difficulties | S162: 19.Change design | T162: 20.Errors and omission in design | U162: 21.Incomplete design drawings and specifications at tendering stage | V162: 22.Delay in preparation and approval of drawing | W162: 23.Inaccurate quantity take-off | X162: 24.Long period from planning of project to construction | Y162: 25.Delays in issuing information to the contractor during construction stage | Z162: 26.No practical use of earned value management system | AA162: 27.Lack of cost planning/monitoring during pre and post contract stage | AB162: 28.Poor communication between client, consultant and contractor | AC162: 29.Insufficient coordination between local authority who is responsible about road projects and service authorities | AD162: 30.Delays in decisions making by the approval authorities | AE162: 31.Change schedule | AF162: 32.Stoppages because of work being rejected by consultant | AG162: 33.Lowest bid price | AH162: 34.Insufficient time for preparation of contract documents | AI162: 35.Discrepancies in contract documents | AJ162: 36.Underestimation of time for completion of project | AK162: 37.Extension of time with cost claims | AL162: 38.Scope and specification changes | AM162: 39.Changes in client requirements | AN162: 40.Frequency of variation orders and additional works | AO162: 41.Rework due to error in execution | AP162: 42.Weather conditions | AQ162: 43.Accidents during construction | AR162: 44.Delay in getting NOCs from different government authorities | AS162: Location of organization | AT162: Relevant working experience
B163: 0.824972 | C163: 0.753338 | D163: 0.691914 | E163: 0.809378 | F163: 0.772098 | G163: 0.844145 | H163: 0.818571 | I163: 0.769504 | J163: 0.752796 | K163: 0.862767 | L163: 0.907212 | M163: 0.870499 | N163: 0.852143 | O163: 0.570167 | P163: 0.647644 | Q163: 0.862175 | R163: 0.663062 | S163: 0.836903 | T163: 0.812289 | U163: 0.725625 | V163: 0.753898 | W163: 0.746632 | X163: 0.569222 | Y163: 0.850098 | Z163: 0.773336 | AA163: 0.841238 | AB163: 0.872517 | AC163: 0.7292 | AD163: 0.656005 | AE163: 0.620685 | AF163: 0.724352 | AG163: 0.58928 | AH163: 0.750442 | AI163: 0.815227 | AJ163: 0.615349 | AK163: 0.63289 | AL163: 0.7356 | AM163: 0.720601 | AN163: 0.622762 | AO163: 0.806187 | AP163: 0.75382 | AQ163: 0.723841 | AR163: 0.811343 | AS163: 0.560343 | AT163: 0.346684 | AU163: 0.766856
A165: Eigenvalues and eigenvectors
B167: 13.24902 | C167: 4.109563 | D167: 3.009904 | E167: 2.521689 | F167: 2.041292 | G167: 1.626274 | H167: 1.60841 | I167: 1.45329 | J167: 1.36846 | K167: 1.199541 | L167: 1.091042 | M167: 1.036112 | N167: 1.006165 | O167: 0.834988 | P167: 0.807773 | Q167: 0.722339 | R167: 0.639153 | S167: 0.623906 | T167: 0.582281 | U167: 0.534664 | V167: 0.511961 | W167: 0.459355 | X167: 0.382607 | Y167: 0.340528 | Z167: 0.33643 | AA167: 0.298327 | AB167: 0.281388 | AC167: 0.26568 | AD167: 0.239051 | AE167: 0.210505 | AF167: 0.194898 | AG167: 0.171041 | AH167: 0.16796 | AI167: 0.149935 | AJ167: 0.141967 | AK167: 0.128508 | AL167: 0.104914 | AM167: 0.100296 | AN167: 0.087254 | AO167: 0.083429 | AP167: 0.076379 | AQ167: 0.066021 | AR167: 0.060467 | AS167: 0.043956 | AT167: 0.031277
B168: -0.1462 | C168: -0.21913 | D168: -0.1188 | E168: -0.18317 | F168: -0.17241 | G168: -0.0467 | H168: -0.04934 | I168: -0.04265 | J168: -0.04914 | K168: -0.02301 | L168: -0.1474 | M168: -0.01382 | N168: -0.21113 | O168: -0.05024 | P168: -0.12351 | Q168: -0.336 | R168: -0.06816 | S168: -0.22402 | T168: -0.00976 | U168: -0.13026 | V168: -0.18962 | W168: -0.16239 | X168: -0.09283 | Y168: -0.04812 | Z168: -0.08227 | AA168: -0.13259 | AB168: -0.11212 | AC168: -0.11063 | AD168: -0.10443 | AE168: -0.1755 | AF168: -0.1391 | AG168: -0.29838 | AH168: -0.12512 | AI168: -0.08404 | AJ168: -0.07509 | AK168: -0.26638 | AL168: -0.32352 | AM168: -0.20925 | AN168: -0.09395 | AO168: -0.00891 | AP168: -0.12259 | AQ168: -0.12052 | AR168: -0.02835 | AS168: -0.11077 | AT168: -0.05462
B169: -0.12174 | C169: -0.21088 | D169: 0.032194 | E169: -0.28227 | F169: -0.25225 | G169: 0.099234 | H169: 0.089243 | I169: -0.01382 | J169: 0.018017 | K169: 0.086115 | L169: -0.15686 | M169: -0.1091 | N169: 0.057095 | O169: 0.069535 | P169: -0.00072 | Q169: -0.15621 | R169: 0.033611 | S169: 0.176797 | T169: 0.09505 | U169: -0.18107 | V169: 0.175881 | W169: 0.134682 | X169: 0.131612 | Y169: 0.023395 | Z169: -0.32019 | AA169: -0.27012 | AB169: 0.049272 | AC169: -0.20858 | AD169: 0.09878 | AE169: -0.03835 | AF169: -0.01378 | AG169: 0.295345 | AH169: 0.142452 | AI169: -0.21402 | AJ169: 0.01304 | AK169: 0.092892 | AL169: 0.03431 | AM169: 0.160361 | AN169: -0.11403 | AO169: -0.21307 | AP169: 0.193667 | AQ169: 0.164929 | AR169: -0.06353 | AS169: 0.024503 | AT169: 0.104238
B170: -0.10038 | C170: -0.18412 | D170: 0.100408 | E170: 0.090611 | F170: -0.19064 | G170: 0.293464 | H170: -0.03077 | I170: 0.144276 | J170: -0.17504 | K170: -0.15155 | L170: 0.199439 | M170: 0.202272 | N170: 0.190363 | O170: 0.086181 | P170: 0.295334 | Q170: 0.109653 | R170: 0.16984 | S170: -0.04804 | T170: 0.118049 | U170: -0.03644 | V170: -0.04426 | W170: -0.19765 | X170: 0.373427 | Y170: -0.08547 | Z170: -0.05403 | AA170: 0.202473 | AB170: 0.179397 | AC170: -0.09867 | AD170: 0.050083 | AE170: -0.15927 | AF170: 0.111292 | AG170: -0.0544 | AH170: 0.119231 | AI170: 0.092528 | AJ170: -0.11672 | AK170: -0.09322 | AL170: -0.14662 | AM170: -0.1066 | AN170: 0.120438 | AO170: -0.14179 | AP170: -0.16513 | AQ170: 0.045538 | AR170: -0.08506 | AS170: -0.01095 | AT170: -0.06153
B171: -0.16842 | C171: -0.2109 | D171: -0.01297 | E171: -0.13575 | F171: -0.17098 | G171: 0.064525 | H171: -0.04833 | I171: 0.018063 | J171: -0.14037 | K171: -0.19889 | L171: 0.122819 | M171: 0.137472 | N171: -0.10628 | O171: -0.16155 | P171: 0.029508 | Q171: -0.16789 | R171: -0.23161 | S171: 0.012205 | T171: -0.05393 | U171: -0.01517 | V171: -0.09192 | W171: 0.153441 | X171: 0.248976 | Y171: 0.097804 | Z171: 0.046631 | AA171: 0.18673 | AB171: -0.05226 | AC171: 0.067919 | AD171: -0.13522 | AE171: 0.10659 | AF171: -0.07432 | AG171: 0.128022 | AH171: -0.36257 | AI171: 0.192136 | AJ171: 0.328873 | AK171: 0.210304 | AL171: 0.059669 | AM171: 0.07117 | AN171: 0.083713 | AO171: 0.130232 | AP171: 0.087126 | AQ171: 0.006816 | AR171: 0.250518 | AS171: -0.04682 | AT171: 0.174459
B172: -0.19469 | C172: -0.05263 | D172: 0.100582 | E172: 0.032345 | F172: -0.17559 | G172: 0.037408 | H172: -0.03373 | I172: -0.08142 | J172: 0.004212 | K172: -0.04093 | L172: 0.040342 | M172: -0.01169 | N172: 0.17519 | O172: -0.29875 | P172: 0.128413 | Q172: -0.07136 | R172: -0.08653 | S172: 0.389348 | T172: 0.182161 | U172: 0.106056 | V172: -0.04025 | W172: -0.05522 | X172: -0.33503 | Y172: 0.246415 | Z172: 0.115316 | AA172: 0.084287 | AB172: -0.26414 | AC172: 0.093238 | AD172: 0.087501 | AE172: -0.16657 | AF172: -0.03797 | AG172: 0.111395 | AH172: -0.05503 | AI172: 0.007304 | AJ172: -0.25605 | AK172: -0.0386 | AL172: 0.04579 | AM172: -0.18345 | AN172: 0.15866 | AO172: -0.00228 | AP172: 0.201903 | AQ172: 0.053683 | AR172: -0.07027 | AS172: -0.05221 | AT172: -0.22705
B173: -0.18718 | C173: -0.22253 | D173: -0.03932 | E173: 0.098678 | F173: 0.174391 | G173: 0.073033 | H173: 0.118276 | I173: -0.07461 | J173: 0.029606 | K173: -0.04417 | L173: -0.11672 | M173: 0.151607 | N173: -0.04832 | O173: 0.013852 | P173: -0.14005 | Q173: -0.05807 | R173: 0.097484 | S173: 0.027082 | T173: -0.19498 | U173: 0.099557 | V173: 0.063174 | W173: -0.12964 | X173: 0.195111 | Y173: 0.138984 | Z173: 0.115728 | AA173: -0.04633 | AB173: 0.039886 | AC173: 0.145318 | AD173: 0.119697 | AE173: 0.243854 | AF173: -0.01621 | AG173: 0.040459 | AH173: -0.13301 | AI173: -0.15143 | AJ173: -0.11088 | AK173: -0.32609 | AL173: -0.04659 | AM173: 0.125996 | AN173: 0.207238 | AO173: 0.220442 | AP173: 0.175186 | AQ173: 0.067198 | AR173: -0.39568 | AS173: 0.209083 | AT173: 0.171167
B174: -0.2091 | C174: -0.18401 | D174: -0.05116 | E174: 0.041705 | F174: 0.083975 | G174: 0.119398 | H174: 0.054173 | I174: 0.016564 | J174: 0.039612 | K174: -0.15989 | L174: -0.08859 | M174: 0.078849 | N174: -0.16028 | O174: -0.12619 | P174: -0.07665 | Q174: 0.125281 | R174: 0.085925 | S174: 0.004836 | T174: -0.03297 | U174: 0.099749 | V174: -0.06975 | W174: -0.04873 | X174: 0.06423 | Y174: 0.072889 | Z174: -0.08589 | AA174: 0.038779 | AB174: 0.141598 | AC174: 0.400413 | AD174: 0.013812 | AE174: 0.132248 | AF174: -0.15633 | AG174: -0.22848 | AH174: 0.211199 | AI174: -0.12378 | AJ174: -0.03794 | AK174: 0.107654 | AL174: 0.102073 | AM174: 0.095873 | AN174: -0.3747 | AO174: -0.165 | AP174: 0.117409 | AQ174: 0.127501 | AR174: 0.223918 | AS174: -0.08076 | AT174: -0.35151
B175: -0.18586 | C175: -0.18285 | D175: -0.13211 | E175: 0.034894 | F175: 0.049007 | G175: -0.05392 | H175: 0.116286 | I175: -0.23293 | J175: -0.02672 | K175: -0.00068 | L175: 0.110485 | M175: 0.092842 | N175: 0.093252 | O175: 0.194229 | P175: -0.0694 | Q175: -0.17847 | R175: 0.151697 | S175: -0.20474 | T175: -0.15384 | U175: -0.0126 | V175: -0.00591 | W175: 0.154698 | X175: -0.17399 | Y175: 0.216808 | Z175: 0.08228 | AA175: 0.085718 | AB175: -0.06474 | AC175: -0.17703 | AD175: 0.015218 | AE175: 0.064745 | AF175: 0.106517 | AG175: 0.245934 | AH175: 0.016912 | AI175: -0.08556 | AJ175: -0.08962 | AK175: 0.088557 | AL175: 0.074096 | AM175: 0.12864 | AN175: 0.106559 | AO175: -0.04052 | AP175: -0.43962 | AQ175: 0.036211 | AR175: 0.180032 | AS175: 0.145189 | AT175: -0.33637
B176: -0.19505 | C176: -0.18164 | D176: 0.084324 | E176: 0.18272 | F176: 0.094793 | G176: 0.027839 | H176: -0.03913 | I176: -0.09173 | J176: -0.03162 | K176: 0.088454 | L176: -0.09141 | M176: -0.06587 | N176: 0.148951 | O176: 0.038944 | P176: -0.11504 | Q176: 0.108299 | R176: 0.084388 | S176: -0.00435 | T176: -0.14585 | U176: -0.13068 | V176: -0.20107 | W176: -0.08925 | X176: -0.17162 | Y176: -0.22354 | Z176: -0.06844 | AA176: 0.105056 | AB176: 0.000964 | AC176: -0.00212 | AD176: 0.346255 | AE176: -0.11779 | AF176: -0.18903 | AG176: 0.007633 | AH176: 0.080454 | AI176: -0.00657 | AJ176: -0.1761 | AK176: 0.25865 | AL176: -0.13443 | AM176: -0.02552 | AN176: 0.079164 | AO176: 0.157104 | AP176: 0.059905 | AQ176: -0.01893 | AR176: 0.342119 | AS176: 0.02333 | AT176: 0.405396
B177: -0.19074 | C177: -0.08488 | D177: -0.15023 | E177: -0.00686 | F177: 0.027416 | G177: -0.04391 | H177: 0.058844 | I177: -0.08149 | J177: -0.3339 | K177: 0.175525 | L177: -0.01464 | M177: -0.05782 | N177: 0.110008 | O177: 0.230572 | P177: -0.19491 | Q177: 0.039612 | R177: 0.021138 | S177: -0.00197 | T177: 0.002393 | U177: 0.086529 | V177: -0.05235 | W177: 0.256436 | X177: -0.12068 | Y177: -0.10321 | Z177: 0.038831 | AA177: 0.153751 | AB177: 0.177897 | AC177: 0.186152 | AD177: -0.1036 | AE177: -0.21752 | AF177: 0.076372 | AG177: -0.1147 | AH177: -0.11658 | AI177: 0.100626 | AJ177: 0.062106 | AK177: 0.099471 | AL177: 0.042117 | AM177: 0.055451 | AN177: 0.09668 | AO177: -0.35755 | AP177: 0.22869 | AQ177: -0.281 | AR177: -0.29387 | AS177: -0.05451 | AT177: -0.01033
B178: -0.1994 | C178: -0.17475 | D178: 0.022769 | E178: -0.01029 | F178: 0.164769 | G178: 0.083182 | H178: 0.169104 | I178: 0.118545 | J178: 0.048195 | K178: 0.093323 | L178: 0.160754 | M178: -0.11258 | N178: 0.080622 | O178: -0.10511 | P178: 0.06374 | Q178: -0.04362 | R178: -0.07541 | S178: -0.13406 | T178: 0.098177 | U178: -0.1486 | V178: 0.067163 | W178: -0.00838 | X178: -0.07331 | Y178: -0.06638 | Z178: 0.192823 | AA178: -0.10082 | AB178: 0.092113 | AC178: 0.008855 | AD178: -0.08276 | AE178: -0.00644 | AF178: 0.120684 | AG178: -0.10513 | AH178: 0.228997 | AI178: -0.34974 | AJ178: 0.351346 | AK178: 0.251863 | AL178: 0.095665 | AM178: -0.31895 | AN178: 0.136842 | AO178: 0.281809 | AP178: 0.002496 | AQ178: 0.018102 | AR178: -0.16906 | AS178: -0.13976 | AT178: -0.04507
... B212: 0.029545 | C212: 0.023641 | D212: -0.04288 | E212: 0.004613 | F212: 0.328726 | G212: -0.13448 | H212: 0.373683 | I212: -0.17884 | J212: 0.165291 | K212: -0.1739 | L212: -0.09975 | M212: 0.270864 | N212: -0.03979 | O212: 0.199864 | P212: 0.072232 | Q212: -0.13976 | R212: -0.34077 | S212: 0.168274 | T212: 0.377607 | U212: -0.032 | V212: -0.25143 | W212: 0.111325 | X212: 0.129757 | Y212: -0.15664 | Z212: -0.00983 | AA212: 0.106345 | AB212: 0.074024 | AC212: -0.15433 | AD212: 0.090686 | AE212: -0.05824 | AF212: -0.01812 | AG212: 0.012954 | AH212: 0.077828 | AI212: 0.027828 | AJ212: -0.06582 | AK212: -0.02695 | AL212: -0.05871 | AM212: 0.008533 | AN212: -0.0034 | AO212: 0.040504 | AP212: 0.089484 | AQ212: -0.03069 | AR212: 0.027153 | AS212: -0.03467 | AT212: -0.07733
A214: Full Load Matrix
B216: 1 | C216: 2 | D216: 3 | E216: 4 | F216: 5 | G216: 6 | H216: 7 | I216: 8 | J216: 9 | K216: 10 | L216: 11 | M216: 12 | N216: 13 | O216: 14 | P216: 15 | Q216: 16 | R216: 17 | S216: 18 | T216: 19 | U216: 20 | V216: 21 | W216: 22 | X216: 23 | Y216: 24 | Z216: 25 | AA216: 26 | AB216: 27 | AC216: 28 | AD216: 29 | AE216: 30 | AF216: 31 | AG216: 32 | AH216: 33 | AI216: 34 | AJ216: 35 | AK216: 36 | AL216: 37 | AM216: 38 | AN216: 39 | AO216: 40 | AP216: 41 | AQ216: 42 | AR216: 43 | AS216: 44 | AT216: 45 | AV216: Commun
A217: 1.Delay in delivering material to construction site | B217: -0.53214 | C217: -0.44422 | D217: -0.20612 | E217: -0.29087 | F217: -0.24633 | G217: -0.05955 | H217: -0.06257 | I217: -0.05141 | J217: -0.05748 | K217: -0.0252 | L217: -0.15396 | M217: -0.01407 | N217: -0.21178 | O217: -0.04591 | P217: -0.11101 | Q217: -0.28557 | R217: -0.05449 | S217: -0.17695 | T217: -0.00745 | U217: -0.09525 | V217: -0.13568 | W217: -0.11006 | X217: -0.05742 | Y217: -0.02808 | Z217: -0.04772 | AA217: -0.07242 | AB217: -0.05948 | AC217: -0.05703 | AD217: -0.05106 | AE217: -0.08052 | AF217: -0.06141 | AG217: -0.1234 | AH217: -0.05128 | AI217: -0.03254 | AJ217: -0.02829 | AK217: -0.09549 | AL217: -0.10479 | AM217: -0.06627 | AN217: -0.02775 | AO217: -0.00257 | AP217: -0.03388 | AQ217: -0.03097 | AR217: -0.00697 | AS217: -0.02322 | AT217: -0.00966 | AV217: 1
A218: 2.Monopoly of material by some suppliers | B218: -0.44311 | C218: -0.4275 | D218: 0.055854 | E218: -0.44824 | F218: -0.3604 | G218: 0.126549 | H218: 0.11318 | I218: -0.01666 | J218: 0.021076 | K218: 0.094316 | L218: -0.16385 | M218: -0.11106 | N218: 0.057271 | O218: 0.063539 | P218: -0.00064 | Q218: -0.13277 | R218: 0.026871 | S218: 0.139648 | T218: 0.07253 | U218: -0.1324 | V218: 0.125845 | W218: 0.091281 | X218: 0.081409 | Y218: 0.013652 | Z218: -0.18572 | AA218: -0.14754 | AB218: 0.026137 | AC218: -0.10751 | AD218: 0.048296 | AE218: -0.0176 | AF218: -0.00608 | AG218: 0.122146 | AH218: 0.058381 | AI218: -0.08287 | AJ218: 0.004913 | AK218: 0.0333 | AL218: 0.011113 | AM218: 0.050786 | AN218: -0.03368 | AO218: -0.06154 | AP218: 0.053523 | AQ218: 0.042378 | AR218: -0.01562 | AS218: 0.005137 | AT218: 0.018435 | AV218: 1
A219: 3.Prices fluctuation | B219: -0.36537 | C219: -0.37325 | D219: 0.174199 | E219: 0.143889 | F219: -0.27238 | G219: 0.374241 | H219: -0.03902 | I219: 0.173928 | J219: -0.20477 | K219: -0.16599 | L219: 0.20832 | M219: 0.205892 | N219: 0.190949 | O219: 0.07875 | P219: 0.265435 | Q219: 0.093195 | R219: 0.135782 | S219: -0.03794 | T219: 0.09008 | U219: -0.02665 | V219: -0.03167 | W219: -0.13396 | X219: 0.230984 | Y219: -0.04988 | Z219: -0.03134 | AA219: 0.110589 | AB219: 0.095163 | AC219: -0.05086 | AD219: 0.024487 | AE219: -0.07307 | AF219: 0.049132 | AG219: -0.0225 | AH219: 0.048864 | AI219: 0.035828 | AJ219: -0.04398 | AK219: -0.03342 | AL219: -0.04749 | AM219: -0.03376 | AN219: 0.035576 | AO219: -0.04096 | AP219: -0.04564 | AQ219: 0.011701 | AR219: -0.02092 | AS219: -0.0023 | AT219: -0.01088 | AV219: 1
A220: 4.Types of material availability at local market | B220: -0.61304 | C220: -0.42753 | D220: -0.0225 | E220: -0.21557 | F220: -0.24429 | G220: 0.082286 | H220: -0.06129 | I220: 0.021776 | J220: -0.16421 | K220: -0.21784 | L220: 0.128288 | M220: 0.139932 | N220: -0.10661 | O220: -0.14762 | P220: 0.026521 | Q220: -0.14269 | R220: -0.18517 | S220: 0.009641 | T220: -0.04115 | U220: -0.01109 | V220: -0.06577 | W220: 0.103995 | X220: 0.154004 | Y220: 0.057073 | Z220: 0.027047 | AA220: 0.101991 | AB220: -0.02772 | AC220: 0.035008 | AD220: -0.06611 | AE220: 0.048904 | AF220: -0.03281 | AG220: 0.052946 | AH220: -0.14859 | AI220: 0.074398 | AJ220: 0.123914 | AK220: 0.07539 | AL220: 0.019327 | AM220: 0.022539 | AN220: 0.024728 | AO220: 0.037616 | AP220: 0.024079 | AQ220: 0.001751 | AR220: 0.061602 | AS220: -0.00982 | AT220: 0.030853 | AV220: 1
A221: 5.Lack of consultant’s knowledge of available materials | B221: -0.70866 | C221: -0.10669 | D221: 0.174501 | E221: 0.051363 | F221: -0.25088 | G221: 0.047704 | H221: -0.04277 | I221: -0.09815 | J221: 0.004928 | K221: -0.04483 | L221: 0.042138 | M221: -0.0119 | N221: 0.17573 | O221: -0.27299 | P221: 0.115412 | Q221: -0.06065 | R221: -0.06918 | S221: 0.307537 | T221: 0.139002 | U221: 0.077549 | V221: -0.0288 | W221: -0.03743 | X221: -0.20723 | Y221: 0.143795 | Z221: 0.066886 | AA221: 0.046037 | AB221: -0.14011 | AC221: 0.048059 | AD221: 0.042782 | AE221: -0.07642 | AF221: -0.01676 | AG221: 0.04607 | AH221: -0.02255 | AI221: 0.002828 | AJ221: -0.09648 | AK221: -0.01384 | AL221: 0.014832 | AM221: -0.0581 | AN221: 0.046866 | AO221: -0.00066 | AP221: 0.055799 | AQ221: 0.013794 | AR221: -0.01728 | AS221: -0.01095 | AT221: -0.04015 | AV221: 1
A222: 6.Low productivity | B222: -0.68133 | C222: -0.45111 | D222: -0.06822 | E222: 0.156699 | F222: 0.249159 | G222: 0.093136 | H222: 0.150002 | I222: -0.08994 | J222: 0.034633 | K222: -0.04838 | L222: -0.12191 | M222: 0.15432 | N222: -0.04847 | O222: 0.012658 | P222: -0.12587 | Q222: -0.04935 | R222: 0.077936 | S222: 0.021392 | T222: -0.14879 | U222: 0.072797 | V222: 0.045202 | W222: -0.08786 | X222: 0.120686 | Y222: 0.081104 | Z222: 0.067125 | AA222: -0.02531 | AB222: 0.021158 | AC222: 0.074903 | AD222: 0.058523 | AE222: 0.111882 | AF222: -0.00716 | AG222: 0.016733 | AH222: -0.05451 | AI222: -0.05863 | AJ222: -0.04178 | AK222: -0.1169 | AL222: -0.01509 | AM222: 0.039902 | AN222: 0.061216 | AO222: 0.063673 | AP222: 0.048416 | AQ222: 0.017266 | AR222: -0.0973 | AS222: 0.043836 | AT222: 0.030271 | AV222: 1
A223: 7.Poor work execution | B223: -0.7611 | C223: -0.37303 | D223: -0.08875 | E223: 0.066228 | F223: 0.119979 | G223: 0.152263 | H223: 0.068704 | I223: 0.019968 | J223: 0.046339 | K223: -0.17512 | L223: -0.09253 | M223: 0.08026 | N223: -0.16077 | O223: -0.11531 | P223: -0.06889 | Q223: 0.106477 | R223: 0.068695 | S223: 0.00382 | T223: -0.02516 | U223: 0.072937 | V223: -0.04991 | W223: -0.03303 | X223: 0.03973 | Y223: 0.042534 | Z223: -0.04982 | AA223: 0.021181 | AB223: 0.075112 | AC223: 0.20639 | AD223: 0.006753 | AE223: 0.060676 | AF223: -0.06902 | AG223: -0.09449 | AH223: 0.086556 | AI223: -0.04793 | AJ223: -0.01429 | AK223: 0.038592 | AL223: 0.033062 | AM223: 0.030363 | AN223: -0.11068 | AO223: -0.04766 | AP223: 0.032448 | AQ223: 0.032761 | AR223: 0.055061 | AS223: -0.01693 | AT223: -0.06216 | AV223: 1
A224: 8.Shortage of laborers | B224: -0.6765 | C224: -0.37068 | D224: -0.22921 | E224: 0.055412 | F224: 0.070018 | G224: -0.06876 | H224: 0.147477 | I224: -0.28081 | J224: -0.03125 | K224: -0.00075 | L224: 0.115404 | M224: 0.094504 | N224: 0.093539 | O224: 0.177482 | P224: -0.06237 | Q224: -0.15168 | R224: 0.121277 | S224: -0.16172 | T224: -0.11739 | U224: -0.00921 | V224: -0.00423 | W224: 0.104848 | X224: -0.10762 | Y224: 0.126518 | Z224: 0.047725 | AA224: 0.046819 | AB224: -0.03434 | AC224: -0.09125 | AD224: 0.007441 | AE224: 0.029706 | AF224: 0.047024 | AG224: 0.101711 | AH224: 0.006931 | AI224: -0.03313 | AJ224: -0.03377 | AK224: 0.031746 | AL224: 0.024 | AM224: 0.04074 | AN224: 0.031476 | AO224: -0.0117 | AP224: -0.1215 | AQ224: 0.009304 | AR224: 0.04427 | AS224: 0.03044 | AT224: -0.05949 | AV224: 1
A225: 9.Mistakes happens during construction phase | B225: -0.70997 | C225: -0.36822 | D225: 0.146294 | E225: 0.290156 | F225: 0.135434 | G225: 0.035502 | H225: -0.04962 | I225: -0.11058 | J225: -0.03699 | K225: 0.096878 | L225: -0.09548 | M225: -0.06705 | N225: 0.149409 | O225: 0.035586 | P225: -0.10339 | Q225: 0.092044 | R225: 0.067466 | S225: -0.00344 | T225: -0.1113 | U225: -0.09556 | V225: -0.14387 | W225: -0.06049 | X225: -0.10616 | Y225: -0.13045 | Z225: -0.0397 | AA225: 0.057381 | AB225: 0.000511 | AC225: -0.00109 | AD225: 0.169294 | AE225: -0.05404 | AF225: -0.08345 | AG225: 0.003157 | AH225: 0.032972 | AI225: -0.00254 | AJ225: -0.06635 | AK225: 0.092721 | AL225: -0.04354 | AM225: -0.00808 | AN225: 0.023384 | AO225: 0.045378 | AP225: 0.016556 | AQ225: -0.00486 | AR225: 0.084127 | AS225: 0.004891 | AT225: 0.071695 | AV225: 1
A226: 10.Unavailability of equipment | B226: -0.69426 | C226: -0.17207 | D226: -0.26064 | E226: -0.01089 | F226: 0.03917 | G226: -0.056 | H226: 0.074628 | I226: -0.09824 | J226: -0.3906 | K226: 0.192242 | L226: -0.01529 | M226: -0.05886 | N226: 0.110347 | O226: 0.210691 | P226: -0.17517 | Q226: 0.033666 | R226: 0.016899 | S226: -0.00156 | T226: 0.001826 | U226: 0.063271 | V226: -0.03746 | W226: 0.173801 | X226: -0.07465 | Y226: -0.06023 | Z226: 0.022523 | AA226: 0.083978 | AB226: 0.094367 | AC226: 0.095951 | AD226: -0.05065 | AE226: -0.0998 | AF226: 0.033716 | AG226: -0.04744 | AH226: -0.04778 | AI226: 0.038964 | AJ226: 0.023401 | AK226: 0.035658 | AL226: 0.013642 | AM226: 0.017561 | AN226: 0.028558 | AO226: -0.10327 | AP226: 0.063203 | AQ226: -0.0722 | AR226: -0.07226 | AS226: -0.01143 | AT226: -0.00183 | AV226: 1
A227: 11.Lack of engineering experience | B227: -0.72581 | C227: -0.35426 | D227: 0.039502 | E227: -0.01635 | F227: 0.235412 | G227: 0.106078 | H227: 0.214463 | I227: 0.142909 | J227: 0.05638 | K227: 0.10221 | L227: 0.167913 | M227: -0.1146 | N227: 0.08087 | O227: -0.09604 | P227: 0.057287 | Q227: -0.03708 | R227: -0.06028 | S227: -0.10589 | T227: 0.074916 | U227: -0.10866 | V227: 0.048056 | W227: -0.00568 | X227: -0.04535 | Y227: -0.03874 | Z227: 0.111842 | AA227: -0.05506 | AB227: 0.048862 | AC227: 0.004564 | AD227: -0.04046 | AE227: -0.00295 | AF227: 0.053279 | AG227: -0.04348 | AH227: 0.09385 | AI227: -0.13542 | AJ227: 0.132382 | AK227: 0.090288 | AL227: 0.030986 | AM227: -0.10101 | AN227: 0.040422 | AO227: 0.081398 | AP227: 0.00069 | AQ227: 0.004651 | AR227: -0.04157 | AS227: -0.0293 | AT227: -0.00797 | AV227: 1
A228: 12.Construction cost underestimation | B228: -0.71994 | C228: -0.27265 | D228: 0.025744 | E228: 0.383086 | F228: 0.13805 | G228: -0.06913 | H228: 0.022934 | I228: 0.011396 | J228: 0.079925 | K228: 0.191368 | L228: 0.190976 | M228: 0.00179 | N228: 0.036916 | O228: 0.126622 | P228: -0.03497 | Q228: 0.026389 | R228: 0.112099 | S228: -0.00882 | T228: 0.063714 | U228: 0.11938 | V228: -0.00539 | W228: 0.066681 | X228: -0.00901 | Y228: -0.06676 | Z228: 0.0939 | AA228: -0.11691 | AB228: -0.06564 | AC228: -0.1185 | AD228: -0.09166 | AE228: -0.04007 | AF228: -0.02127 | AG228: -0.04181 | AH228: -0.05669 | AI228: 0.095215 | AJ228: 0.029959 | AK228: -0.06615 | AL228: 0.016592 | AM228: -0.00911 | AN228: -0.04932 | AO228: -0.01656 | AP228: 0.038122 | AQ228: 0.14259 | AR228: 0.021379 | AS228: -0.02469 | AT228: 0.01257 | AV228: 1
... A261: Relevant working experience | B261: 0.10754 | C261: 0.047924 | D261: -0.07439 | E261: 0.007325 | F261: 0.469663 | G261: -0.17149 | H261: 0.473916 | I261: -0.2156 | J261: 0.193359 | K261: -0.19046 | L261: -0.10419 | M261: 0.275711 | N261: -0.03991 | O261: 0.182631 | P261: 0.06492 | Q261: -0.11878 | R261: -0.27244 | S261: 0.132916 | T261: 0.288142 | U261: -0.0234 | V261: -0.1799 | W261: 0.075451 | X261: 0.080261 | Y261: -0.09141 | Z261: -0.0057 | AA261: 0.058085 | AB261: 0.039267 | AC261: -0.07955 | AD261: 0.044339 | AE261: -0.02672 | AF261: -0.008 | AG261: 0.005357 | AH261: 0.031896 | AI261: 0.010775 | AJ261: -0.0248 | AK261: -0.00966 | AL261: -0.01902 | AM261: 0.002702 | AN261: -0.001 | AO261: 0.011699 | AP261: 0.024731 | AQ261: -0.00789 | AR261: 0.006677 | AS261: -0.00727 | AT261: -0.01368 | AV261: 1
A263: Scree Plot
B265: eValue | C265: % | D265: Cum %
B266: 13.24902 | C266: 0.2944 | D266: 0.2944
B267: 4.109563 | C267: 0.0913 | D267: 0.3857
B268: 3.009904 | C268: 0.0669 | D268: 0.4526
B269: 2.521689 | C269: 0.056 | D269: 0.5087
B270: 2.041292 | C270: 0.0454 | D270: 0.554
B271: 1.626274 | C271: 0.0361 | D271: 0.5902
B272: 1.60841 | C272: 0.0357 | D272: 0.6259
B273: 1.45329 | C273: 0.0323 | D273: 0.6582
B274: 1.36846 | C274: 0.0304 | D274: 0.6886
B275: 1.199541 | C275: 0.0267 | D275: 0.7153
B276: 1.091042 | C276: 0.0242 | D276: 0.7395
B277: 1.036112 | C277: 0.023 | D277: 0.7625
... B310: 0.031277 | C310: 0.0007 | D310: 1
...

Sheet Main Part of Analysis
A1: Scree Plot | G1: KMO
B3: eValue | C3: % | D3: Cum % | H3: 1.Delay in delivering material to construction site | I3: 2.Monopoly of material by some suppliers | J3: 3.Prices fluctuation | K3: 4.Types of material availability at local market | L3: 5.Lack of consultant’s knowledge of available materials | M3: 6.Low productivity | N3: 7.Poor work execution | O3: 8.Shortage of laborers | P3: 9.Mistakes happens during construction phase | Q3: 10.Unavailability of equipment | R3: 11.Lack of engineering experience | S3: 12.Construction cost underestimation | T3: 13.Poor site management | U3: 14.Delayed payment for completed work | V3: 15.Cash flow problem during construction | W3: 16.High rate of interest | X3: 17.Contractor’s financial difficulties | Y3: 19.Change design | Z3: 20.Errors and omission in design | AA3: 21.Incomplete design drawings and specifications at tendering stage | AB3: 22.Delay in preparation and approval of drawing | AC3: 23.Inaccurate quantity take-off | AD3: 24.Long period from planning of project to construction | AE3: 25.Delays in issuing information to the contractor during construction stage | AF3: 26.No practical use of earned value management system | AG3: 27.Lack of cost planning/monitoring during pre and post contract stage | AH3: 28.Poor communication between client, consultant and contractor | AI3: 29.Insufficient coordination between local authority who is responsible about road projects and service authorities | AJ3: 30.Delays in decisions making by the approval authorities | AK3: 31.Change schedule | AL3: 32.Stoppages because of work being rejected by consultant | AM3: 33.Lowest bid price | AN3: 34.Insufficient time for preparation of contract documents | AO3: 35.Discrepancies in contract documents | AP3: 36.Underestimation of time for completion of project | AQ3: 37.Extension of time with cost claims | AR3: 38.Scope and specification changes | AS3: 39.Changes in client requirements | AT3: 40.Frequency of variation orders and additional works | AU3: 41.Rework due to error in execution | AV3: 42.Weather conditions | AW3: 43.Accidents during construction | AX3: 44.Delay in getting NOCs from different government authorities | AY3: Location of organization | AZ3: Relevant working experience
B4: 13.24902 | C4: 0.2944 | D4: 0.2944 | H4: 0.824972 | I4: 0.753338 | J4: 0.691914 | K4: 0.809378 | L4: 0.772098 | M4: 0.844145 | N4: 0.818571 | O4: 0.769504 | P4: 0.752796 | Q4: 0.862767 | R4: 0.907212 | S4: 0.870499 | T4: 0.852143 | U4: 0.570167 | V4: 0.647644 | W4: 0.862175 | X4: 0.663062 | Y4: 0.836903 | Z4: 0.812289 | AA4: 0.725625 | AB4: 0.753898 | AC4: 0.746632 | AD4: 0.569222 | AE4: 0.850098 | AF4: 0.773336 | AG4: 0.841238 | AH4: 0.872517 | AI4: 0.7292 | AJ4: 0.656005 | AK4: 0.620685 | AL4: 0.724352 | AM4: 0.58928 | AN4: 0.750442 | AO4: 0.815227 | AP4: 0.615349 | AQ4: 0.63289 | AR4: 0.7356 | AS4: 0.720601 | AT4: 0.622762 | AU4: 0.806187 | AV4: 0.75382 | AW4: 0.723841 | AX4: 0.811343 | AY4: 0.560343 | AZ4: 0.346684 | BA4: 0.766856
B5: 4.109563 | C5: 0.0913 | D5: 0.3857
B6: 3.009904 | C6: 0.0669 | D6: 0.4526
B7: 2.521689 | C7: 0.056 | D7: 0.5087
B8: 2.041292 | C8: 0.0454 | D8: 0.554
B9: 1.626274 | C9: 0.0361 | D9: 0.5902
B10: 1.60841 | C10: 0.0357 | D10: 0.6259 | G10: Factor Matrix (rotated Varimax)
B11: 1.45329 | C11: 0.0323 | D11: 0.6582
B12: 1.36846 | C12: 0.0304 | D12: 0.6886 | H12: 1 | I12: 2 | J12: 3 | K12: 4 | L12: 5 | M12: 6 | O12: Commun | P12: Specific
B13: 1.199541 | C13: 0.0267 | D13: 0.7153 | G13: 1.Delay in delivering material to construction site | H13: -0.42743 | I13: -0.217 | J13: -0.20707 | K13: 0.004154 | L13: -0.61737 | M13: -0.13413 | O13: 0.671813 | P13: 0.328187
B14: 1.091042 | C14: 0.0242 | D14: 0.7395 | G14: 2.Monopoly of material by some suppliers | H14: -0.29489 | I14: 0.035137 | J14: -0.14306 | K14: -0.19042 | L14: -0.76181 | M14: -0.06141 | O14: 0.729048 | P14: 0.270952
B15: 1.036112 | C15: 0.023 | D15: 0.7625 | G15: 3.Prices fluctuation | H15: -0.43014 | I15: 0.289559 | J15: 0.173324 | K15: 0.100275 | L15: -0.43497 | M15: 0.199858 | O15: 0.538106 | P15: 0.461894
B16: 1.006165 | C16: 0.0224 | D16: 0.7849 | G16: 4.Types of material availability at local market | H16: -0.50993 | I16: 0.013875 | J16: -0.13142 | K16: -0.0054 | L16: -0.61768 | M16: -0.11387 | O16: 0.672023 | P16: 0.327977
B17: 0.834988 | C17: 0.0186 | D17: 0.8035 | G17: 5.Lack of consultant’s knowledge of available materials | H17: -0.45379 | I17: 0.309829 | J17: -0.04435 | K17: 0.225343 | L17: -0.41591 | M17: -0.29024 | O17: 0.611881 | P17: 0.388119
B18: 0.807773 | C18: 0.018 | D18: 0.8214 | G18: 6.Low productivity | H18: -0.86181 | I18: -0.01856 | J18: -0.05572 | K18: 0.052252 | L18: -0.11351 | M18: -0.07665 | O18: 0.767663 | P18: 0.232337
B19: 0.722339 | C19: 0.0161 | D19: 0.8375 | G19: 7.Poor work execution | H19: -0.81165 | I19: 0.062538 | J19: -0.17007 | K19: 0.097767 | L19: -0.24337 | M19: -0.08871 | O19: 0.768264 | P19: 0.231736
B20: 0.639153 | C20: 0.0142 | D20: 0.8517 | G20: 8.Shortage of laborers | H20: -0.69791 | I20: -0.16785 | J20: -0.16827 | K20: 0.166463 | L20: -0.24097 | M20: -0.17595 | O20: 0.660296 | P20: 0.339704
B21: 0.623906 | C21: 0.0139 | D21: 0.8655 | G21: 9.Mistakes happens during construction phase | H21: -0.80615 | I21: 0.151749 | J21: 0.121543 | K21: 0.144758 | L21: -0.12515 | M21: -0.20136 | O21: 0.764842 | P21: 0.235158
B22: 0.582281 | C22: 0.0129 | D22: 0.8785 | G22: 10.Unavailability of equipment | H22: -0.57933 | I22: -0.09021 | J22: -0.31335 | K22: 0.213045 | L22: -0.21609 | M22: -0.22428 | O22: 0.584325 | P22: 0.415675
B23: 0.534664 | C23: 0.0119 | D23: 0.8904 | G23: 11.Lack of engineering experience | H23: -0.79104 | I23: 0.099912 | J23: -0.14681 | K23: -0.06235 | L23: -0.17178 | M23: -0.17356 | O23: 0.720801 | P23: 0.279199
B24: 0.511961 | C24: 0.0114 | D24: 0.9017 | G24: 12.Construction cost underestimation | H24: -0.77285 | I24: 0.068882 | J24: 0.080759 | K24: 0.296076 | L24: -0.03753 | M24: -0.25742 | O24: 0.763904 | P24: 0.236096
... B48: 0.031277 | C48: 0.0007 | D48: 1 | G48: 37.Extension of time with cost claims | H48: -0.054 | I48: -0.07994 | J48: -0.4764 | K48: 0.093694 | L48: -0.31895 | M48: -0.19383 | O48: 0.38434 | P48: 0.61566
B49: 45 | G49: 38.Scope and specification changes | H49: -0.1219 | I49: 0.047085 | J49: -0.07732 | K49: 0.795198 | L49: -0.0281 | M49: -0.09688 | O49: 0.665571 | P49: 0.334429
G50: 39.Changes in client requirements | H50: -0.27487 | I50: 0.033092 | J50: -0.17186 | K50: 0.76887 | L50: -0.13299 | M50: 0.098823 | O50: 0.724797 | P50: 0.275203
G51: 40.Frequency of variation orders and additional works | H51: -0.10664 | I51: -0.02455 | J51: -0.10565 | K51: 0.76257 | L51: -0.02592 | M51: -0.11868 | O51: 0.619409 | P51: 0.380591
G52: 41.Rework due to error in execution | H52: -0.38445 | I52: 0.201913 | J52: 0.072873 | K52: 0.095183 | L52: -0.09845 | M52: -0.39736 | O52: 0.37053 | P52: 0.62947
G53: 42.Weather conditions | H53: -0.25381 | I53: 0.175261 | J53: -0.19443 | K53: -0.14552 | L53: -0.25877 | M53: -0.66699 | O53: 0.665947 | P53: 0.334053
G54: 43.Accidents during construction | H54: -0.24571 | I54: 0.023274 | J54: -0.03687 | K54: -0.0961 | L54: -0.47802 | M54: -0.46042 | O54: 0.512005 | P54: 0.487995
G55: 44.Delay in getting NOCs from different government authorities | H55: -0.20072 | I55: -0.15448 | J55: -0.65944 | K55: -0.01934 | L55: -0.23474 | M55: -0.16013 | O55: 0.580129 | P55: 0.419871
G56: Location of organization | H56: 0.133712 | I56: 0.509408 | J56: 0.181049 | K56: -0.28787 | L56: -0.25944 | M56: 0.135387 | O56: 0.478665 | P56: 0.521335
G57: Relevant working experience | H57: -0.06545 | I57: -0.19444 | J57: -0.06086 | K57: -0.17684 | L57: 0.429176 | M57: -0.09046 | O57: 0.269441 | P57: 0.730559
H58: 7.872626 | I58: 3.535375 | J58: 4.244592 | K58: 3.37707 | L58: 3.261012 | M58: 4.267069 | O58: 26.55774 | P58: 18.44226

Sheet Factor Interpretation
A1: Factor Matrix (rotated Varimax)
B3: Factor 1: Construction execution / site management problems | C3: Factor 2: Design and planning deficiencies | D3: Factor 3: Financial and administrative delays | E3: Factor 4: Scope changes / client changes | F3: Factor 5: Supply and procurement issues | G3: Factor 6: Contract management / external conditions | I3: Commun | J3: Specific | L3: Factor 1: Construction execution / site management problems | O3: Factor 2: Design and planning deficiencies | R3: Factor 3: Financial and administrative delays | U3: Factor 4: Scope changes / client changes | X3: Factor 5: Supply and procurement issues | AA3: Factor 6: Contract management / external conditions
A4: 1.Delay in delivering material to construction site | B4: -0.42743 | C4: -0.217 | D4: -0.20707 | E4: 0.004154 | F4: -0.61737 | G4: -0.13413 | I4: 0.671813 | J4: 0.328187 | L4: 6.Low productivity | M4: -0.86181 | O4: 20.Errors and omission in design | P4: 0.655962 | R4: 14.Delayed payment for completed work | S4: -0.75304 | U4: 38.Scope and specification changes | V4: 0.795198 | X4: 1.Delay in delivering material to construction site | Y4: -0.61737 | AA4: 34.Insufficient time for preparation of contract documents | AB4: -0.66338
A5: 2.Monopoly of material by some suppliers | B5: -0.29489 | C5: 0.035137 | D5: -0.14306 | E5: -0.19042 | F5: -0.76181 | G5: -0.06141 | I5: 0.729048 | J5: 0.270952 | L5: 7.Poor work execution | M5: -0.81165 | O5: 21.Incomplete design drawings and specifications at tendering stage | P5: 0.641673 | R5: 15.Cash flow problem during construction | S5: -0.70674 | U5: 39.Changes in client requirements | V5: 0.76887 | X5: 2.Monopoly of material by some suppliers | Y5: -0.76181 | AA5: 42.Weather conditions | AB5: -0.66699
A6: 3.Prices fluctuation | B6: -0.43014 | C6: 0.289559 | D6: 0.173324 | E6: 0.100275 | F6: -0.43497 | G6: 0.199858 | I6: 0.538106 | J6: 0.461894 | L6: 8.Shortage of laborers | M6: -0.69791 | O6: 23.Inaccurate quantity take-off | P6: 0.655488 | R6: 17.Contractor’s financial difficulties | S6: -0.61867 | U6: 40.Frequency of variation orders and additional works | V6: 0.76257 | X6: 4.Types of material availability at local market | Y6: -0.61768
A7: 4.Types of material availability at local market | B7: -0.50993 | C7: 0.013875 | D7: -0.13142 | E7: -0.0054 | F7: -0.61768 | G7: -0.11387 | I7: 0.672023 | J7: 0.327977 | L7: 9.Mistakes happens during construction phase | M7: -0.80615 | R7: 30.Delays in decisions making by the approval authorities | S7: -0.63904
A8: 5.Lack of consultant’s knowledge of available materials | B8: -0.45379 | C8: 0.309829 | D8: -0.04435 | E8: 0.225343 | F8: -0.41591 | G8: -0.29024 | I8: 0.611881 | J8: 0.388119 | L8: 11.Lack of engineering experience | M8: -0.79104 | R8: 44.Delay in getting NOCs from different government authorities | S8: -0.65944
A9: 6.Low productivity | B9: -0.86181 | C9: -0.01856 | D9: -0.05572 | E9: 0.052252 | F9: -0.11351 | G9: -0.07665 | I9: 0.767663 | J9: 0.232337 | L9: 12.Construction cost underestimation | M9: -0.77285
A10: 7.Poor work execution | B10: -0.81165 | C10: 0.062538 | D10: -0.17007 | E10: 0.097767 | F10: -0.24337 | G10: -0.08871 | I10: 0.768264 | J10: 0.231736 | L10: 13.Poor site management | M10: -0.76484
A11: 8.Shortage of laborers | B11: -0.69791 | C11: -0.16785 | D11: -0.16827 | E11: 0.166463 | F11: -0.24097 | G11: -0.17595 | I11: 0.660296 | J11: 0.339704
A12: 9.Mistakes happens during construction phase | B12: -0.80615 | C12: 0.151749 | D12: 0.121543 | E12: 0.144758 | F12: -0.12515 | G12: -0.20136 | I12: 0.764842 | J12: 0.235158
A13: 10.Unavailability of equipment | B13: -0.57933 | C13: -0.09021 | D13: -0.31335 | E13: 0.213045 | F13: -0.21609 | G13: -0.22428 | I13: 0.584325 | J13: 0.415675
A14: 11.Lack of engineering experience | B14: -0.79104 | C14: 0.099912 | D14: -0.14681 | E14: -0.06235 | F14: -0.17178 | G14: -0.17356 | I14: 0.720801 | J14: 0.279199 | L14: Some items show cross-loading, for example:
A15: 12.Construction cost underestimation | B15: -0.77285 | C15: 0.068882 | D15: 0.080759 | E15: 0.296076 | F15: -0.03753 | G15: -0.25742 | I15: 0.763904 | J15: 0.236096 | L15: Prices fluctuation
A16: 13.Poor site management | B16: -0.76484 | C16: 0.172559 | D16: -0.10891 | E16: 0.141591 | F16: -0.05751 | G16: -0.10992 | I16: 0.662052 | J16: 0.337948 | L16: Communication problems
A17: 14.Delayed payment for completed work | B17: 0.057623 | C17: -0.01215 | D17: -0.75304 | E17: 0.244967 | F17: -0.11854 | G17: -0.04671 | I17: 0.646774 | J17: 0.353226 | L17: Some coordination variables
A18: 15.Cash flow problem during construction | B18: 0.011461 | C18: 0.246447 | D18: -0.70674 | E18: 0.145104 | F18: -0.12257 | G18: -0.17049 | I18: 0.62549 | J18: 0.37451 | L18: But this is normal in exploratory models.
A19: 16.High rate of interest | B19: -0.16497 | C19: 0.283684 | D19: -0.25023 | E19: 0.131664 | F19: -0.00472 | G19: -0.59984 | I19: 0.547467 | J19: 0.452533 | L19: Variance explained
A20: 17.Contractor’s financial difficulties | B20: 0.041407 | C20: 0.240986 | D20: -0.61867 | E20: -0.03131 | F20: -0.0257 | G20: -0.20306 | I20: 0.485421 | J20: 0.514579 | L20: Your table shows about:
A21: 19.Change design | B21: -0.31121 | C21: 0.566415 | D21: 0.012153 | E21: 0.270686 | F21: -0.22682 | G21: -0.20199 | I21: 0.583341 | J21: 0.416659 | L21: ~26.6% common variance captured by the 6 factors
A22: 20.Errors and omission in design | B22: -0.13596 | C22: 0.655962 | D22: -0.10451 | E22: 0.069415 | F22: -0.13694 | G22: -0.40617 | I22: 0.64824 | J22: 0.35176 | L22: This is typical for large social-science surveys.
A23: 21.Incomplete design drawings and specifications at tendering stage | B23: -0.04604 | C23: 0.641673 | D23: -0.20072 | E23: 0.42273 | F23: -0.06014 | G23: -0.24954 | I23: 0.69874 | J23: 0.30126 | L23: If you lower the cutoff to 0.50, many of your cross-loadings will disappear.
A24: 22.Delay in preparation and approval of drawing | B24: -0.01913 | C24: 0.378018 | D24: -0.26751 | E24: 0.459281 | F24: 0.072028 | G24: -0.26998 | I24: 0.503841 | J24: 0.496159
A25: 23.Inaccurate quantity take-off | B25: -0.05873 | C25: 0.655488 | D25: -0.02691 | E25: 0.008989 | F25: 0.118505 | G25: -0.43472 | I25: 0.636946 | J25: 0.363054
A26: 24.Long period from planning of project to construction | B26: -0.03842 | C26: 0.473665 | D26: -0.19655 | E26: -0.07501 | F26: 0.101998 | G26: -0.0101 | I26: 0.280599 | J26: 0.719401
A27: 25.Delays in issuing information to the contractor during construction stage | B27: -0.35741 | C27: 0.4414 | D27: -0.41498 | E27: -0.05617 | F27: -0.00357 | G27: -0.31086 | I27: 0.594591 | J27: 0.405409
A28: 26.No practical use of earned value management system | B28: -0.32792 | C28: 0.328056 | D28: -0.16989 | E28: 0.321843 | F28: 0.14277 | G28: -0.41021 | I28: 0.536253 | J28: 0.463747
A29: 27.Lack of cost planning/monitoring during pre and post contract stage | B29: -0.49309 | C29: 0.395415 | D29: -0.39608 | E29: 0.143697 | F29: -0.00642 | G29: -0.28613 | I29: 0.658928 | J29: 0.341072
A30: 28.Poor communication between client, consultant and contractor | B30: -0.5035 | C30: 0.107485 | D30: -0.4815 | E30: 0.203016 | F30: 0.006733 | G30: -0.21333 | I30: 0.583679 | J30: 0.416321
A31: 29.Insufficient coordination between local authority who is responsible about road projects and service authorities | B31: -0.49226 | C31: 0.122693 | D31: -0.54894 | E31: 0.091049 | F31: 0.189929 | G31: 0.127536 | I31: 0.619336 | J31: 0.380664
A32: 30.Delays in decisions making by the approval authorities | B32: -0.15404 | C32: 0.092718 | D32: -0.63904 | E32: 0.119018 | F32: 0.152705 | G32: 0.005942 | I32: 0.478214 | J32: 0.521786
A33: 31.Change schedule | B33: -0.01354 | C33: 0.093817 | D33: -0.25069 | E33: 0.351373 | F33: 0.060229 | G33: -0.54597 | I33: 0.497003 | J33: 0.502997
A34: 32.Stoppages because of work being rejected by consultant | B34: -0.19733 | C34: 0.268977 | D34: -0.03195 | E34: 0.052178 | F34: -0.35782 | G34: -0.59162 | I34: 0.593078 | J34: 0.406922
A35: 33.Lowest bid price | B35: -0.15488 | C35: -0.23036 | D35: -0.15657 | E35: 0.32805 | F35: -0.46771 | G35: -0.15181 | I35: 0.450989 | J35: 0.549011
... A48: Relevant working experience | B48: -0.06545 | C48: -0.19444 | D48: -0.06086 | E48: -0.17684 | F48: 0.429176 | G48: -0.09046 | I48: 0.269441 | J48: 0.730559
B49: 7.872626 | C49: 3.535375 | D49: 4.244592 | E49: 3.37707 | F49: 3.261012 | G49: 4.267069 | I49: 26.55774 | J49: 18.44226

Sheet Factor Scores
A1: Factor Scores Matrix - Regression Method
B3: 1 | C3: 2 | D3: 3 | E3: 4 | F3: 5 | G3: 6 | K3: 1.Delay in delivering material to construction site | L3: 2.Monopoly of material by some suppliers | M3: 3.Prices fluctuation | N3: 4.Types of material availability at local market | O3: 5.Lack of consultant’s knowledge of available materials | P3: 6.Low productivity | Q3: 7.Poor work execution | R3: 8.Shortage of laborers | S3: 9.Mistakes happens during construction phase | T3: 10.Unavailability of equipment | U3: 11.Lack of engineering experience | V3: 12.Construction cost underestimation | W3: 13.Poor site management | X3: 14.Delayed payment for completed work | Y3: 15.Cash flow problem during construction | Z3: 16.High rate of interest | AA3: 17.Contractor’s financial difficulties | AB3: 19.Change design | AC3: 20.Errors and omission in design | AD3: 21.Incomplete design drawings and specifications at tendering stage | AE3: 22.Delay in preparation and approval of drawing | AF3: 23.Inaccurate quantity take-off | AG3: 24.Long period from planning of project to construction | AH3: 25.Delays in issuing information to the contractor during construction stage | AI3: 26.No practical use of earned value management system | AJ3: 27.Lack of cost planning/monitoring during pre and post contract stage | AK3: 28.Poor communication between client, consultant and contractor | AL3: 29.Insufficient coordination between local authority who is responsible about road projects and service authorities | AM3: 30.Delays in decisions making by the approval authorities | AN3: 31.Change schedule | AO3: 32.Stoppages because of work being rejected by consultant | AP3: 33.Lowest bid price | AQ3: 34.Insufficient time for preparation of contract documents | AR3: 35.Discrepancies in contract documents | AS3: 36.Underestimation of time for completion of project | AT3: 37.Extension of time with cost claims | AU3: 38.Scope and specification changes | AV3: 39.Changes in client requirements | AW3: 40.Frequency of variation orders and additional works | AX3: 41.Rework due to error in execution | AY3: 42.Weather conditions | AZ3: 43.Accidents during construction | BA3: 44.Delay in getting NOCs from different government authorities | BB3: Location of organization | BC3: Relevant working experience
A4: 1.Delay in delivering material to construction site | B4: -0.00468 | C4: -0.09871 | D4: -0.03821 | E4: -0.01581 | F4: -0.18881 | G4: -0.00845 | J4: 1 | K4: -0.00468 | L4: 0.023745 | M4: -0.06411 | N4: -0.02679 | O4: -0.00863 | P4: -0.16823 | Q4: -0.13448 | R4: -0.09773 | S4: -0.14075 | T4: -0.06221 | U4: -0.13852 | V4: -0.12907 | W4: -0.14252 | X4: 0.065418 | Y4: 0.062854 | Z4: 0.040252 | AA4: 0.049723 | AB4: -0.00588 | AC4: 0.036862 | AD4: 0.053254 | AE4: 0.048398 | AF4: 0.021732 | AG4: -0.01595 | AH4: -0.03746 | AI4: -0.02514 | AJ4: -0.0603 | AK4: -0.0675 | AL4: -0.12552 | AM4: -0.02882 | AN4: 0.071876 | AO4: 0.063397 | AP4: 0.056467 | AQ4: 0.010944 | AR4: -0.04583 | AS4: -0.08067 | AT4: 0.063059 | AU4: 0.030324 | AV4: -0.01064 | AW4: 0.034458 | AX4: -0.03006 | AY4: 0.040364 | AZ4: 0.044352 | BA4: 0.015437 | BB4: 0.028809 | BC4: -0.06453
A5: 2.Monopoly of material by some suppliers | B5: 0.023745 | C5: 0.020749 | D5: -0.03856 | E5: -0.0779 | F5: -0.26544 | G5: 0.045807 | J5: 2 | K5: -0.09871 | L5: 0.020749 | M5: 0.14917 | N5: -0.00563 | O5: 0.069422 | P5: -0.02398 | Q5: 0.005108 | R5: -0.09972 | S5: 0.020651 | T5: -0.08085 | U5: 0.009837 | V5: -0.02736 | W5: 0.040065 | X5: -0.02659 | Y5: 0.056356 | Z5: 0.002904 | AA5: 0.054025 | AB5: 0.179101 | AC5: 0.184433 | AD5: 0.191003 | AE5: 0.081785 | AF5: 0.178059 | AG5: 0.178932 | AH5: 0.114439 | AI5: 0.042378 | AJ5: 0.093903 | AK5: -0.00828 | AL5: 0.053097 | AM5: 0.021881 | AN5: -0.06907 | AO5: 0.010093 | AP5: -0.11826 | AQ5: -0.10453 | AR5: -0.07597 | AS5: -0.03226 | AT5: -0.06554 | AU5: -0.02467 | AV5: 0.003085 | AW5: -0.05508 | AX5: 0.010301 | AY5: -0.03591 | AZ5: -0.05623 | BA5: -0.08939 | BB5: 0.235401 | BC5: -0.09295
A6: 3.Prices fluctuation | B6: -0.06411 | C6: 0.14917 | D6: 0.064021 | E6: 0.03637 | F6: -0.14332 | G6: 0.184531 | J6: 3 | K6: -0.03821 | L6: -0.03856 | M6: 0.064021 | N6: -0.01163 | O6: 0.050087 | P6: 0.017946 | Q6: -0.01329 | R6: -0.00521 | S6: 0.093915 | T6: -0.04629 | U6: -0.01093 | V6: 0.09481 | W6: 0.009762 | X6: -0.21892 | Y6: -0.19584 | Z6: -0.00647 | AA6: -0.17981 | AB6: 0.060594 | AC6: 0.022269 | AD6: 0.000265 | AE6: -0.02155 | AF6: 0.040568 | AG6: -0.06218 | AH6: -0.09328 | AI6: 0.019621 | AJ6: -0.07112 | AK6: -0.10393 | AL6: -0.16769 | AM6: -0.19245 | AN6: -0.00198 | AO6: 0.060853 | AP6: -0.00496 | AQ6: 0.023999 | AR6: 0.02036 | AS6: 0.030304 | AT6: -0.12381 | AU6: 0.048753 | AV6: 0.003335 | AW6: 0.037958 | AX6: 0.081476 | AY6: 0.000322 | AZ6: 0.035487 | BA6: -0.1918 | BB6: 0.028304 | BC6: -0.02913
A7: 4.Types of material availability at local market | B7: -0.02679 | C7: -0.00563 | D7: -0.01163 | E7: -0.02492 | F7: -0.18474 | G7: 0.039679 | J7: 4 | K7: -0.01581 | L7: -0.0779 | M7: 0.03637 | N7: -0.02492 | O7: 0.049459 | P7: -0.02887 | Q7: -0.0173 | R7: 0.019202 | S7: 0.012913 | T7: 0.027063 | U7: -0.07945 | V7: 0.066134 | W7: -0.00353 | X7: 0.039047 | Y7: -0.00876 | Z7: -0.00552 | AA7: -0.06934 | AB7: 0.066809 | AC7: -0.01869 | AD7: 0.112331 | AE7: 0.126417 | AF7: -0.03925 | AG7: -0.0634 | AH7: -0.09452 | AI7: 0.062128 | AJ7: -0.024 | AK7: 0.002051 | AL7: -0.0398 | AM7: -0.01984 | AN7: 0.089663 | AO7: -0.00919 | AP7: 0.117928 | AQ7: 0.024319 | AR7: -0.03263 | AS7: -0.11364 | AT7: 0.001859 | AU7: 0.278431 | AV7: 0.262575 | AW7: 0.266658 | AX7: 0.005112 | AY7: -0.09965 | AZ7: -0.05171 | BA7: -0.06065 | BB7: -0.09094 | BC7: -0.08218
A8: 5.Lack of consultant’s knowledge of available materials | B8: -0.00863 | C8: 0.069422 | D8: 0.050087 | E8: 0.049459 | F8: -0.11575 | G8: -0.00544 | J8: 5 | K8: -0.18881 | L8: -0.26544 | M8: -0.14332 | N8: -0.18474 | O8: -0.11575 | P8: 0.057786 | Q8: -0.00198 | R8: -0.00876 | S8: 0.043777 | T8: -0.01214 | U8: 0.03158 | V8: 0.0751 | W8: 0.064758 | X8: -0.0525 | Y8: -0.04628 | Z8: 0.034056 | AA8: -0.00496 | AB8: -0.06591 | AC8: -0.03695 | AD8: -0.03143 | AE8: 0.024238 | AF8: 0.05959 | AG8: 0.041569 | AH8: 0.05013 | AI8: 0.098606 | AJ8: 0.058898 | AK8: 0.0671 | AL8: 0.130479 | AM8: 0.080898 | AN8: 0.037658 | AO8: -0.10514 | AP8: -0.16914 | AQ8: 0.048623 | AR8: 0.113018 | AS8: 0.017676 | AT8: -0.112 | AU8: -0.01635 | AV8: -0.04646 | AW8: -0.01387 | AX8: 0.013495 | AY8: -0.04641 | AZ8: -0.14435 | BA8: -0.05547 | BB8: -0.12902 | BC8: 0.194438
A9: 6.Low productivity | B9: -0.16823 | C9: -0.02398 | D9: 0.017946 | E9: -0.02887 | F9: 0.057786 | G9: 0.062266 | J9: 6 | K9: -0.00845 | L9: 0.045807 | M9: 0.184531 | N9: 0.039679 | O9: -0.00544 | P9: 0.062266 | Q9: 0.082024 | R9: -0.00472 | S9: 0.015459 | T9: -0.01183 | U9: 0.038581 | V9: -0.0218 | W9: 0.074225 | X9: 0.053008 | Y9: 0.037885 | Z9: -0.17707 | AA9: 0.002315 | AB9: 0.050241 | AC9: -0.04268 | AD9: 0.031938 | AE9: -0.02108 | AF9: -0.08227 | AG9: 0.089412 | AH9: 0.007489 | AI9: -0.07602 | AJ9: 0.029054 | AK9: 0.024513 | AL9: 0.17405 | AM9: 0.09074 | AN9: -0.19583 | AO9: -0.18149 | AP9: -0.0476 | AQ9: -0.22876 | AR9: -0.19007 | AS9: -0.07935 | AT9: -0.03478 | AU9: 0.008333 | AV9: 0.121224 | AW9: -0.01313 | AX9: -0.10506 | AY9: -0.21918 | AZ9: -0.1575 | BA9: -0.0064 | BB9: 0.115213 | BC9: -0.08164
A10: 7.Poor work execution | B10: -0.13448 | C10: 0.005108 | D10: -0.01329 | E10: -0.0173 | F10: -0.00198 | G10: 0.082024
A11: 8.Shortage of laborers | B11: -0.09773 | C11: -0.09972 | D11: -0.00521 | E11: 0.019202 | F11: -0.00876 | G11: -0.00472
A12: 9.Mistakes happens during construction phase | B12: -0.14075 | C12: 0.020651 | D12: 0.093915 | E12: 0.012913 | F12: 0.043777 | G12: 0.015459
A13: 10.Unavailability of equipment | B13: -0.06221 | C13: -0.08085 | D13: -0.04629 | E13: 0.027063 | F13: -0.01214 | G13: -0.01183
A14: 11.Lack of engineering experience | B14: -0.13852 | C14: 0.009837 | D14: -0.01093 | E14: -0.07945 | F14: 0.03158 | G14: 0.038581
A15: 12.Construction cost underestimation | B15: -0.12907 | C15: -0.02736 | D15: 0.09481 | E15: 0.066134 | F15: 0.0751 | G15: -0.0218
A16: 13.Poor site management | B16: -0.14252 | C16: 0.040065 | D16: 0.009762 | E16: -0.00353 | F16: 0.064758 | G16: 0.074225
A17: 14.Delayed payment for completed work | B17: 0.065418 | C17: -0.02659 | D17: -0.21892 | E17: 0.039047 | F17: -0.0525 | G17: 0.053008
A18: 15.Cash flow problem during construction | B18: 0.062854 | C18: 0.056356 | D18: -0.19584 | E18: -0.00876 | F18: -0.04628 | G18: 0.037885
A19: 16.High rate of interest | B19: 0.040252 | C19: 0.002904 | D19: -0.00647 | E19: -0.00552 | F19: 0.034056 | G19: -0.17707
A20: 17.Contractor’s financial difficulties | B20: 0.049723 | C20: 0.054025 | D20: -0.17981 | E20: -0.06934 | F20: -0.00496 | G20: 0.002315
A21: 19.Change design | B21: -0.00588 | C21: 0.179101 | D21: 0.060594 | E21: 0.066809 | F21: -0.06591 | G21: 0.050241
... A48: Relevant working experience | B48: -0.06453 | C48: -0.09295 | D48: -0.02913 | E48: -0.08218 | F48: 0.194438 | G48: -0.08164

Sheet Factor 1
A1: Factor 1: Construction execution / site management problems | B1: ='3rd Iteration Dataset'!B1 -> 1.Delay in delivering material to construction site | C1: ='3rd Iteration Dataset'!C1 -> 2.Monopoly of material by some suppliers | D1: ='3rd Iteration Dataset'!D1 -> 3.Prices fluctuation | E1: ='3rd Iteration Dataset'!E1 -> 4.Types of material availability at local market | F1: ='3rd Iteration Dataset'!F1 -> 5.Lack of consultant’s knowledge of available materials | G1: ='3rd Iteration Dataset'!G1 -> 6.Low productivity | H1: ='3rd Iteration Dataset'!H1 -> 7.Poor work execution | I1: ='3rd Iteration Dataset'!I1 -> 8.Shortage of laborers | ... AT1: ='3rd Iteration Dataset'!AT1 -> Relevant working experience
A2: =SUM(B2:AS2) -> 4.46 | B2: -0.1 | C2: 0.02 | D2: 0.15 | E2: -0.01 | F2: 0.07 | G2: -0.02 | H2: 0.01 | I2: -0.1 | J2: 0.02 | K2: -0.08 | L2: 0.01 | M2: -0.03 | N2: 0.04 | O2: -0.03 | P2: 0.06 | Q2: 0 | R2: 0.05 | S2: 0.54 | T2: 0.55 | U2: 0.57 | V2: 0.33 | W2: 0.71 | X2: 0.54 | Y2: 0.34 | Z2: 0.08 | AA2: 0.09 | AB2: -0.02 | AC2: 0.21 | AD2: -0.12 | AE2: 0.07 | AF2: 0.06 | AG2: 0.11 | AH2: 0.02 | AI2: -0.09 | AJ2: -0.16 | AK2: 0.13 | AL2: 0.09 | AM2: -0.03 | AN2: 0.1 | AO2: -0.03 | AP2: 0.08 | AQ2: 0.09 | AR2: 0.05 | AS2: 0.09 | AT2: -0.32
A3: =SUM(B3:AS3) -> 6.83 | B3: -0.2 | C3: 0.1 | D3: 0.45 | E3: -0.01 | F3: 0.21 | G3: -0.05 | H3: 0.01 | I3: -0.2 | J3: 0.06 | K3: -0.16 | L3: 0.02 | M3: -0.05 | N3: 0.08 | O3: -0.05 | P3: 0.11 | Q3: 0 | R3: 0.22 | S3: 0.9 | T3: 0.92 | U3: 0.76 | V3: 0.33 | W3: 0.71 | X3: 0.89 | Y3: 0.34 | Z3: 0.13 | AA3: 0.28 | AB3: -0.03 | AC3: 0.21 | AD3: -0.09 | AE3: 0.29 | AF3: 0.25 | AG3: 0.28 | AH3: 0.03 | AI3: -0.18 | AJ3: -0.32 | AK3: 0.25 | AL3: 0.09 | AM3: -0.03 | AN3: 0.14 | AO3: -0.09 | AP3: 0.04 | AQ3: 0.04 | AR3: 0.06 | AS3: 0.09 | AT3: -0.19
A4: =SUM(B4:AS4) -> 3.66 | B4: -0.1 | C4: 0.04 | D4: 0.15 | E4: -0.01 | F4: 0.14 | G4: -0.05 | H4: 0.01 | I4: -0.2 | J4: 0.02 | K4: -0.08 | L4: 0.02 | M4: -0.03 | N4: 0.12 | O4: -0.08 | P4: 0.17 | Q4: 0.01 | R4: 0.11 | S4: 0.36 | T4: 0.37 | U4: 0.38 | V4: 0.16 | W4: 0.53 | X4: 0.36 | Y4: 0.34 | Z4: 0.04 | AA4: 0.19 | AB4: -0.01 | AC4: 0.16 | AD4: -0.12 | AE4: 0.22 | AF4: 0.06 | AG4: 0.11 | AH4: 0.02 | AI4: -0.09 | AJ4: -0.16 | AK4: 0.25 | AL4: 0.06 | AM4: -0.02 | AN4: 0.07 | AO4: -0.06 | AP4: 0.04 | AQ4: 0.04 | AR4: 0.06 | AS4: 0.06 | AT4: -0.26
A5: =SUM(B5:AS5) -> 4.92 | B5: -0.2 | C5: 0.04 | D5: 0.45 | E5: -0.02 | F5: 0.14 | G5: -0.05 | H5: 0.02 | I5: -0.4 | J5: 0.08 | K5: -0.32 | L5: 0.02 | M5: -0.14 | N5: 0.08 | O5: -0.05 | P5: 0.06 | Q5: 0 | R5: 0.05 | S5: 0.72 | T5: 0.74 | U5: 0.76 | V5: 0.33 | W5: 0.71 | X5: 0.54 | Y5: 0.23 | Z5: 0.08 | AA5: 0.19 | AB5: -0.02 | AC5: 0.16 | AD5: -0.09 | AE5: 0.14 | AF5: 0.13 | AG5: 0.11 | AH5: 0.03 | AI5: -0.09 | AJ5: -0.32 | AK5: 0.25 | AL5: 0.12 | AM5: -0.04 | AN5: 0.14 | AO5: -0.09 | AP5: 0.16 | AQ5: 0.13 | AR5: 0.05 | AS5: 0.09 | AT5: -0.26
A6: =SUM(B6:AS6) -> 3.86 | B6: -0.1 | C6: 0.04 | D6: 0.15 | E6: -0.01 | F6: 0.14 | G6: -0.05 | H6: 0.01 | I6: -0.2 | J6: 0.02 | K6: -0.08 | L6: 0.02 | M6: -0.03 | N6: 0.08 | O6: -0.11 | P6: 0.23 | Q6: 0.01 | R6: 0.11 | S6: 0.36 | T6: 0.37 | U6: 0.38 | V6: 0.16 | W6: 0.53 | X6: 0.36 | Y6: 0.46 | Z6: 0.13 | AA6: 0.19 | AB6: -0.01 | AC6: 0.16 | AD6: -0.12 | AE6: 0.22 | AF6: 0.06 | AG6: 0.11 | AH6: 0.02 | AI6: -0.09 | AJ6: -0.16 | AK6: 0.25 | AL6: 0.06 | AM6: -0.02 | AN6: 0.07 | AO6: -0.06 | AP6: 0.04 | AQ6: 0.04 | AR6: 0.06 | AS6: 0.06 | AT6: -0.26
A7: =SUM(B7:AS7) -> 5.46 | B7: -0.1 | C7: 0.02 | D7: 0.15 | E7: -0.01 | F7: 0.07 | G7: -0.05 | H7: 0.01 | I7: -0.2 | J7: 0.02 | K7: -0.08 | L7: 0.01 | M7: -0.05 | N7: 0.04 | O7: -0.11 | P7: 0.23 | Q7: 0.01 | R7: 0.22 | S7: 0.72 | T7: 0.74 | U7: 0.76 | V7: 0.33 | W7: 0.71 | X7: 0.72 | Y7: 0.23 | Z7: 0.08 | AA7: 0.19 | AB7: -0.01 | AC7: 0.05 | AD7: -0.09 | AE7: 0.22 | AF7: 0.25 | AG7: 0.11 | AH7: 0.02 | AI7: -0.09 | AJ7: -0.16 | AK7: 0.13 | AL7: 0.09 | AM7: -0.02 | AN7: 0.1 | AO7: -0.09 | AP7: 0.08 | AQ7: 0.09 | AR7: 0.03 | AS7: 0.09 | AT7: -0.32
A8: =SUM(B8:AS8) -> 5.79 | B8: -0.1 | C8: 0.02 | D8: 0.15 | E8: -0.01 | F8: 0.07 | G8: -0.02 | H8: 0.01 | I8: -0.1 | J8: 0.02 | K8: -0.08 | L8: 0.01 | M8: -0.03 | N8: 0.04 | O8: -0.11 | P8: 0.23 | Q8: 0.01 | R8: 0.22 | S8: 0.72 | T8: 0.74 | U8: 0.76 | V8: 0.33 | W8: 0.71 | X8: 0.72 | Y8: 0.23 | Z8: 0.08 | AA8: 0.19 | AB8: -0.01 | AC8: 0.11 | AD8: -0.12 | AE8: 0.22 | AF8: 0.25 | AG8: 0.11 | AH8: 0.02 | AI8: -0.09 | AJ8: -0.16 | AK8: 0.25 | AL8: 0.12 | AM8: -0.03 | AN8: 0.14 | AO8: -0.12 | AP8: 0.08 | AQ8: 0.09 | AR8: 0.03 | AS8: 0.09 | AT8: -0.32
A9: =SUM(B9:AS9) -> 5.58 | B9: -0.1 | C9: 0.02 | D9: 0.15 | E9: -0.01 | F9: 0.07 | G9: -0.02 | H9: 0.01 | I9: -0.1 | J9: 0.02 | K9: -0.08 | L9: 0.01 | M9: -0.03 | N9: 0.04 | O9: -0.08 | P9: 0.17 | Q9: 0.01 | R9: 0.22 | S9: 0.72 | T9: 0.74 | U9: 0.76 | V9: 0.33 | W9: 0.71 | X9: 0.72 | Y9: 0.23 | Z9: 0.08 | AA9: 0.19 | AB9: -0.01 | AC9: 0.05 | AD9: -0.09 | AE9: 0.22 | AF9: 0.25 | AG9: 0.11 | AH9: 0.02 | AI9: -0.09 | AJ9: -0.16 | AK9: 0.13 | AL9: 0.09 | AM9: -0.02 | AN9: 0.1 | AO9: -0.09 | AP9: 0.08 | AQ9: 0.09 | AR9: 0.03 | AS9: 0.09 | AT9: -0.32
A10: =SUM(B10:AS10) -> 5.67 | B10: -0.1 | C10: 0.02 | D10: 0.15 | E10: -0.01 | F10: 0.07 | G10: -0.02 | H10: 0.01 | I10: -0.1 | J10: 0.02 | K10: -0.08 | L10: 0.01 | M10: -0.03 | N10: 0.04 | O10: -0.11 | P10: 0.23 | Q10: 0.01 | R10: 0.22 | S10: 0.72 | T10: 0.74 | U10: 0.76 | V10: 0.33 | W10: 0.71 | X10: 0.72 | Y10: 0.23 | Z10: 0.08 | AA10: 0.19 | AB10: -0.01 | AC10: 0.11 | AD10: -0.12 | AE10: 0.22 | AF10: 0.25 | AG10: 0.11 | AH10: 0.02 | AI10: -0.09 | AJ10: -0.16 | AK10: 0.13 | AL10: 0.12 | AM10: -0.03 | AN10: 0.14 | AO10: -0.12 | AP10: 0.08 | AQ10: 0.09 | AR10: 0.03 | AS10: 0.09 | AT10: -0.32
A11: =SUM(B11:AS11) -> 5.61 | B11: -0.1 | C11: 0.02 | D11: 0.15 | E11: -0.01 | F11: 0.07 | G11: -0.02 | H11: 0.01 | I11: -0.1 | J11: 0.02 | K11: -0.08 | L11: 0.01 | M11: -0.03 | N11: 0.04 | O11: -0.11 | P11: 0.23 | Q11: 0.01 | R11: 0.22 | S11: 0.72 | T11: 0.74 | U11: 0.76 | V11: 0.33 | W11: 0.71 | X11: 0.72 | Y11: 0.23 | Z11: 0.08 | AA11: 0.19 | AB11: -0.01 | AC11: 0.05 | AD11: -0.09 | AE11: 0.22 | AF11: 0.25 | AG11: 0.11 | AH11: 0.02 | AI11: -0.09 | AJ11: -0.16 | AK11: 0.13 | AL11: 0.09 | AM11: -0.02 | AN11: 0.1 | AO11: -0.09 | AP11: 0.08 | AQ11: 0.09 | AR11: 0.03 | AS11: 0.09 | AT11: -0.32
A12: =SUM(B12:AS12) -> 4.16 | B12: -0.2 | C12: 0.08 | D12: 0.6 | E12: -0.01 | F12: 0.07 | G12: -0.12 | H12: 0.01 | I12: -0.4 | J12: 0.1 | K12: -0.24 | L12: 0.02 | M12: -0.14 | N12: 0.08 | O12: -0.03 | P12: 0.06 | Q12: 0 | R12: 0.05 | S12: 0.9 | T12: 0.37 | U12: 0.57 | V12: 0.33 | W12: 0.53 | X12: 0.36 | Y12: 0.23 | Z12: 0.04 | AA12: 0.19 | AB12: -0.01 | AC12: 0.27 | AD12: -0.03 | AE12: 0.07 | AF12: 0.06 | AG12: 0.06 | AH12: 0.01 | AI12: -0.05 | AJ12: -0.24 | AK12: 0.19 | AL12: 0.12 | AM12: -0.04 | AN12: 0.14 | AO12: -0.03 | AP12: 0.04 | AQ12: 0.04 | AR12: 0.02 | AS12: 0.09 | AT12: -0.26
A13: =SUM(B13:AS13) -> 5.92 | B13: -0.2 | C13: 0.02 | D13: 0.45 | E13: -0.02 | F13: 0.28 | G13: -0.07 | H13: 0.02 | I13: -0.4 | J13: 0.06 | K13: -0.32 | L13: 0.05 | M13: -0.11 | N13: 0.12 | O13: -0.08 | P13: 0.23 | Q13: 0.01 | R13: 0.22 | S13: 0.72 | T13: 0.74 | U13: 0.96 | V13: 0.25 | W13: 0.71 | X13: 0.54 | Y13: 0.34 | Z13: 0.13 | AA13: 0.28 | AB13: -0.03 | AC13: 0.21 | AD13: -0.12 | AE13: 0.22 | AF13: 0.25 | AG13: 0.23 | AH13: 0.03 | AI13: -0.14 | AJ13: -0.32 | AK13: 0.25 | AL13: 0.12 | AM13: -0.04 | AN13: 0.14 | AO13: -0.12 | AP13: 0.08 | AQ13: 0.09 | AR13: 0.05 | AS13: 0.09 | AT13: -0.32
... A144: =SUM(B144:AS144) -> 3.8 | B144: -0.2 | C144: 0.04 | D144: 0.45 | E144: -0.01 | F144: 0.07 | G144: -0.05 | H144: 0.01 | I144: -0.3 | J144: 0.04 | K144: -0.24 | L144: 0.02 | M144: -0.08 | N144: 0.08 | O144: -0.11 | P144: 0.23 | Q144: 0.01 | R144: 0.16 | S144: 0.36 | T144: 0.37 | U144: 0.38 | V144: 0.16 | W144: 0.36 | X144: 0.72 | Y144: 0.23 | Z144: 0.08 | AA144: 0.19 | AB144: -0.02 | AC144: 0.16 | AD144: -0.09 | AE144: 0.22 | AF144: 0.13 | AG144: 0.17 | AH144: 0.04 | AI144: -0.09 | AJ144: -0.32 | AK144: 0.19 | AL144: 0.12 | AM144: -0.04 | AN144: 0.1 | AO144: -0.06 | AP144: 0.08 | AQ144: 0.09 | AR144: 0.06 | AS144: 0.09 | AT144: -0.32

Sheet Factor 2
A1: Factor 2: Design and planning deficiencies | B1: ='3rd Iteration Dataset'!B1 -> 1.Delay in delivering material to construction site | C1: ='3rd Iteration Dataset'!C1 -> 2.Monopoly of material by some suppliers | D1: ='3rd Iteration Dataset'!D1 -> 3.Prices fluctuation | E1: ='3rd Iteration Dataset'!E1 -> 4.Types of material availability at local market | F1: ='3rd Iteration Dataset'!F1 -> 5.Lack of consultant’s knowledge of available materials | G1: ='3rd Iteration Dataset'!G1 -> 6.Low productivity | H1: ='3rd Iteration Dataset'!H1 -> 7.Poor work execution | I1: ='3rd Iteration Dataset'!I1 -> 8.Shortage of laborers | ... AT1: ='3rd Iteration Dataset'!AT1 -> Relevant working experience
A2: -2.68 | B2: -0.04 | C2: -0.04 | D2: 0.06 | E2: -0.01 | F2: 0.05 | G2: 0.02 | H2: -0.01 | I2: -0.01 | J2: 0.09 | K2: -0.05 | L2: -0.01 | M2: 0.09 | N2: 0.01 | O2: -0.22 | P2: -0.2 | Q2: -0.01 | R2: -0.18 | S2: 0.18 | T2: 0.07 | U2: 0 | V2: -0.09 | W2: 0.16 | X2: -0.19 | Y2: -0.28 | Z2: 0.04 | AA2: -0.07 | AB2: -0.21 | AC2: -0.67 | AD2: 0.09 | AE2: -0.07 | AF2: 0.01 | AG2: -0.24 | AH2: -0.21 | AI2: -0.15 | AJ2: -0.06 | AK2: -0.13 | AL2: -0.07 | AM2: 0.01 | AN2: -0.17 | AO2: 0.01 | AP2: -0.07 | AQ2: -0.11 | AR2: -0.27 | AS2: 0.71 | AT2: -0.46
A3: -4.52 | B3: -0.08 | C3: -0.19 | D3: 0.19 | E3: -0.02 | F3: 0.15 | G3: 0.04 | H3: -0.03 | I3: -0.01 | J3: 0.28 | K3: -0.09 | L3: -0.02 | M3: 0.19 | N3: 0.02 | O3: -0.44 | P3: -0.39 | Q3: -0.01 | R3: -0.72 | S3: 0.3 | T3: 0.11 | U3: 0 | V3: -0.09 | W3: 0.16 | X3: -0.31 | Y3: -0.28 | Z3: 0.06 | AA3: -0.21 | AB3: -0.42 | AC3: -0.67 | AD3: 0.07 | AE3: -0.28 | AF3: 0.04 | AG3: -0.59 | AH3: -0.31 | AI3: -0.3 | AJ3: -0.13 | AK3: -0.26 | AL3: -0.07 | AM3: 0.01 | AN3: -0.22 | AO3: 0.03 | AP3: -0.04 | AQ3: -0.06 | AR3: -0.36 | AS3: 0.71 | AT3: -0.28
A4: -3.82 | B4: -0.04 | C4: -0.08 | D4: 0.06 | E4: -0.01 | F4: 0.1 | G4: 0.04 | H4: -0.01 | I4: -0.01 | J4: 0.09 | K4: -0.05 | L4: -0.02 | M4: 0.09 | N4: 0.03 | O4: -0.66 | P4: -0.59 | Q4: -0.01 | R4: -0.36 | S4: 0.12 | T4: 0.04 | U4: 0 | V4: -0.04 | W4: 0.12 | X4: -0.12 | Y4: -0.28 | Z4: 0.02 | AA4: -0.14 | AB4: -0.1 | AC4: -0.5 | AD4: 0.09 | AE4: -0.21 | AF4: 0.01 | AG4: -0.24 | AH4: -0.21 | AI4: -0.15 | AJ4: -0.06 | AK4: -0.26 | AL4: -0.05 | AM4: 0.01 | AN4: -0.11 | AO4: 0.02 | AP4: -0.04 | AQ4: -0.06 | AR4: -0.36 | AS4: 0.47 | AT4: -0.37
A5: -2.52 | B5: -0.08 | C5: -0.08 | D5: 0.19 | E5: -0.03 | F5: 0.1 | G5: 0.04 | H5: -0.04 | I5: -0.02 | J5: 0.38 | K5: -0.19 | L5: -0.02 | M5: 0.47 | N5: 0.02 | O5: -0.44 | P5: -0.2 | Q5: -0.01 | R5: -0.18 | S5: 0.24 | T5: 0.09 | U5: 0 | V5: -0.09 | W5: 0.16 | X5: -0.19 | Y5: -0.19 | Z5: 0.04 | AA5: -0.14 | AB5: -0.21 | AC5: -0.5 | AD5: 0.07 | AE5: -0.14 | AF5: 0.02 | AG5: -0.24 | AH5: -0.31 | AI5: -0.15 | AJ5: -0.13 | AK5: -0.26 | AL5: -0.1 | AM5: 0.01 | AN5: -0.22 | AO5: 0.03 | AP5: -0.14 | AQ5: -0.17 | AR5: -0.27 | AS5: 0.71 | AT5: -0.37
A6: -4.3 | B6: -0.04 | C6: -0.08 | D6: 0.06 | E6: -0.01 | F6: 0.1 | G6: 0.04 | H6: -0.01 | I6: -0.01 | J6: 0.09 | K6: -0.05 | L6: -0.02 | M6: 0.09 | N6: 0.02 | O6: -0.88 | P6: -0.78 | Q6: -0.01 | R6: -0.36 | S6: 0.12 | T6: 0.04 | U6: 0 | V6: -0.04 | W6: 0.12 | X6: -0.12 | Y6: -0.37 | Z6: 0.06 | AA6: -0.14 | AB6: -0.1 | AC6: -0.5 | AD6: 0.09 | AE6: -0.21 | AF6: 0.01 | AG6: -0.24 | AH6: -0.21 | AI6: -0.15 | AJ6: -0.06 | AK6: -0.26 | AL6: -0.05 | AM6: 0.01 | AN6: -0.11 | AO6: 0.02 | AP6: -0.04 | AQ6: -0.06 | AR6: -0.36 | AS6: 0.47 | AT6: -0.37
A7: -3.76 | B7: -0.04 | C7: -0.04 | D7: 0.06 | E7: -0.01 | F7: 0.05 | G7: 0.04 | H7: -0.03 | I7: -0.01 | J7: 0.09 | K7: -0.05 | L7: -0.01 | M7: 0.19 | N7: 0.01 | O7: -0.88 | P7: -0.78 | Q7: -0.03 | R7: -0.72 | S7: 0.24 | T7: 0.09 | U7: 0 | V7: -0.09 | W7: 0.16 | X7: -0.25 | Y7: -0.19 | Z7: 0.04 | AA7: -0.14 | AB7: -0.1 | AC7: -0.17 | AD7: 0.07 | AE7: -0.21 | AF7: 0.04 | AG7: -0.24 | AH7: -0.21 | AI7: -0.15 | AJ7: -0.06 | AK7: -0.13 | AL7: -0.07 | AM7: 0.01 | AN7: -0.17 | AO7: 0.03 | AP7: -0.07 | AQ7: -0.11 | AR7: -0.18 | AS7: 0.71 | AT7: -0.46
A8: -4.2 | B8: -0.04 | C8: -0.04 | D8: 0.06 | E8: -0.01 | F8: 0.05 | G8: 0.02 | H8: -0.01 | I8: -0.01 | J8: 0.09 | K8: -0.05 | L8: -0.01 | M8: 0.09 | N8: 0.01 | O8: -0.88 | P8: -0.78 | Q8: -0.03 | R8: -0.72 | S8: 0.24 | T8: 0.09 | U8: 0 | V8: -0.09 | W8: 0.16 | X8: -0.25 | Y8: -0.19 | Z8: 0.04 | AA8: -0.14 | AB8: -0.1 | AC8: -0.34 | AD8: 0.09 | AE8: -0.21 | AF8: 0.04 | AG8: -0.24 | AH8: -0.21 | AI8: -0.15 | AJ8: -0.06 | AK8: -0.26 | AL8: -0.1 | AM8: 0.01 | AN8: -0.22 | AO8: 0.04 | AP8: -0.07 | AQ8: -0.11 | AR8: -0.18 | AS8: 0.71 | AT8: -0.46
A9: -3.44 | B9: -0.04 | C9: -0.04 | D9: 0.06 | E9: -0.01 | F9: 0.05 | G9: 0.02 | H9: -0.01 | I9: -0.01 | J9: 0.09 | K9: -0.05 | L9: -0.01 | M9: 0.09 | N9: 0.01 | O9: -0.66 | P9: -0.59 | Q9: -0.02 | R9: -0.72 | S9: 0.24 | T9: 0.09 | U9: 0 | V9: -0.09 | W9: 0.16 | X9: -0.25 | Y9: -0.19 | Z9: 0.04 | AA9: -0.14 | AB9: -0.1 | AC9: -0.17 | AD9: 0.07 | AE9: -0.21 | AF9: 0.04 | AG9: -0.24 | AH9: -0.21 | AI9: -0.15 | AJ9: -0.06 | AK9: -0.13 | AL9: -0.07 | AM9: 0.01 | AN9: -0.17 | AO9: 0.03 | AP9: -0.07 | AQ9: -0.11 | AR9: -0.18 | AS9: 0.71 | AT9: -0.46
A10: -4.07 | B10: -0.04 | C10: -0.04 | D10: 0.06 | E10: -0.01 | F10: 0.05 | G10: 0.02 | H10: -0.01 | I10: -0.01 | J10: 0.09 | K10: -0.05 | L10: -0.01 | M10: 0.09 | N10: 0.01 | O10: -0.88 | P10: -0.78 | Q10: -0.03 | R10: -0.72 | S10: 0.24 | T10: 0.09 | U10: 0 | V10: -0.09 | W10: 0.16 | X10: -0.25 | Y10: -0.19 | Z10: 0.04 | AA10: -0.14 | AB10: -0.1 | AC10: -0.34 | AD10: 0.09 | AE10: -0.21 | AF10: 0.04 | AG10: -0.24 | AH10: -0.21 | AI10: -0.15 | AJ10: -0.06 | AK10: -0.13 | AL10: -0.1 | AM10: 0.01 | AN10: -0.22 | AO10: 0.04 | AP10: -0.07 | AQ10: -0.11 | AR10: -0.18 | AS10: 0.71 | AT10: -0.46
A11: -3.86 | B11: -0.04 | C11: -0.04 | D11: 0.06 | E11: -0.01 | F11: 0.05 | G11: 0.02 | H11: -0.01 | I11: -0.01 | J11: 0.09 | K11: -0.05 | L11: -0.01 | M11: 0.09 | N11: 0.01 | O11: -0.88 | P11: -0.78 | Q11: -0.03 | R11: -0.72 | S11: 0.24 | T11: 0.09 | U11: 0 | V11: -0.09 | W11: 0.16 | X11: -0.25 | Y11: -0.19 | Z11: 0.04 | AA11: -0.14 | AB11: -0.1 | AC11: -0.17 | AD11: 0.07 | AE11: -0.21 | AF11: 0.04 | AG11: -0.24 | AH11: -0.21 | AI11: -0.15 | AJ11: -0.06 | AK11: -0.13 | AL11: -0.07 | AM11: 0.01 | AN11: -0.17 | AO11: 0.03 | AP11: -0.07 | AQ11: -0.11 | AR11: -0.18 | AS11: 0.71 | AT11: -0.46
A12: -1.44 | B12: -0.08 | C12: -0.15 | D12: 0.26 | E12: -0.01 | F12: 0.05 | G12: 0.09 | H12: -0.01 | I12: -0.02 | J12: 0.47 | K12: -0.14 | L12: -0.02 | M12: 0.47 | N12: 0.02 | O12: -0.22 | P12: -0.2 | Q12: -0.01 | R12: -0.18 | S12: 0.3 | T12: 0.04 | U12: 0 | V12: -0.09 | W12: 0.12 | X12: -0.12 | Y12: -0.19 | Z12: 0.02 | AA12: -0.14 | AB12: -0.1 | AC12: -0.84 | AD12: 0.02 | AE12: -0.07 | AF12: 0.01 | AG12: -0.12 | AH12: -0.1 | AI12: -0.08 | AJ12: -0.1 | AK12: -0.2 | AL12: -0.1 | AM12: 0.01 | AN12: -0.22 | AO12: 0.01 | AP12: -0.04 | AQ12: -0.06 | AR12: -0.09 | AS12: 0.71 | AT12: -0.37
A13: -4.74 | B13: -0.08 | C13: -0.04 | D13: 0.19 | E13: -0.05 | F13: 0.2 | G13: 0.05 | H13: -0.04 | I13: -0.02 | J13: 0.28 | K13: -0.19 | L13: -0.05 | M13: 0.38 | N13: 0.03 | O13: -0.66 | P13: -0.78 | Q13: -0.01 | R13: -0.72 | S13: 0.24 | T13: 0.09 | U13: 0 | V13: -0.06 | W13: 0.16 | X13: -0.19 | Y13: -0.28 | Z13: 0.06 | AA13: -0.21 | AB13: -0.42 | AC13: -0.67 | AD13: 0.09 | AE13: -0.21 | AF13: 0.04 | AG13: -0.47 | AH13: -0.31 | AI13: -0.23 | AJ13: -0.13 | AK13: -0.26 | AL13: -0.1 | AM13: 0.01 | AN13: -0.22 | AO13: 0.04 | AP13: -0.07 | AQ13: -0.11 | AR13: -0.27 | AS13: 0.71 | AT13: -0.46
... A144: -4.77 | B144: -0.08 | C144: -0.08 | D144: 0.19 | E144: -0.02 | F144: 0.05 | G144: 0.04 | H144: -0.03 | I144: -0.02 | J144: 0.19 | K144: -0.14 | L144: -0.02 | M144: 0.28 | N144: 0.02 | O144: -0.88 | P144: -0.78 | Q144: -0.01 | R144: -0.54 | S144: 0.12 | T144: 0.04 | U144: 0 | V144: -0.04 | W144: 0.08 | X144: -0.25 | Y144: -0.19 | Z144: 0.04 | AA144: -0.14 | AB144: -0.21 | AC144: -0.5 | AD144: 0.07 | AE144: -0.21 | AF144: 0.02 | AG144: -0.35 | AH144: -0.42 | AI144: -0.15 | AJ144: -0.13 | AK144: -0.2 | AL144: -0.1 | AM144: 0.01 | AN144: -0.17 | AO144: 0.02 | AP144: -0.07 | AQ144: -0.11 | AR144: -0.36 | AS144: 0.71 | AT144: -0.46

Sheet Factor 3
A1: Factor 3: Financial and administrative delays | B1: ='3rd Iteration Dataset'!B1 -> 1.Delay in delivering material to construction site | C1: ='3rd Iteration Dataset'!C1 -> 2.Monopoly of material by some suppliers | D1: ='3rd Iteration Dataset'!D1 -> 3.Prices fluctuation | E1: ='3rd Iteration Dataset'!E1 -> 4.Types of material availability at local market | F1: ='3rd Iteration Dataset'!F1 -> 5.Lack of consultant’s knowledge of available materials | G1: ='3rd Iteration Dataset'!G1 -> 6.Low productivity | H1: ='3rd Iteration Dataset'!H1 -> 7.Poor work execution | I1: ='3rd Iteration Dataset'!I1 -> 8.Shortage of laborers | ... AT1: ='3rd Iteration Dataset'!AT1 -> Relevant working experience | AV1: ='[1]cleaned dataset'!AU1 -> #REF!
A2: -0.81 | B2: -0.02 | C2: -0.08 | D2: 0.04 | E2: -0.02 | F2: 0.05 | G2: -0.03 | H2: -0.02 | I2: 0.02 | J2: 0.01 | K2: 0.03 | L2: -0.08 | M2: 0.07 | N2: 0 | O2: 0.04 | P2: -0.01 | Q2: -0.01 | R2: -0.07 | S2: 0.2 | T2: -0.06 | U2: 0.34 | V2: 0.51 | W2: -0.16 | X2: -0.19 | Y2: -0.28 | Z2: 0.12 | AA2: -0.02 | AB2: 0 | AC2: -0.16 | AD2: -0.77 | AE2: 0 | AF2: 0.06 | AG2: -0.01 | AH2: 0.05 | AI2: 0.04 | AJ2: 0.06 | AK2: -0.25 | AL2: 0.15 | AM2: 0.01 | AN2: 0.11 | AO2: 0.08 | AP2: 0 | AQ2: 0.07 | AR2: -0.58 | AS2: 0.08 | AT2: -0.15
A3: -0.8 | B3: -0.03 | C3: -0.39 | D3: 0.11 | E3: -0.05 | F3: 0.15 | G3: -0.06 | H3: -0.03 | I3: 0.04 | J3: 0.04 | K3: 0.05 | L3: -0.16 | M3: 0.13 | N3: -0.01 | O3: 0.08 | P3: -0.02 | Q3: -0.01 | R3: -0.28 | S3: 0.33 | T3: -0.09 | U3: 0.45 | V3: 0.51 | W3: -0.16 | X3: -0.32 | Y3: -0.28 | Z3: 0.19 | AA3: -0.07 | AB3: 0.01 | AC3: -0.16 | AD3: -0.58 | AE3: -0.01 | AF3: 0.24 | AG3: -0.02 | AH3: 0.07 | AI3: 0.08 | AJ3: 0.12 | AK3: -0.5 | AL3: 0.15 | AM3: 0.01 | AN3: 0.15 | AO3: 0.24 | AP3: 0 | AQ3: 0.04 | AR3: -0.77 | AS3: 0.08 | AT3: -0.09
A4: -1.8 | B4: -0.02 | C4: -0.16 | D4: 0.04 | E4: -0.02 | F4: 0.1 | G4: -0.06 | H4: -0.02 | I4: 0.04 | J4: 0.01 | K4: 0.03 | L4: -0.16 | M4: 0.07 | N4: -0.01 | O4: 0.12 | P4: -0.03 | Q4: -0.01 | R4: -0.14 | S4: 0.13 | T4: -0.04 | U4: 0.22 | V4: 0.25 | W4: -0.12 | X4: -0.13 | Y4: -0.28 | Z4: 0.06 | AA4: -0.05 | AB4: 0 | AC4: -0.12 | AD4: -0.77 | AE4: -0.01 | AF4: 0.06 | AG4: -0.01 | AH4: 0.05 | AI4: 0.04 | AJ4: 0.06 | AK4: -0.5 | AL4: 0.1 | AM4: 0.01 | AN4: 0.08 | AO4: 0.16 | AP4: 0 | AQ4: 0.04 | AR4: -0.77 | AS4: 0.06 | AT4: -0.12
A5: 0.18 | B5: -0.03 | C5: -0.16 | D5: 0.11 | E5: -0.07 | F5: 0.1 | G5: -0.06 | H5: -0.05 | I5: 0.08 | J5: 0.05 | K5: 0.11 | L5: -0.16 | M5: 0.33 | N5: -0.01 | O5: 0.08 | P5: -0.01 | Q5: -0.01 | R5: -0.07 | S5: 0.27 | T5: -0.07 | U5: 0.45 | V5: 0.51 | W5: -0.16 | X5: -0.19 | Y5: -0.19 | Z5: 0.12 | AA5: -0.05 | AB5: 0 | AC5: -0.12 | AD5: -0.58 | AE5: 0 | AF5: 0.12 | AG5: -0.01 | AH5: 0.07 | AI5: 0.04 | AJ5: 0.12 | AK5: -0.5 | AL5: 0.2 | AM5: 0.01 | AN5: 0.15 | AO5: 0.24 | AP5: 0 | AQ5: 0.11 | AR5: -0.58 | AS5: 0.08 | AT5: -0.12
A6: -1.73 | B6: -0.02 | C6: -0.16 | D6: 0.04 | E6: -0.02 | F6: 0.1 | G6: -0.06 | H6: -0.02 | I6: 0.04 | J6: 0.01 | K6: 0.03 | L6: -0.16 | M6: 0.07 | N6: -0.01 | O6: 0.16 | P6: -0.04 | Q6: -0.01 | R6: -0.14 | S6: 0.13 | T6: -0.04 | U6: 0.22 | V6: 0.25 | W6: -0.12 | X6: -0.13 | Y6: -0.38 | Z6: 0.19 | AA6: -0.05 | AB6: 0 | AC6: -0.12 | AD6: -0.77 | AE6: -0.01 | AF6: 0.06 | AG6: -0.01 | AH6: 0.05 | AI6: 0.04 | AJ6: 0.06 | AK6: -0.5 | AL6: 0.1 | AM6: 0.01 | AN6: 0.08 | AO6: 0.16 | AP6: 0 | AQ6: 0.04 | AR6: -0.77 | AS6: 0.06 | AT6: -0.12
A7: 0.1 | B7: -0.02 | C7: -0.08 | D7: 0.04 | E7: -0.02 | F7: 0.05 | G7: -0.06 | H7: -0.03 | I7: 0.04 | J7: 0.01 | K7: 0.03 | L7: -0.08 | M7: 0.13 | N7: 0 | O7: 0.16 | P7: -0.04 | Q7: -0.02 | R7: -0.28 | S7: 0.27 | T7: -0.07 | U7: 0.45 | V7: 0.51 | W7: -0.16 | X7: -0.25 | Y7: -0.19 | Z7: 0.12 | AA7: -0.05 | AB7: 0 | AC7: -0.04 | AD7: -0.58 | AE7: -0.01 | AF7: 0.24 | AG7: -0.01 | AH7: 0.05 | AI7: 0.04 | AJ7: 0.06 | AK7: -0.25 | AL7: 0.15 | AM7: 0.01 | AN7: 0.11 | AO7: 0.24 | AP7: 0 | AQ7: 0.07 | AR7: -0.38 | AS7: 0.08 | AT7: -0.15
A8: -0.25 | B8: -0.02 | C8: -0.08 | D8: 0.04 | E8: -0.02 | F8: 0.05 | G8: -0.03 | H8: -0.02 | I8: 0.02 | J8: 0.01 | K8: 0.03 | L8: -0.08 | M8: 0.07 | N8: 0 | O8: 0.16 | P8: -0.04 | Q8: -0.02 | R8: -0.28 | S8: 0.27 | T8: -0.07 | U8: 0.45 | V8: 0.51 | W8: -0.16 | X8: -0.25 | Y8: -0.19 | Z8: 0.12 | AA8: -0.05 | AB8: 0 | AC8: -0.08 | AD8: -0.77 | AE8: -0.01 | AF8: 0.24 | AG8: -0.01 | AH8: 0.05 | AI8: 0.04 | AJ8: 0.06 | AK8: -0.5 | AL8: 0.2 | AM8: 0.01 | AN8: 0.15 | AO8: 0.33 | AP8: 0 | AQ8: 0.07 | AR8: -0.38 | AS8: 0.08 | AT8: -0.15
A9: 0.04 | B9: -0.02 | C9: -0.08 | D9: 0.04 | E9: -0.02 | F9: 0.05 | G9: -0.03 | H9: -0.02 | I9: 0.02 | J9: 0.01 | K9: 0.03 | L9: -0.08 | M9: 0.07 | N9: 0 | O9: 0.12 | P9: -0.03 | Q9: -0.02 | R9: -0.28 | S9: 0.27 | T9: -0.07 | U9: 0.45 | V9: 0.51 | W9: -0.16 | X9: -0.25 | Y9: -0.19 | Z9: 0.12 | AA9: -0.05 | AB9: 0 | AC9: -0.04 | AD9: -0.58 | AE9: -0.01 | AF9: 0.24 | AG9: -0.01 | AH9: 0.05 | AI9: 0.04 | AJ9: 0.06 | AK9: -0.25 | AL9: 0.15 | AM9: 0.01 | AN9: 0.11 | AO9: 0.24 | AP9: 0 | AQ9: 0.07 | AR9: -0.38 | AS9: 0.08 | AT9: -0.15
A10: 0 | B10: -0.02 | C10: -0.08 | D10: 0.04 | E10: -0.02 | F10: 0.05 | G10: -0.03 | H10: -0.02 | I10: 0.02 | J10: 0.01 | K10: 0.03 | L10: -0.08 | M10: 0.07 | N10: 0 | O10: 0.16 | P10: -0.04 | Q10: -0.02 | R10: -0.28 | S10: 0.27 | T10: -0.07 | U10: 0.45 | V10: 0.51 | W10: -0.16 | X10: -0.25 | Y10: -0.19 | Z10: 0.12 | AA10: -0.05 | AB10: 0 | AC10: -0.08 | AD10: -0.77 | AE10: -0.01 | AF10: 0.24 | AG10: -0.01 | AH10: 0.05 | AI10: 0.04 | AJ10: 0.06 | AK10: -0.25 | AL10: 0.2 | AM10: 0.01 | AN10: 0.15 | AO10: 0.33 | AP10: 0 | AQ10: 0.07 | AR10: -0.38 | AS10: 0.08 | AT10: -0.15
A11: 0.06 | B11: -0.02 | C11: -0.08 | D11: 0.04 | E11: -0.02 | F11: 0.05 | G11: -0.03 | H11: -0.02 | I11: 0.02 | J11: 0.01 | K11: 0.03 | L11: -0.08 | M11: 0.07 | N11: 0 | O11: 0.16 | P11: -0.04 | Q11: -0.02 | R11: -0.28 | S11: 0.27 | T11: -0.07 | U11: 0.45 | V11: 0.51 | W11: -0.16 | X11: -0.25 | Y11: -0.19 | Z11: 0.12 | AA11: -0.05 | AB11: 0 | AC11: -0.04 | AD11: -0.58 | AE11: -0.01 | AF11: 0.24 | AG11: -0.01 | AH11: 0.05 | AI11: 0.04 | AJ11: 0.06 | AK11: -0.25 | AL11: 0.15 | AM11: 0.01 | AN11: 0.11 | AO11: 0.24 | AP11: 0 | AQ11: 0.07 | AR11: -0.38 | AS11: 0.08 | AT11: -0.15
A12: 0.41 | B12: -0.03 | C12: -0.31 | D12: 0.15 | E12: -0.02 | F12: 0.05 | G12: -0.14 | H12: -0.02 | I12: 0.08 | J12: 0.06 | K12: 0.08 | L12: -0.16 | M12: 0.33 | N12: -0.01 | O12: 0.04 | P12: -0.01 | Q12: -0.01 | R12: -0.07 | S12: 0.33 | T12: -0.04 | U12: 0.34 | V12: 0.51 | W12: -0.12 | X12: -0.13 | Y12: -0.19 | Z12: 0.06 | AA12: -0.05 | AB12: 0 | AC12: -0.2 | AD12: -0.19 | AE12: 0 | AF12: 0.06 | AG12: 0 | AH12: 0.02 | AI12: 0.02 | AJ12: 0.09 | AK12: -0.37 | AL12: 0.2 | AM12: 0.01 | AN12: 0.15 | AO12: 0.08 | AP12: 0 | AQ12: 0.04 | AR12: -0.19 | AS12: 0.08 | AT12: -0.12
A13: -0.37 | B13: -0.03 | C13: -0.08 | D13: 0.11 | E13: -0.1 | F13: 0.2 | G13: -0.09 | H13: -0.05 | I13: 0.08 | J13: 0.04 | K13: 0.11 | L13: -0.4 | M13: 0.26 | N13: -0.01 | O13: 0.12 | P13: -0.04 | Q13: -0.01 | R13: -0.28 | S13: 0.27 | T13: -0.07 | U13: 0.56 | V13: 0.38 | W13: -0.16 | X13: -0.19 | Y13: -0.28 | Z13: 0.19 | AA13: -0.07 | AB13: 0.01 | AC13: -0.16 | AD13: -0.77 | AE13: -0.01 | AF13: 0.24 | AG13: -0.02 | AH13: 0.07 | AI13: 0.06 | AJ13: 0.12 | AK13: -0.5 | AL13: 0.2 | AM13: 0.01 | AN13: 0.15 | AO13: 0.33 | AP13: 0 | AQ13: 0.07 | AR13: -0.58 | AS13: 0.08 | AT13: -0.15
... A144: -0.92 | B144: -0.03 | C144: -0.16 | D144: 0.11 | E144: -0.05 | F144: 0.05 | G144: -0.06 | H144: -0.03 | I144: 0.06 | J144: 0.03 | K144: 0.08 | L144: -0.16 | M144: 0.2 | N144: -0.01 | O144: 0.16 | P144: -0.04 | Q144: -0.01 | R144: -0.21 | S144: 0.13 | T144: -0.04 | U144: 0.22 | V144: 0.25 | W144: -0.08 | X144: -0.25 | Y144: -0.19 | Z144: 0.12 | AA144: -0.05 | AB144: 0 | AC144: -0.12 | AD144: -0.58 | AE144: -0.01 | AF144: 0.12 | AG144: -0.01 | AH144: 0.1 | AI144: 0.04 | AJ144: 0.12 | AK144: -0.37 | AL144: 0.2 | AM144: 0.01 | AN144: 0.11 | AO144: 0.16 | AP144: 0 | AQ144: 0.07 | AR144: -0.77 | AS144: 0.08 | AT144: -0.15

Sheet Factor 4
A1: Factor 4: Scope changes / client changes | B1: ='3rd Iteration Dataset'!B1 -> 1.Delay in delivering material to construction site | C1: ='3rd Iteration Dataset'!C1 -> 2.Monopoly of material by some suppliers | D1: ='3rd Iteration Dataset'!D1 -> 3.Prices fluctuation | E1: ='3rd Iteration Dataset'!E1 -> 4.Types of material availability at local market | F1: ='3rd Iteration Dataset'!F1 -> 5.Lack of consultant’s knowledge of available materials | G1: ='3rd Iteration Dataset'!G1 -> 6.Low productivity | H1: ='3rd Iteration Dataset'!H1 -> 7.Poor work execution | I1: ='3rd Iteration Dataset'!I1 -> 8.Shortage of laborers | ... AT1: ='3rd Iteration Dataset'!AT1 -> Relevant working experience | AV1: ='[1]cleaned dataset'!AU1 -> #REF!
A2: 1.66 | B2: -0.19 | C2: -0.27 | D2: -0.14 | E2: -0.18 | F2: -0.12 | G2: 0.06 | H2: 0 | I2: -0.01 | J2: 0.04 | K2: -0.01 | L2: 0.03 | M2: 0.08 | N2: 0.06 | O2: -0.05 | P2: -0.05 | Q2: 0.03 | R2: 0 | S2: -0.2 | T2: -0.11 | U2: -0.09 | V2: 0.1 | W2: 0.24 | X2: 0.12 | Y2: 0.15 | Z2: 0.2 | AA2: 0.06 | AB2: 0.13 | AC2: 0.52 | AD2: -0.08 | AE2: 0.09 | AF2: -0.01 | AG2: 0.24 | AH2: 0.05 | AI2: -0.07 | AJ2: -0.23 | AK2: 0 | AL2: 0.84 | AM2: 0.79 | AN2: 0.8 | AO2: 0.01 | AP2: -0.2 | AQ2: -0.1 | AR2: -0.18 | AS2: -0.27 | AT2: -0.41
A3: 0.96 | B3: -0.38 | C3: -1.33 | D3: -0.43 | E3: -0.37 | F3: -0.35 | G3: 0.12 | H3: 0 | I3: -0.02 | J3: 0.13 | K3: -0.02 | L3: 0.06 | M3: 0.15 | N3: 0.13 | O3: -0.11 | P3: -0.09 | Q3: 0.03 | R3: -0.02 | S3: -0.33 | T3: -0.18 | U3: -0.13 | V3: 0.1 | W3: 0.24 | X3: 0.21 | Y3: 0.15 | Z3: 0.3 | AA3: 0.18 | AB3: 0.27 | AC3: 0.52 | AD3: -0.06 | AE3: 0.36 | AF3: -0.04 | AG3: 0.59 | AH3: 0.07 | AI3: -0.13 | AJ3: -0.45 | AK3: 0.01 | AL3: 0.84 | AM3: 0.79 | AN3: 1.07 | AO3: 0.02 | AP3: -0.1 | AQ3: -0.05 | AR3: -0.24 | AS3: -0.27 | AT3: -0.25
A4: 0.71 | B4: -0.19 | C4: -0.53 | D4: -0.14 | E4: -0.18 | F4: -0.23 | G4: 0.12 | H4: 0 | I4: -0.02 | J4: 0.04 | K4: -0.01 | L4: 0.06 | M4: 0.08 | N4: 0.19 | O4: -0.16 | P4: -0.14 | Q4: 0.07 | R4: -0.01 | S4: -0.13 | T4: -0.07 | U4: -0.06 | V4: 0.05 | W4: 0.18 | X4: 0.08 | Y4: 0.15 | Z4: 0.1 | AA4: 0.12 | AB4: 0.07 | AC4: 0.39 | AD4: -0.08 | AE4: 0.27 | AF4: -0.01 | AG4: 0.24 | AH4: 0.05 | AI4: -0.07 | AJ4: -0.23 | AK4: 0.01 | AL4: 0.56 | AM4: 0.53 | AN4: 0.53 | AO4: 0.01 | AP4: -0.1 | AQ4: -0.05 | AR4: -0.24 | AS4: -0.18 | AT4: -0.33
A5: 1.19 | B5: -0.38 | C5: -0.53 | D5: -0.43 | E5: -0.55 | F5: -0.23 | G5: 0.12 | H5: -0.01 | I5: -0.04 | J5: 0.18 | K5: -0.05 | L5: 0.06 | M5: 0.38 | N5: 0.13 | O5: -0.11 | P5: -0.05 | Q5: 0.03 | R5: 0 | S5: -0.26 | T5: -0.15 | U5: -0.13 | V5: 0.1 | W5: 0.24 | X5: 0.12 | Y5: 0.1 | Z5: 0.2 | AA5: 0.12 | AB5: 0.13 | AC5: 0.39 | AD5: -0.06 | AE5: 0.18 | AF5: -0.02 | AG5: 0.24 | AH5: 0.07 | AI5: -0.07 | AJ5: -0.45 | AK5: 0.01 | AL5: 1.11 | AM5: 1.05 | AN5: 1.07 | AO5: 0.02 | AP5: -0.4 | AQ5: -0.16 | AR5: -0.18 | AS5: -0.27 | AT5: -0.33
A6: 0.79 | B6: -0.19 | C6: -0.53 | D6: -0.14 | E6: -0.18 | F6: -0.23 | G6: 0.12 | H6: 0 | I6: -0.02 | J6: 0.04 | K6: -0.01 | L6: 0.06 | M6: 0.08 | N6: 0.13 | O6: -0.21 | P6: -0.19 | Q6: 0.07 | R6: -0.01 | S6: -0.13 | T6: -0.07 | U6: -0.06 | V6: 0.05 | W6: 0.18 | X6: 0.08 | Y6: 0.2 | Z6: 0.3 | AA6: 0.12 | AB6: 0.07 | AC6: 0.39 | AD6: -0.08 | AE6: 0.27 | AF6: -0.01 | AG6: 0.24 | AH6: 0.05 | AI6: -0.07 | AJ6: -0.23 | AK6: 0.01 | AL6: 0.56 | AM6: 0.53 | AN6: 0.53 | AO6: 0.01 | AP6: -0.1 | AQ6: -0.05 | AR6: -0.24 | AS6: -0.18 | AT6: -0.33
A7: 1.01 | B7: -0.19 | C7: -0.27 | D7: -0.14 | E7: -0.18 | F7: -0.12 | G7: 0.12 | H7: 0 | I7: -0.02 | J7: 0.04 | K7: -0.01 | L7: 0.03 | M7: 0.15 | N7: 0.06 | O7: -0.21 | P7: -0.19 | Q7: 0.14 | R7: -0.02 | S7: -0.26 | T7: -0.15 | U7: -0.13 | V7: 0.1 | W7: 0.24 | X7: 0.17 | Y7: 0.1 | Z7: 0.2 | AA7: 0.12 | AB7: 0.07 | AC7: 0.13 | AD7: -0.06 | AE7: 0.27 | AF7: -0.04 | AG7: 0.24 | AH7: 0.05 | AI7: -0.07 | AJ7: -0.23 | AK7: 0 | AL7: 0.84 | AM7: 0.53 | AN7: 0.8 | AO7: 0.02 | AP7: -0.2 | AQ7: -0.1 | AR7: -0.12 | AS7: -0.27 | AT7: -0.41
A8: 1.81 | B8: -0.19 | C8: -0.27 | D8: -0.14 | E8: -0.18 | F8: -0.12 | G8: 0.06 | H8: 0 | I8: -0.01 | J8: 0.04 | K8: -0.01 | L8: 0.03 | M8: 0.08 | N8: 0.06 | O8: -0.21 | P8: -0.19 | Q8: 0.14 | R8: -0.02 | S8: -0.26 | T8: -0.15 | U8: -0.13 | V8: 0.1 | W8: 0.24 | X8: 0.17 | Y8: 0.1 | Z8: 0.2 | AA8: 0.12 | AB8: 0.07 | AC8: 0.26 | AD8: -0.08 | AE8: 0.27 | AF8: -0.04 | AG8: 0.24 | AH8: 0.05 | AI8: -0.07 | AJ8: -0.23 | AK8: 0.01 | AL8: 1.11 | AM8: 0.79 | AN8: 1.07 | AO8: 0.02 | AP8: -0.2 | AQ8: -0.1 | AR8: -0.12 | AS8: -0.27 | AT8: -0.41
A9: 0.95 | B9: -0.19 | C9: -0.27 | D9: -0.14 | E9: -0.18 | F9: -0.12 | G9: 0.06 | H9: 0 | I9: -0.01 | J9: 0.04 | K9: -0.01 | L9: 0.03 | M9: 0.08 | N9: 0.06 | O9: -0.16 | P9: -0.14 | Q9: 0.1 | R9: -0.02 | S9: -0.26 | T9: -0.15 | U9: -0.13 | V9: 0.1 | W9: 0.24 | X9: 0.17 | Y9: 0.1 | Z9: 0.2 | AA9: 0.12 | AB9: 0.07 | AC9: 0.13 | AD9: -0.06 | AE9: 0.27 | AF9: -0.04 | AG9: 0.24 | AH9: 0.05 | AI9: -0.07 | AJ9: -0.23 | AK9: 0 | AL9: 0.84 | AM9: 0.53 | AN9: 0.8 | AO9: 0.02 | AP9: -0.2 | AQ9: -0.1 | AR9: -0.12 | AS9: -0.27 | AT9: -0.41
